Workbook
Name capa1: Producten!$H$8:$H$15
Name capa2: Producten!$H$42:$H$45
Name capa3: Producten!$H$16:$H$33
Name capa4: Producten!$H$21:$H$33
Name capa5: Producten!$H$34:$H$41
Name capa6: Producten!$H$46:$H$52
Name capa7: Producten!$H$53:$H$56
Name fase1: Productselectie!$B$4:$B$5
Name fase11: Productselectie!$B$4:$E$5
Name merk1: Productselectie!$B$12:$B$13
Name merk11: Productselectie!$B$12:$E$13
Name merk2: Productselectie!$F$12:$F$14
Name merk21: Productselectie!$F$12:$I$14
Name omvo1: Productselectie!$B$21
Name omvo11: Productselectie!$B$21:$E$21
Name omvo2: Productselectie!$F$21
Name omvo21: Productselectie!$F$21:$I$21
Name omvo3: Productselectie!$B$25:$B$26
Name omvo31: Productselectie!$B$25:$E$26
Name omvo4: Productselectie!$F$25
Name omvo41: Productselectie!$F$25:$I$25
Name omvo5: Productselectie!$J$25:$J$26
Name omvo51: Productselectie!$J$25:$M$26
Name ParticulierJaJa: BTW!$S$55:$X$62
Name ParticulierJaNee: BTW!$S$45:$X$52
Name ParticulierNeeJa: BTW!$S$75:$Y$82
Name ParticulierNeeNee: BTW!$S$65:$X$72
Name ZakelijkJaJa: BTW!$S$85:$X$92
Name ZakelijkJaNee: BTW!$S$95:$X$102
Name ZakelijkNeeJa: BTW!$S$115:$X$122
Name ZakelijkNeeNee: BTW!$S$105:$X$112

Sheet Calculator
C2: Rendementscalculator
C3: Versie 67
C5: Klantgegevens
C6: Vul de gegevens van de klant in.
C8: Voor- en achternaam | H8: Jan Modaal
C10: Straat en huisnummer | H10: Hoogstraat 20
AC11: Contract
C12: Postcode en plaats | H12: 3552XM | K12: Utrecht | AC12: Vast
AC13: Variabel
C14: E-mailadres | H14: jan@modaal.nl | AC14: Dynamisch
C16: Telefoonnummer | H16: 0612345678
C18: Stroom
C19: Vul de gegevens van het energiecontract in van de klant.
C21: Overeenkomst
C23: Leverancier | G23: De huidige leverancier van de klant. | R23: Vattenfall
C25: Huidig contract | G25: Het soort contract dat de klant nu heeft. | R25: Variabel
C28: Levering
AC29: Zonnepanelen
C30: Verbruik | G30: De stroom die de klant van het net verbruikt (jaarnota). | R30: 3500 | U30: kWh
C32: Teruglevering | G32: De stroom die de klant teruglevert aan het net (jaarnota). | R32: 2500 | U32: kWh | V32: =IF(ISERROR(1-R36/R34),0,1-R36/R34) -> 0.71428571 | AC32: Aantal zonnepanelen | AD32: 10
C34: Opwek | G34: De stroom die de klant per jaar opwekt (app van zonnepanelen). | R34: 3500 | U34: kWh | AC34: Opwekvermogen per zonnepaneel | AD34: 410 | AE34: Wp
C36: Direct verbruik | G36: De opgewekte stroom die de klant direct verbruikt. | R36: =R34-R32 -> 1000 | U36: kWh | V36: =IF(ISERROR(R36/R34),0,R36/R34) -> 0.28571429 | AC36: Rendementspercentage | AD36: 0.85
C38: Totaal verbruik | G38: De totale hoeveelheid stroom die de klant gebruikt. | R38: =R30+R36 -> 4500 | U38: kWh | AC38: Opwek per jaar | AD38: =AD32*AD34*AD36 -> 3485
C40: Saldo | G40: De stroom die de klant netto inkoopt (+) of teruglevert (-). | R40: =R38-R34 -> 1000 | U40: kWh
C43: Financieel
C45: Vaste leveringskosten | G45: De vaste leveringskosten die de klant betaalt voor stroom | S45: 8.99 | U45: per maand inclusief BTW
C47: Leveringstarief | G47: Het tarief exclusief energiebelasting dat de klant nu betaalt | S47: 0.18 | U47: per kWh inclusief BTW
S48: 0.1
C49: Terugleverkosten | G49: De terugleverkosten die de huidige leverancier rekent. | S49: 0.15 | U49: per kWh inclusief BTW
C51: Terugleververgoeding | G51: De vergoeding die klant ontvangt. | S51: 0.14 | U51: per kWh
C54: Financieel nadeel afschaffen saldering
C56: Oorspronkelijke kosten | G56: Dit betaalde de klant zonder terugleveringskosten | R56: ='financieel nadeel'!G31 -> 411 | U56: per jaar
C58: Huidige kosten | G58: Dit betaalt de klant nu voor stroom. | R58: ='financieel nadeel'!M31 -> 786 | U58: per jaar
C60: Na afschaffen saldering | G60: Dit gaat de klant betalen zonder saldering | R60: ='financieel nadeel'!S31 -> 1168 | U60: per jaar
C62: Financieel nadeel | G62: Hogere kosten door einde saldering (t.o.v. oorspronkelijke kosten). | R62: =R60-R56 -> 757 | U62: per jaar
R63: =R62/12 -> 63.083333 | U63: per maand
C66: Toekomstig stroomverbruik
C67: Nederland is in 2050 volledig van het gas af. Nederlandse huishoudens gaan in de komende jaren 2 tot 4x zoveel stroom verbruiken. Wat zijn de verwachtingen met betrekking tot extra stroomverbruik in de komende jaren?
C69: Van het gas af
C71: Verbruik | G71: Huidig gasverbruik invullen vanaf de jaarnota. | R71: 1200 | U71: m3
C73: Vaste leveringskosten | G73: De vaste leveringskosten die de klant betaalt voor gas. | R73: 5.99 | U73: per maand
C75: Leveringstarief | G75: Het tarief dat de klant betaalt bij de huidige leverancier. | R75: 1.17 | U75: per m3
C77: Jaar overstap | G77: Vanaf wanneer is de klant van het gas af? | R77: 54789 | U77: =IF(ISNUMBER(R77),"","dit is geen geldige datum")
C79: Specificaties
C80: Selecteer de aansluiting, de batterij en de omvormer.
C82: Batterij
Q83: B - Compacte auto | AC83: Zomerfunctie (opslag) | AI83: Winterfunctie (inkoop)
C84: Aansluiting | G84: Deze aansluiting heeft de klant nodig. | R84: 3 fase
C86: Merk | G86: Merk batterij | Q86: AlphaESS Smile 3 fase | V86: =IF(Q86=Productselectie!C7,"",Productselectie!C7) | AC86: Totale opwek per jaar | AD86: =R34 -> 3500 | AE86: kWh | AI86: Totaal verbruik per jaar | AJ86: =Opbrengsten!AR31 -> 4500 | AK86: kWh
C88: Omvormer | G88: Vermogen van de standaard bijgeleverde omvormer. | Q88: 10,0 kW (Hybride) | V88: =IF(V86=Productselectie!G1,V86,IF(Q88=Productselectie!C16,"",Productselectie!C16)) | AC88: Gemiddelde opwek per dag | AD88: =AD86/365 -> 9.5890411 | AE88: kWh | AI88: Gemiddeld verbruik per dag | AJ88: =AJ86/365 -> 12.328767 | AK88: kWh
C90: Batterij | G90: Selecteer de batterij uit de lijst. | M90: AlphaESS Smile3,6 binnen 21,85 (3 Fase) | V90: =IF(V88=Productselectie!G1,V88,IF(M90=Productselectie!C28,"",Productselectie!C28)) | AC90: Opwek factor (percentage van gemiddelde) | AD90: 2.2 | AI90: Verbruik factor (percentage van gemiddelde) | AJ90: 1.6
C92: Capaciteit | G92: De capaciteit van de gekozen thuisbatterij. | R92: =VLOOKUP($M$90,Producten!$H$7:$AA$1007,6,FALSE) -> 21.85 | U92: kWh | AC92: Direct verbruik (van zonnepanelen) | AD92: =R36/365 -> 2.739726 | AE92: kWh | AI92: Direct verbruik (van stroomnet) | AJ92: 0.04
Q93: B - Compacte auto
C94: Efficiëntie | G94: Het percentage van geladen stroom dat ontladen wordt. | R94: =VLOOKUP($M$90,Producten!$H$7:$AA$1007,8,FALSE) -> 0.96 | AC94: Opslag per dag | AD94: =(AD88*AD90)-AD92 -> 18.356164 | AE94: kWh | AI94: Opslag per dag | AJ94: =(AJ88*AJ90)*(1-AJ92) -> 18.936986 | AK94: kWh
Q95: B - Compacte auto
C96: Garantie | G96: Het aantal jaren fabrieksgarantie. | R96: =VLOOKUP($M$90,Producten!$H$7:$AA$1007,12,FALSE) -> 10 | U96: Jaar
Q97: B - Compacte auto
C98: Cycli | G98: Het gegarandeerde aantal cycli van de batterij. | R98: =VLOOKUP($M$90,Producten!$H$7:$AA$1007,10,FALSE) -> 10000 | U98: =VLOOKUP($M$90,Producten!$H$7:$AA$1007,9,FALSE) -> 10000
Q99: B - Compacte auto
C100: Restcapaciteit | G100: De resterende capaciteit na het gegarandeerde aantal cycli. | R100: =VLOOKUP($M$90,Producten!$H$7:$AA$1007,11,FALSE) -> 0.7
Q101: B - Compacte auto
C102: Omvormer | G102: Vermogen van de standaard bijgeleverde omvormer. | R102: =IF(Q88=Productselectie!B26,20,VLOOKUP($M$90,Producten!$H$7:$AA$1007,13,FALSE)) -> 10 | U102: kW
C104: Noodstroom | G104: Meegeleverde noodstroomvoorziening. | R104: =VLOOKUP($M$90,Producten!$H$7:$AA$1007,20,FALSE) -> Basis
C107: Gebruik
C108: Geef aan op welke manier de klant de thuisbatterij gaat inzetten.
C110: Installatiedatum | G110: De datum waarop de batterij wordt geïnstalleerd. | R110: 45992 | U110: =IF(ISNUMBER(R110),"","dit is geen geldige datum")
C112: Nieuwe leverancier | G112: De nieuwe energieleverancier van de klant. | R112: Frank Energie
C114: Instelling | G114: De instelling van de batterij tot einde saldering. | P114: Actief handelen | U114: =Keuzemenu!R31 -> 1.5 | V114: cycli per dag
C116: Toekomstige instelling | G116: De instelling van de batterij in de toekomst. | P116: Actief handelen | U116: =Keuzemenu!T31 -> 1.5 | V116: cycli per dag
C118: Ingangsjaar | G118: Het jaar waarop de toekomstige instelling van toepassing wordt | R118: 2030
C120: Kosten
C121: Vul de eenmalige en doorlopende kosten in die de klant heeft voor de thuisbatterij.
C123: Eenmalige kosten
Q124: B - Compacte auto | AD124: E - Prestigewagen | AE124: 0.4
C125: Pakketprijs | G125: Aankoop batterij, inclusief installatie en services. | R125: =VLOOKUP($M$90,Producten!$H$7:$AA$1007,14,FALSE) -> 14999 | U125: inclusief BTW
C127: Meerkosten opties | G127: Kosten voor opties (bijvoorbeeld noodstroomvoorziening). | R127: 0 | U127: inclusief BTW
C129: Meerwerk | G129: Meerwerkkosten (bijvoorbeeld meterkast of graafwerk). | R129: 0 | U129: eenmalig
C131: Omvormer | G131: Kosten voor 20 kW omvormer Alpha ESS. | R131: =Productselectie!C17 -> 0 | U131: eenmalig
C133: Overstapboete | G133: Eventuele boete voor overstap naar een dynamisch contract. | R133: 0 | U133: eenmalig
T134: =SUM(R125:T133) -> 14999
C135: BTW teruggave
Q136: B - Compacte auto | AD136: E - Prestigewagen | AE136: 0.4
C137: Particulier of zakelijk | G137: Koopt de klant de thuisbatterij particulier of zakelijk? | R137: Particulier
C139: BTW teruggave | G139: Geef aan of de klant BTW terugontvangt. | R139: Ja
C141: KOR | G141: Gebruikt de klant al KOR voor zonnepanelen? | R141: Nee
C144: BTW bedrag | G144: =BTW!E45 -> € 2430 minus € 15 per kWh capaciteit (€ 328). | S144: =VLOOKUP(BTW!W8,BTW!W17:X24,2,FALSE) -> 2102
G145: =BTW!E46
G146: =BTW!E47
G147: =BTW!E48
G148: =BTW!E49
G149: =BTW!E50
G150: =BTW!E51
C153: Investering | G153: =IF(BTW!V10=0,"De eenmalige investering voor de klant, exclusief teruggave BTW.","De eenmalige investering voor de klant, inclusief teruggave BTW.") -> De eenmalige investering voor de klant, inclusief teruggave BTW. | R153: =R125+R127+R129+R131+R133-BTW!V12 -> 12897
C156: Jaarlijkse kosten
C158: Aansluiting | G158: Extra kosten voor zwaardere aansluiting. | R158: 0 | U158: per jaar
C160: Onderhoud | G160: Minimaal elke 2 jaar om volledige garantie te behouden. | R160: 0 | U160: per jaar
C162: Financiering
C163: Vul alle informatie in met betrekking tot de financiering.
C165: Financieringsbedrag | F165: Bedrag dat de klant wil financieren. | R165: 0
C167: Looptijd | F167: Maximale looptijd 20 jaar. | R167: 10 | U167: jaar
...

Sheet financieel nadeel
A2: Contract | C2: Verbruik | F2: Leveringstarief | K2: Energiebelasting | O2: Leveringstarief
A3: =Calculator!R25 -> Variabel | C3: =Calculator!R30 -> 3500 | D3: kWh | F3: exclusief energiebelasting | O3: inclusief energiebelasting
G4: =Calculator!S47 -> 0.18 | H4: per kWh | K4: =Jaargegevens!M9 -> 0.12286 | L4: per kWh | O4: =G4+K4 -> 0.30286 | P4: per kWh
C6: Teruglevering | F6: Terugleververgoeding | K6: Terugleververgoeding | O6: Terugleverkosten | S6: Vaste leveringskosten
C7: =Calculator!R32 -> 2500 | D7: kWh | F7: (boven saldering) | K7: (bij saldering met verbruik) | O7: =IF(A3="Dynamisch",0,Calculator!S49) -> 0.15 | P7: per kWh | S7: =Calculator!S45 -> 8.99 | T7: per maand
G8: =IF(A3="Dynamisch",0,Calculator!S51) -> 0.14 | H8: per kWh | K8: =O4 -> 0.30286 | L8: per kWh
C10: Na afschaffing saldering wordt uitgegaan van een teruglevergoeding gelijk aan terugleverkosten In de berekening beiden € 0,00)
G13: Oorspronkelijk kosten | M13: Huidige kosten | S13: na afschaffing saldering
A15: Verbruik | C15: =C3 -> 3500 | D15: x | E15: =G4 -> 0.18 | F15: = | G15: =ROUND(C15*E15,0) -> 630 | I15: =C15 -> 3500 | J15: x | K15: =E15 -> 0.18 | L15: = | M15: =ROUND(I15*K15,0) -> 630 | O15: =I15 -> 3500 | P15: x | Q15: =K15 -> 0.18 | R15: = | S15: =ROUND(O15*Q15,0) -> 630
A17: Teruglevering (saldering) | C17: =MIN(C7,C15) -> 2500 | D17: x | E17: =G4 -> 0.18 | F17: = | G17: =-ROUND(C17*E17,0) -> -450 | I17: =C17 -> 2500 | J17: x | K17: =E17 -> 0.18 | L17: = | M17: =-ROUND(I17*K17,0) -> -450 | P17: x | Q17: =K17 -> 0.18 | R17: = | S17: =-ROUND(O17*Q17,0) -> 0
C18: - | G18: - | I18: - | M18: - | S18: -
A19: Per saldo | C19: =C15-C17 -> 1000 | G19: =SUM(G14:G18) -> 180 | I19: =I15-I17 -> 1000 | M19: =SUM(M14:M18) -> 180 | S19: =SUM(S14:S18) -> 630
A21: Energiebelasting | C21: =C19 -> 1000 | D21: x | E21: =K4 -> 0.12286 | F21: = | G21: =ROUND(C21*E21,0) -> 123 | I21: =I19 -> 1000 | J21: x | K21: =E21 -> 0.12286 | L21: = | M21: =ROUND(I21*K21,0) -> 123 | O21: =O15 -> 3500 | P21: x | Q21: =K21 -> 0.12286 | R21: = | S21: =ROUND(O21*Q21,0) -> 430
A23: Teruglevering (boven saldering) | C23: =C7-C17 -> 0 | D23: x | E23: =G8 -> 0.14 | F23: = | G23: =-ROUND(C23*E23,0) -> 0 | I23: =C23 -> 0 | J23: x | K23: =E23 -> 0.14 | L23: = | M23: =-ROUND(I23*K23,0) -> 0 | O23: =C7 -> 2500 | P23: x | Q23: 0 | R23: = | S23: =-ROUND(O23*Q23,0) -> 0
A25: Terugleverkosten | C25: =C7 -> 2500 | D25: x | E25: 0 | F25: = | G25: =ROUND(C25*E25,0) -> 0 | I25: =C25 -> 2500 | J25: x | K25: =O7 -> 0.15 | L25: = | M25: =ROUND(I25*K25,0) -> 375 | O25: =I25 -> 2500 | P25: x | Q25: =Q23 -> 0 | R25: = | S25: =ROUND(O25*Q25,0) -> 0
G26: - | M26: - | S26: -
G27: =SUM(G18:G26) -> 303 | M27: =SUM(M18:M26) -> 678 | S27: =SUM(S18:S26) -> 1060
A29: Vaste leveringskosten | C29: 12 | D29: x | E29: =S7 -> 8.99 | F29: = | G29: =ROUND(C29*E29,0) -> 108 | I29: =C29 -> 12 | J29: x | K29: =E29 -> 8.99 | L29: = | M29: =ROUND(I29*K29,0) -> 108 | O29: =I29 -> 12 | P29: x | Q29: =K29 -> 8.99 | R29: = | S29: =ROUND(O29*Q29,0) -> 108
G30: - | M30: - | S30: -
G31: =SUM(G26:G30) -> 411 | M31: =SUM(M26:M30) -> 786 | S31: =SUM(S26:S30) -> 1168
G32: = | M32: = | S32: =

Sheet Productselectie
B1: Keuze-menu fase | F1: tekst na wijziging eerdere selectie | G1: maak andere keuze
B3: Fase | C3: Kosten
B4: 1 fase | C4: 0 | D4: merk1
B5: 3 fase | C5: 0 | D5: merk2
C6: =VLOOKUP(Calculator!R84,fase11,3) -> merk2 | D6: =CONCATENATE(C6,"1") -> merk21
C7: =IF(ISERROR(VLOOKUP(Calculator!Q86,INDIRECT(Productselectie!C6),1,FALSE)),G1,VLOOKUP(Calculator!Q86,INDIRECT(Productselectie!C6),1,FALSE)) -> AlphaESS Smile 3 fase
B9: Keuzemenu's merk
B11: =B4 -> 1 fase | C11: Kosten | F11: =B5 -> 3 fase | G11: Kosten
B12: AlphaESS Smile 1 fase | C12: 0 | D12: omvo1 | F12: AlphaESS Smile 3 fase | G12: 0 | H12: omvo3
B13: HYXI HYX 1 fase | C13: 0 | D13: omvo2 | F13: AplhaESS Storion 3 fase | G13: 0 | H13: omvo4
F14: HYXI HYX 3 fase | G14: 0 | H14: omvo5
C15: =VLOOKUP(Calculator!Q86,INDIRECT(D6),3) -> omvo3 | D15: =CONCATENATE(C15,"1") -> omvo31
C16: =IF(ISERROR(VLOOKUP(Calculator!Q88,INDIRECT(Productselectie!C15),1,FALSE)),G1,VLOOKUP(Calculator!Q88,INDIRECT(Productselectie!C15),1,FALSE)) -> 10,0 kW (Hybride)
C17: =VLOOKUP(Calculator!Q88,INDIRECT(Productselectie!D15),2) -> 0
B18: Keuzemenu's omvormer
B20: =B12 -> AlphaESS Smile 1 fase | C20: Kosten | F20: =B13 -> HYXI HYX 1 fase | G20: Kosten
B21: 5,0 kW (Hybride) | C21: 0 | D21: capa1 | F21: 5,0 kW (Hybride) | G21: 0 | H21: capa2
B24: =F12 -> AlphaESS Smile 3 fase | C24: Kosten | F24: =F13 -> AplhaESS Storion 3 fase | G24: Kosten | J24: =F14 -> HYXI HYX 3 fase | K24: Kosten
B25: 10,0 kW (Hybride) | C25: 0 | D25: capa3 | F25: 30,0 - 50,0 kW (Hybride) | G25: 0 | H25: capa5 | J25: 10,0 kW (Hybride) | K25: 0 | L25: capa6
B26: 20,0 kW (Hybride) | C26: 2000 | D26: capa4 | J26: 6,0 - 13,0 kW (All-in-One) | K26: 0 | L26: capa7
C27: =VLOOKUP(Calculator!Q88,INDIRECT(D15),3) -> capa3
C28: =IF(ISERROR(VLOOKUP(Calculator!M90,INDIRECT(Productselectie!C27),1,FALSE)),G1,VLOOKUP(Calculator!M90,INDIRECT(Productselectie!C27),1,FALSE)) -> AlphaESS Smile3,6 binnen 21,85 (3 Fase)

Sheet Producten
H4: =I4&" "&M4&" ("&N4&")" -> AlphaESS 20 kW Omvormer (3 Fase) | I4: AlphaESS | M4: 20 kW Omvormer | N4: 3 Fase | T4: 20 | U4: 2000 | V4: 2000 | W4: 2000 | X4: 2000 | Y4: 2000
D6: capa | W6: factuur | X6: factuur | Y6: factuur | Z6: factuur
A7: 1 | B7: 2 | C7: 3 | D7: 4 | E7: 5 | F7: 6 | G7: 7 | H7: Product | I7: Merk | J7: Model | K7: Module | L7: Aantal | M7: Capaciteit | N7: Aansluiting | O7: RTE | P7: Cycles | Q7: Cycles Tonen | R7: Restcapaciteit | S7: Garantie | T7: Omvormer | U7: Prijs in BTW | V7: Prijs Ex BTW | W7: Batterijen | X7: Installatie | Y7: BTW teruggave | Z7: buiten BTW | AA7: Noodstroom | AB7: Prijs per kWh | AC7: IP Omvormer | AD7: IP Batterij | AE7: Geschikt Buiten | AF7: Breedte (mm) | AG7: Diepte (mm) | AH7: Hoogte (mm) | AI7: Totale Hoogte (mm) | AJ7: Gewicht Module (kg) | AK7: Max modules in toren | AL7: Aansturing | AM7: Bevestiging | AN7: Opmerkingen | AO7: BTW per saldo
A8: 1 | H8: =I8&" "&" "&J8&" "&M8&" ("&N8&")" -> AlphaESS Smile3,6 binnen 3,64 (1 Fase) | I8: AlphaESS | J8: Smile3,6 binnen | K8: =(46/12)*0.95 -> 3.6416667 | L8: 1 | M8: =ROUND(K8*L8,2) -> 3.64 | N8: 1 Fase | O8: 0.96 | P8: 10000 | Q8: =P8 -> 10000 | R8: 0.7 | S8: 10 | T8: 5 | U8: 7499 | V8: =U8/1.21 -> 6197.5207 | W8: =U8-X8 -> 6499 | X8: 1000 | Y8: =U8-Z8 -> 7499 | AA8: Basis | AB8: =U8/M8 -> 2060.1648 | AC8: IP65 | AD8: IP21 | AE8: Nee | AF8: 610 | AG8: 213 | AH8: 435 | AI8: 851 | AJ8: 39.2 | AK8: 4 | AN8: Basis configuratie, alleen binnen IP21
A9: 1 | H9: =I9&" "&" "&J9&" "&M9&" ("&N9&")" -> AlphaESS Smile3,6 binnen 7,28 (1 Fase) | I9: AlphaESS | J9: Smile3,6 binnen | K9: =(46/12)*0.95 -> 3.6416667 | L9: 2 | M9: =ROUND(K9*L9,2) -> 7.28 | N9: 1 Fase | O9: 0.96 | P9: 10000 | Q9: =P9 -> 10000 | R9: 0.7 | S9: 10 | T9: 5 | U9: 8999 | V9: =U9/1.21 -> 7437.1901 | W9: =U9-X9 -> 7999 | X9: 1000 | Y9: =U9-Z9 -> 8999 | AA9: Basis | AB9: =U9/M9 -> 1236.1264 | AC9: IP65 | AD9: IP21 | AE9: Nee | AF9: 610 | AG9: 213 | AH9: 435 | AI9: 1286 | AJ9: 39.2 | AK9: 4
A10: 1 | H10: =I10&" "&" "&J10&" "&M10&" ("&N10&")" -> AlphaESS Smile3,6 binnen 10,93 (1 Fase) | I10: AlphaESS | J10: Smile3,6 binnen | K10: =(46/12)*0.95 -> 3.6416667 | L10: 3 | M10: =ROUND(K10*L10,2) -> 10.93 | N10: 1 Fase | O10: 0.96 | P10: 10000 | Q10: =P10 -> 10000 | R10: 0.7 | S10: 10 | T10: 5 | U10: 10499 | V10: =U10/1.21 -> 8676.8595 | W10: =U10-X10 -> 9499 | X10: 1000 | Y10: =U10-Z10 -> 10499 | AA10: Basis | AB10: =U10/M10 -> 960.56725 | AC10: IP65 | AD10: IP21 | AE10: Nee | AF10: 610 | AG10: 213 | AH10: 435 | AI10: 1721 | AJ10: 39.2 | AK10: 4
A11: 1 | H11: =I11&" "&" "&J11&" "&M11&" ("&N11&")" -> AlphaESS Smile3,6 binnen 14,57 (1 Fase) | I11: AlphaESS | J11: Smile3,6 binnen | K11: =(46/12)*0.95 -> 3.6416667 | L11: 4 | M11: =ROUND(K11*L11,2) -> 14.57 | N11: 1 Fase | O11: 0.96 | P11: 10000 | Q11: 10000 | R11: 0.7 | S11: 10 | T11: 5 | U11: 11999 | V11: =U11/1.21 -> 9916.5289 | W11: =U11-X11 -> 10999 | X11: 1000 | Y11: =U11-Z11 -> 11999 | AA11: Basis | AB11: =U11/M11 -> 823.54152 | AC11: IP65 | AD11: IP21 | AE11: Nee | AF11: 610 | AG11: 213 | AH11: 435 | AI11: 2156 | AJ11: 39.2 | AK11: 4 | AN11: Maximum voor 1-fase systeem
A12: 1 | H12: =I12&" "&" "&J12&" "&M12&" ("&N12&")" -> AlphaESS Smile9,3 buiten 9,3 (1 Fase) | I12: AlphaESS | J12: Smile9,3 buiten | K12: 9.3 | L12: 1 | M12: =ROUND(K12*L12,2) -> 9.3 | N12: 1 Fase | O12: 0.98 | P12: 10000 | Q12: 10000 | R12: 0.7 | S12: 10 | T12: 10 | U12: =5999+L12*3000 -> 8999 | V12: =U12/1.21 -> 7437.1901 | W12: =U12-X12 -> 7999 | X12: 1000 | Y12: =U12-Z12 -> 8999 | AA12: Basis | AB12: =U12/M12 -> 967.63441 | AC12: IP65 | AD12: IP65 | AE12: Ja | AF12: 610 | AG12: 210 | AH12: 634 | AI12: 850 | AJ12: 81 | AK12: 3 | AN12: IP65 batterij = buitengeschikt, vanaf hier 1 fase
A13: 1 | H13: =I13&" "&" "&J13&" "&M13&" ("&N13&")" -> AlphaESS Smile9,3 buiten 18,6 (1 Fase) | I13: AlphaESS | J13: Smile9,3 buiten | K13: 9.3 | L13: 2 | M13: =ROUND(K13*L13,2) -> 18.6 | N13: 1 Fase | O13: 0.98 | P13: 10000 | Q13: 10000 | R13: 0.7 | S13: 10 | T13: 10 | U13: =5999+L13*3000 -> 11999 | V13: =U13/1.21 -> 9916.5289 | W13: =U13-X13 -> 10999 | X13: 1000 | Y13: =U13-Z13 -> 11999 | AA13: Basis | AB13: =U13/M13 -> 645.10753 | AC13: IP65 | AD13: IP65 | AE13: Ja | AF13: 610 | AG13: 210 | AH13: 634 | AI13: 1068 | AJ13: 81 | AK13: 3
A14: 1 | H14: =I14&" "&" "&J14&" "&M14&" ("&N14&")" -> AlphaESS Smile9,3 buiten 27,9 (1 Fase) | I14: AlphaESS | J14: Smile9,3 buiten | K14: 9.3 | L14: 3 | M14: =ROUND(K14*L14,2) -> 27.9 | N14: 1 Fase | O14: 0.98 | P14: 10000 | Q14: 10000 | R14: 0.7 | S14: 10 | T14: 10 | U14: =5999+L14*3000 -> 14999 | V14: =U14/1.21 -> 12395.868 | W14: =U14-X14 -> 13999 | X14: 1000 | Y14: =U14-Z14 -> 13999 | Z14: 1000 | AA14: Basis | AB14: =U14/M14 -> 537.59857 | AC14: IP65 | AD14: IP65 | AE14: Ja | AF14: 610 | AG14: 210 | AH14: 634 | AI14: 1286 | AJ14: 81 | AK14: 3 | AN14: BTW grens €13.999 overschreden, factuur gesplitst
A15: 1 | H15: =I15&" "&" "&J15&" "&M15&" ("&N15&")" -> AlphaESS Smile9,3 buiten 37,2 (1 Fase) | I15: AlphaESS | J15: Smile9,3 buiten | K15: 9.3 | L15: 4 | M15: =ROUND(K15*L15,2) -> 37.2 | N15: 1 Fase | O15: 0.98 | P15: 10000 | Q15: 10000 | R15: 0.7 | S15: 10 | T15: 10 | U15: =5999+L15*3000 -> 17999 | V15: =U15/1.21 -> 14875.207 | W15: =U15-X15 -> 16999 | X15: 1000 | Y15: =U15-Z15 -> 17999 | AA15: Basis | AB15: =U15/M15 -> 483.84409 | AC15: IP65 | AD15: IP65 | AE15: Ja | AF15: 1420 | AG15: 210 | AH15: 634 | AI15: 1684 | AJ15: 81 | AK15: 3 | AN15: Grootste 9.3 opstelling 1-fase | AO15: =Y15-Y15/1.21-5*15*M15-4*50 -> 133.79339
C16: 3 | H16: =I16&" "&" "&J16&" "&M16&" ("&N16&")" -> AlphaESS Smile3,6 binnen 3,64 (3 Fase) | I16: AlphaESS | J16: Smile3,6 binnen | K16: =(46/12)*0.95 -> 3.6416667 | L16: 1 | M16: =ROUND(K16*L16,2) -> 3.64 | N16: 3 Fase | O16: 0.96 | P16: 10000 | Q16: =P16 -> 10000 | R16: 0.7 | S16: 10 | T16: 10 | U16: 7499 | V16: =U16/1.21 -> 6197.5207 | W16: =U16-X16 -> 6499 | X16: 1000 | Y16: =U16-Z16 -> 7499 | AA16: Basis | AB16: =U16/M16 -> 2060.1648 | AC16: IP65 | AD16: IP21 | AE16: Nee | AF16: 610 | AG16: 213 | AH16: 435 | AI16: 851 | AJ16: 39.2 | AK16: 4 | AN16: 3 fase 3,6 kWh modules, flexibel in opbouw
C17: 3 | H17: =I17&" "&" "&J17&" "&M17&" ("&N17&")" -> AlphaESS Smile3,6 binnen 7,28 (3 Fase) | I17: AlphaESS | J17: Smile3,6 binnen | K17: =(46/12)*0.95 -> 3.6416667 | L17: 2 | M17: =ROUND(K17*L17,2) -> 7.28 | N17: 3 Fase | O17: 0.96 | P17: 10000 | Q17: =P17 -> 10000 | R17: 0.7 | S17: 10 | T17: 10 | U17: 8999 | V17: =U17/1.21 -> 7437.1901 | W17: =U17-X17 -> 7999 | X17: 1000 | Y17: =U17-Z17 -> 8999 | AA17: Basis | AB17: =U17/M17 -> 1236.1264 | AC17: IP65 | AD17: IP21 | AE17: Nee | AF17: 610 | AG17: 213 | AH17: 435 | AI17: 1286 | AJ17: 39.2 | AK17: 4
C18: 3 | H18: =I18&" "&" "&J18&" "&M18&" ("&N18&")" -> AlphaESS Smile3,6 binnen 10,93 (3 Fase) | I18: AlphaESS | J18: Smile3,6 binnen | K18: =(46/12)*0.95 -> 3.6416667 | L18: 3 | M18: =ROUND(K18*L18,2) -> 10.93 | N18: 3 Fase | O18: 0.96 | P18: 10000 | Q18: =P18 -> 10000 | R18: 0.7 | S18: 10 | T18: 10 | U18: 10499 | V18: =U18/1.21 -> 8676.8595 | W18: =U18-X18 -> 9499 | X18: 1000 | Y18: =U18-Z18 -> 10499 | AA18: Basis | AB18: =U18/M18 -> 960.56725 | AC18: IP65 | AD18: IP21 | AE18: Nee | AF18: 610 | AG18: 213 | AH18: 435 | AI18: 1721 | AJ18: 39.2 | AK18: 4
C19: 3 | H19: =I19&" "&" "&J19&" "&M19&" ("&N19&")" -> AlphaESS Smile3,6 binnen 14,57 (3 Fase) | I19: AlphaESS | J19: Smile3,6 binnen | K19: =(46/12)*0.95 -> 3.6416667 | L19: 4 | M19: =ROUND(K19*L19,2) -> 14.57 | N19: 3 Fase | O19: 0.96 | P19: 10000 | Q19: =P19 -> 10000 | R19: 0.7 | S19: 10 | T19: 10 | U19: 11999 | V19: =U19/1.21 -> 9916.5289 | W19: =U19-X19 -> 10999 | X19: 1000 | Y19: =U19-Z19 -> 11999 | AA19: Basis | AB19: =U19/M19 -> 823.54152 | AC19: IP65 | AD19: IP21 | AE19: Nee | AF19: 610 | AG19: 213 | AH19: 435 | AI19: 2156 | AJ19: 39.2 | AK19: 4
C20: 3 | H20: =I20&" "&" "&J20&" "&M20&" ("&N20&")" -> AlphaESS Smile3,6 binnen 18,21 (3 Fase) | I20: AlphaESS | J20: Smile3,6 binnen | K20: =(46/12)*0.95 -> 3.6416667 | L20: 5 | M20: =ROUND(K20*L20,2) -> 18.21 | N20: 3 Fase | O20: 0.96 | P20: 10000 | Q20: =P20 -> 10000 | R20: 0.7 | S20: 10 | T20: 10 | U20: 13499 | V20: =U20/1.21 -> 11156.198 | W20: =U20-X20 -> 12499 | X20: 1000 | Y20: =U20-Z20 -> 13499 | AA20: Basis | AB20: =U20/M20 -> 741.29599 | AC20: IP65 | AD20: IP21 | AE20: Nee | AF20: 1420 | AG20: 213 | AH20: 435 | AI20: 1305 | AJ20: 39.2 | AK20: 4 | AN20: Dubbele rack vanaf hier
C21: 3 | D21: 4 | H21: =I21&" "&" "&J21&" "&M21&" ("&N21&")" -> AlphaESS Smile3,6 binnen 21,85 (3 Fase) | I21: AlphaESS | J21: Smile3,6 binnen | K21: =(46/12)*0.95 -> 3.6416667 | L21: 6 | M21: =ROUND(K21*L21,2) -> 21.85 | N21: 3 Fase | O21: 0.96 | P21: 10000 | Q21: =P21 -> 10000 | R21: 0.7 | S21: 10 | T21: 10 | U21: 14999 | V21: =U21/1.21 -> 12395.868 | W21: =U21-X21 -> 13999 | X21: 1000 | Y21: =U21-Z21 -> 13999 | Z21: 1000 | AA21: Basis | AB21: =U21/M21 -> 686.45309 | AC21: IP65 | AD21: IP21 | AE21: Nee | AF21: 1420 | AG21: 213 | AH21: 435 | AI21: 1721 | AJ21: 39.2 | AK21: 4 | AN21: BTW grens €13.999 overschreden, factuur gesplitst
C22: 3 | D22: 4 | H22: =I22&" "&" "&J22&" "&M22&" ("&N22&")" -> AlphaESS Smile3,6 binnen 29,13 (3 Fase) | I22: AlphaESS | J22: Smile3,6 binnen | K22: =(46/12)*0.95 -> 3.6416667 | L22: 8 | M22: =ROUND(K22*L22,2) -> 29.13 | N22: 3 Fase | O22: 0.96 | P22: 10000 | Q22: =P22 -> 10000 | R22: 0.7 | S22: 10 | T22: 10 | U22: 17999 | V22: =U22/1.21 -> 14875.207 | W22: =U22-X22 -> 16999 | X22: 1000 | Y22: =U22-Z22 -> 17999 | AA22: Basis | AB22: =U22/M22 -> 617.88534 | AC22: IP65 | AD22: IP21 | AE22: Nee | AF22: 1420 | AG22: 213 | AH22: 435 | AI22: 2156 | AJ22: 39.2 | AK22: 4 | AN22: 8 modules dubbele rack | AO22: =Y22-Y22/1.21-5*15*M22-4*50 -> 739.04339
C23: 3 | D23: 4 | H23: =I23&" "&" "&J23&" "&M23&" ("&N23&")" -> AlphaESS Smile3,6 binnen 36,42 (3 Fase) | I23: AlphaESS | J23: Smile3,6 binnen | K23: =(46/12)*0.95 -> 3.6416667 | L23: 10 | M23: =ROUND(K23*L23,2) -> 36.42 | N23: 3 Fase | O23: 0.96 | P23: 10000 | Q23: =P23 -> 10000 | R23: 0.7 | S23: 10 | T23: 10 | U23: 20999 | V23: =U23/1.21 -> 17354.545 | W23: =U23-X23 -> 19999 | X23: 1000 | Y23: =U23-Z23 -> 20999 | AA23: Basis | AB23: =U23/M23 -> 576.5788 | AC23: IP65 | AD23: IP21 | AE23: Nee | AF23: 2230 | AG23: 213 | AH23: 435 | AI23: 1740 | AJ23: 39.2 | AK23: 4 | AN23: Triple rack | AO23: =Y23-Y23/1.21-5*15*M23-4*50 -> 712.95455
C24: 3 | D24: 4 | H24: =I24&" "&" "&J24&" "&M24&" ("&N24&")" -> AlphaESS Smile3,6 binnen 43,7 (3 Fase) | I24: AlphaESS | J24: Smile3,6 binnen | K24: =(46/12)*0.95 -> 3.6416667 | L24: 12 | M24: =ROUND(K24*L24,2) -> 43.7 | N24: 3 Fase | O24: 0.96 | P24: 10000 | Q24: =P24 -> 10000 | R24: 0.7 | S24: 10 | T24: 10 | U24: 23999 | V24: =U24/1.21 -> 19833.884 | W24: =U24-X24 -> 22999 | X24: 1000 | Y24: =U24-Z24 -> 23999 | AA24: Basis | AB24: =U24/M24 -> 549.1762 | AC24: IP65 | AD24: IP21 | AE24: Nee | AF24: 2230 | AG24: 213 | AH24: 435 | AI24: 2156 | AJ24: 39.2 | AK24: 4 | AN24: Grootste 3.6kWh opstelling | AO24: =Y24-Y24/1.21-5*15*M24-4*50 -> 687.6157
C25: 3 | D25: 4 | H25: =I25&" "&" "&J25&" "&M25&" ("&N25&")" -> AlphaESS Smile9,3 buiten 9,3 (3 Fase) | I25: AlphaESS | J25: Smile9,3 buiten | K25: 9.3 | L25: 1 | M25: =ROUND(K25*L25,2) -> 9.3 | N25: 3 Fase | O25: 0.98 | P25: 10000 | Q25: 10000 | R25: 0.7 | S25: 10 | T25: 10 | U25: =5999+L25*3000 -> 8999 | V25: =U25/1.21 -> 7437.1901 | W25: =U25-X25 -> 7999 | X25: 1000 | Y25: =U25-Z25 -> 8999 | AA25: Basis | AB25: =U25/M25 -> 967.63441 | AC25: IP65 | AD25: IP65 | AE25: Ja | AF25: 610 | AG25: 210 | AH25: 634 | AI25: 850 | AJ25: 81 | AK25: 3 | AN25: Goede specs voor de prijs
C26: 3 | D26: 4 | H26: =I26&" "&" "&J26&" "&M26&" ("&N26&")" -> AlphaESS Smile9,3 buiten 18,6 (3 Fase) | I26: AlphaESS | J26: Smile9,3 buiten | K26: 9.3 | L26: 2 | M26: =ROUND(K26*L26,2) -> 18.6 | N26: 3 Fase | O26: 0.98 | P26: 10000 | Q26: 10000 | R26: 0.7 | S26: 10 | T26: 10 | U26: =5999+L26*3000 -> 11999 | V26: =U26/1.21 -> 9916.5289 | W26: =U26-X26 -> 10999 | X26: 1000 | Y26: =U26-Z26 -> 11999 | AA26: Basis | AB26: =U26/M26 -> 645.10753 | AC26: IP65 | AD26: IP65 | AE26: Ja | AF26: 610 | AG26: 210 | AH26: 634 | AI26: 1068 | AJ26: 81 | AK26: 3
C27: 3 | D27: 4 | H27: =I27&" "&" "&J27&" "&M27&" ("&N27&")" -> AlphaESS Smile9,3 buiten 27,9 (3 Fase) | I27: AlphaESS | J27: Smile9,3 buiten | K27: 9.3 | L27: 3 | M27: =ROUND(K27*L27,2) -> 27.9 | N27: 3 Fase | O27: 0.98 | P27: 10000 | Q27: 10000 | R27: 0.7 | S27: 10 | T27: 10 | U27: =5999+L27*3000 -> 14999 | V27: =U27/1.21 -> 12395.868 | W27: =U27-X27 -> 13999 | X27: 1000 | Y27: =U27-Z27 -> 13999 | Z27: 1000 | AA27: Basis | AB27: =U27/M27 -> 537.59857 | AC27: IP65 | AD27: IP65 | AE27: Ja | AF27: 610 | AG27: 210 | AH27: 634 | AI27: 1286 | AJ27: 81 | AK27: 3 | AN27: BTW grens €13.999 overschreden, factuur gesplitst
C28: 3 | D28: 4 | H28: =I28&" "&" "&J28&" "&M28&" ("&N28&")" -> AlphaESS Smile9,3 buiten 37,2 (3 Fase) | I28: AlphaESS | J28: Smile9,3 buiten | K28: 9.3 | L28: 4 | M28: =ROUND(K28*L28,2) -> 37.2 | N28: 3 Fase | O28: 0.98 | P28: 10000 | Q28: 10000 | R28: 0.7 | S28: 10 | T28: 10 | U28: =5999+L28*3000 -> 17999 | V28: =U28/1.21 -> 14875.207 | W28: =U28-X28 -> 16999 | X28: 1000 | Y28: =U28-Z28 -> 17999 | AA28: Basis | AB28: =U28/M28 -> 483.84409 | AC28: IP65 | AD28: IP65 | AE28: Ja | AF28: 1420 | AG28: 210 | AH28: 634 | AI28: 1684 | AJ28: 81 | AK28: 3 | AN28: Dubbele rack | AO28: =Y28-Y28/1.21-5*15*M28-4*50 -> 133.79339
C29: 3 | D29: 4 | H29: =I29&" "&" "&J29&" "&M29&" ("&N29&")" -> AlphaESS Smile9,3 buiten 46,5 (3 Fase) | I29: AlphaESS | J29: Smile9,3 buiten | K29: 9.3 | L29: 5 | M29: =ROUND(K29*L29,2) -> 46.5 | N29: 3 Fase | O29: 0.98 | P29: 10000 | Q29: 10000 | R29: 0.7 | S29: 10 | T29: 10 | U29: =5999+L29*3000 -> 20999 | V29: =U29/1.21 -> 17354.545 | W29: =U29-X29 -> 19999 | X29: 1000 | Y29: =U29-Z29 -> 20999 | AA29: Basis | AB29: =U29/M29 -> 451.5914 | AC29: IP65 | AD29: IP65 | AE29: Ja | AF29: 1420 | AG29: 210 | AH29: 634 | AI29: 1902 | AJ29: 81 | AK29: 3 | AN29: 5 modules dubbele rack | AO29: =Y29-Y29/1.21-5*15*M29-4*50 -> -43.045455
C30: 3 | D30: 4 | H30: =I30&" "&" "&J30&" "&M30&" ("&N30&")" -> AlphaESS Smile9,3 buiten 55,8 (3 Fase) | I30: AlphaESS | J30: Smile9,3 buiten | K30: 9.3 | L30: 6 | M30: =ROUND(K30*L30,2) -> 55.8 | N30: 3 Fase | O30: 0.98 | P30: 10000 | Q30: 10000 | R30: 0.7 | S30: 10 | T30: 10 | U30: =5999+L30*3000 -> 23999 | V30: =U30/1.21 -> 19833.884 | W30: =U30-X30 -> 22999 | X30: 1000 | Y30: =U30-Z30 -> 23999 | AA30: Basis | AB30: =U30/M30 -> 430.08961 | AC30: IP65 | AD30: IP65 | AE30: Ja | AF30: 1420 | AG30: 210 | AH30: 634 | AI30: 2120 | AJ30: 81 | AK30: 3 | AN30: 6 modules dubbele rack | AO30: =Y30-Y30/1.21-5*15*M30-4*50 -> -219.8843
C31: 3 | D31: 4 | H31: =I31&" "&" "&J31&" "&M31&" ("&N31&")" -> AlphaESS Smile9,3 buiten 74,4 (3 Fase) | I31: AlphaESS | J31: Smile9,3 buiten | K31: 9.3 | L31: 8 | M31: =ROUND(K31*L31,2) -> 74.4 | N31: 3 Fase | O31: 0.98 | P31: 10000 | Q31: 10000 | R31: 0.7 | S31: 10 | T31: 10 | U31: =5999+L31*3000 -> 29999 | V31: =U31/1.21 -> 24792.562 | W31: =U31-X31 -> 28999 | X31: 1000 | Y31: =U31-Z31 -> 29999 | AA31: Basis | AB31: =U31/M31 -> 403.21237 | AC31: IP65 | AD31: IP65 | AE31: Ja | AF31: 1830 | AG31: 210 | AH31: 634 | AI31: 1902 | AJ31: 81 | AK31: 3 | AN31: 8 modules triple rack | AO31: =Y31-Y31/1.21-5*15*M31-4*50 -> -573.56198
C32: 3 | D32: 4 | H32: =I32&" "&" "&J32&" "&M32&" ("&N32&")" -> AlphaESS Smile9,3 buiten 93 (3 Fase) | I32: AlphaESS | J32: Smile9,3 buiten | K32: 9.3 | L32: 10 | M32: =ROUND(K32*L32,2) -> 93 | N32: 3 Fase | O32: 0.98 | P32: 10000 | Q32: 10000 | R32: 0.7 | S32: 10 | T32: 10 | U32: =5999+L32*3000 -> 35999 | V32: =U32/1.21 -> 29751.24 | W32: =U32-X32 -> 34999 | X32: 1000 | Y32: =U32-Z32 -> 35999 | AA32: Basis | AB32: =U32/M32 -> 387.08602 | AC32: IP65 | AD32: IP65 | AE32: Ja | AF32: 2240 | AG32: 210 | AH32: 634 | AI32: 1902 | AJ32: 81 | AK32: 3 | AN32: 10 modules quad rack | AO32: =Y32-Y32/1.21-5*15*M32-4*50 -> -927.23967
C33: 3 | D33: 4 | H33: =I33&" "&" "&J33&" "&M33&" ("&N33&")" -> AlphaESS Smile9,3 buiten 111,6 (3 Fase) | I33: AlphaESS | J33: Smile9,3 buiten | K33: 9.3 | L33: 12 | M33: =ROUND(K33*L33,2) -> 111.6 | N33: 3 Fase | O33: 0.98 | P33: 10000 | Q33: 10000 | R33: 0.7 | S33: 10 | T33: 10 | U33: =5999+L33*3000 -> 41999 | V33: =U33/1.21 -> 34709.917 | W33: =U33-X33 -> 40999 | X33: 1000 | Y33: =U33-Z33 -> 41999 | AA33: Basis | AB33: =U33/M33 -> 376.33513 | AC33: IP65 | AD33: IP65 | AE33: Ja | AF33: 2240 | AG33: 210 | AH33: 634 | AI33: 2120 | AJ33: 81 | AK33: 3 | AN33: Grootste Smile configuratie | AO33: =Y33-Y33/1.21-5*15*M33-4*50 -> -1280.9174
E34: 5 | H34: =I34&" "&" "&J34&" "&M34&" ("&N34&")" -> AlphaESS Storion 72,3 (3 Fase) | I34: AlphaESS | J34: Storion | K34: 24.1 | L34: 3 | M34: =ROUND(K34*L34,2) -> 72.3 | N34: 3 Fase | O34: 0.98 | P34: 8000 | Q34: 8000 | R34: 0.7 | S34: 5 | T34: 30 | U34: 39999 | V34: =U34/1.21 -> 33057.025 | W34: =U34-X34 -> 38999 | X34: 1000 | Y34: =U34-Z34 -> 39999 | AA34: Volwaardig | AB34: =U34/M34 -> 553.23651 | AC34: IP55 | AD34: IP20 | AE34: Ja | AF34: 1120 | AG34: 1300 | AH34: 250 | AI34: 2050 | AJ34: 168 | AK34: 5 | AN34: Off-grid capable, 8000 cycli, 5 jaar garantie | AO34: =Y34-Y34/1.21-5*15*M34-4*50 -> 1319.4752
E35: 5 | H35: =I35&" "&" "&J35&" "&M35&" ("&N35&")" -> AlphaESS Storion 96,4 (3 Fase) | I35: AlphaESS | J35: Storion | K35: 24.1 | L35: 4 | M35: =ROUND(K35*L35,2) -> 96.4 | N35: 3 Fase | O35: 0.98 | P35: 8000 | Q35: 8000 | R35: 0.7 | S35: 5 | T35: 30 | U35: 43999 | V35: =U35/1.21 -> 36362.81 | W35: =U35-X35 -> 42999 | X35: 1000 | Y35: =U35-Z35 -> 43999 | AA35: Volwaardig | AB35: =U35/M35 -> 456.42116 | AC35: IP55 | AD35: IP20 | AE35: Ja | AF35: 1120 | AG35: 1300 | AH35: 250 | AI35: 2050 | AJ35: 168 | AK35: 5 | AO35: =Y35-Y35/1.21-5*15*M35-4*50 -> 206.19008
E36: 5 | H36: =I36&" "&" "&J36&" "&M36&" ("&N36&")" -> AlphaESS Storion 120,5 (3 Fase) | I36: AlphaESS | J36: Storion | K36: 24.1 | L36: 5 | M36: =ROUND(K36*L36,2) -> 120.5 | N36: 3 Fase | O36: 0.98 | P36: 8000 | Q36: 8000 | R36: 0.7 | S36: 5 | T36: 30 | U36: 47999 | V36: =U36/1.21 -> 39668.595 | W36: =U36-X36 -> 46999 | X36: 1000 | Y36: =U36-Z36 -> 47999 | AA36: Volwaardig | AB36: =U36/M36 -> 398.33195 | AC36: IP55 | AD36: IP20 | AE36: Ja | AF36: 1120 | AG36: 1300 | AH36: 250 | AI36: 2050 | AJ36: 168 | AK36: 5 | AO36: =Y36-Y36/1.21-5*15*M36-4*50 -> -907.09504
E37: 5 | H37: =I37&" "&" "&J37&" "&M37&" ("&N37&")" -> AlphaESS Storion 144,6 (3 Fase) | I37: AlphaESS | J37: Storion | K37: 24.1 | L37: 6 | M37: =ROUND(K37*L37,2) -> 144.6 | N37: 3 Fase | O37: 0.98 | P37: 8000 | Q37: 8000 | R37: 0.7 | S37: 5 | T37: 30 | U37: 61999 | V37: =U37/1.21 -> 51238.843 | W37: =U37-X37 -> 60999 | X37: 1000 | Y37: =U37-Z37 -> 61999 | AA37: Volwaardig | AB37: =U37/M37 -> 428.7621 | AC37: IP55 | AD37: IP20 | AE37: Ja | AF37: 2240 | AG37: 1300 | AH37: 250 | AI37: 2050 | AJ37: 168 | AK37: 5 | AN37: Dubbele kast vanaf 6 modules | AO37: =Y37-Y37/1.21-5*15*M37-4*50 -> -284.84298
E38: 5 | H38: =I38&" "&" "&J38&" "&M38&" ("&N38&")" -> AlphaESS Storion 168,7 (3 Fase) | I38: AlphaESS | J38: Storion | K38: 24.1 | L38: 7 | M38: =ROUND(K38*L38,2) -> 168.7 | N38: 3 Fase | O38: 0.98 | P38: 8000 | Q38: 8000 | R38: 0.7 | S38: 5 | T38: 30 | U38: 65999 | V38: =U38/1.21 -> 54544.628 | W38: =U38-X38 -> 64999 | X38: 1000 | Y38: =U38-Z38 -> 65999 | AA38: Volwaardig | AB38: =U38/M38 -> 391.2211 | AC38: IP55 | AD38: IP20 | AE38: Ja | AF38: 2240 | AG38: 1300 | AH38: 250 | AI38: 2050 | AJ38: 168 | AK38: 5 | AN38: 7 modules dubbele kast | AO38: =Y38-Y38/1.21-5*15*M38-4*50 -> -1398.1281
E39: 5 | H39: =I39&" "&" "&J39&" "&M39&" ("&N39&")" -> AlphaESS Storion 192,8 (3 Fase) | I39: AlphaESS | J39: Storion | K39: 24.1 | L39: 8 | M39: =ROUND(K39*L39,2) -> 192.8 | N39: 3 Fase | O39: 0.98 | P39: 8000 | Q39: 8000 | R39: 0.7 | S39: 5 | T39: 30 | U39: 69999 | V39: =U39/1.21 -> 57850.413 | W39: =U39-X39 -> 68999 | X39: 1000 | Y39: =U39-Z39 -> 69999 | AA39: Volwaardig | AB39: =U39/M39 -> 363.06535 | AC39: IP55 | AD39: IP20 | AE39: Ja | AF39: 2240 | AG39: 1300 | AH39: 250 | AI39: 2050 | AJ39: 168 | AK39: 5 | AN39: 8 modules dubbele kast | AO39: =Y39-Y39/1.21-5*15*M39-4*50 -> -2511.4132
E40: 5 | H40: =I40&" "&" "&J40&" "&M40&" ("&N40&")" -> AlphaESS Storion 216,9 (3 Fase) | I40: AlphaESS | J40: Storion | K40: 24.1 | L40: 9 | M40: =ROUND(K40*L40,2) -> 216.9 | N40: 3 Fase | O40: 0.98 | P40: 8000 | Q40: 8000 | R40: 0.7 | S40: 5 | T40: 30 | U40: 73999 | V40: =U40/1.21 -> 61156.198 | W40: =U40-X40 -> 72999 | X40: 1000 | Y40: =U40-Z40 -> 73999 | AA40: Volwaardig | AB40: =U40/M40 -> 341.16644 | AC40: IP55 | AD40: IP20 | AE40: Ja | AF40: 2240 | AG40: 1300 | AH40: 250 | AI40: 2050 | AJ40: 168 | AK40: 5 | AN40: 9 modules dubbele kast | AO40: =Y40-Y40/1.21-5*15*M40-4*50 -> -3624.6983
E41: 5 | H41: =I41&" "&" "&J41&" "&M41&" ("&N41&")" -> AlphaESS Storion 241 (3 Fase) | I41: AlphaESS | J41: Storion | K41: 24.1 | L41: 10 | M41: =ROUND(K41*L41,2) -> 241 | N41: 3 Fase | O41: 0.98 | P41: 8000 | Q41: 8000 | R41: 0.7 | S41: 5 | T41: 30 | U41: 77999 | V41: =U41/1.21 -> 64461.983 | W41: =U41-X41 -> 76999 | X41: 1000 | Y41: =U41-Z41 -> 77999 | AA41: Volwaardig | AB41: =U41/M41 -> 323.6473 | AC41: IP55 | AD41: IP20 | AE41: Ja | AF41: 2240 | AG41: 1300 | AH41: 250 | AI41: 2050 | AJ41: 168 | AK41: 5 | AN41: Grootste Storion opstelling | AO41: =Y41-Y41/1.21-5*15*M41-4*50 -> -4737.9835
B42: 2 | H42: =I42&" "&" "&J42&" "&M42&" ("&N42&")" -> HYXiPOWER HYX Hybride 10,07 (1 Fase) | I42: HYXiPOWER | J42: HYX Hybride | K42: 5.035 | L42: 2 | M42: =ROUND(K42*L42,2) -> 10.07 | N42: 1 Fase | O42: 0.98 | P42: 6000 | Q42: =P42 -> 6000 | R42: 0.7 | S42: 10 | T42: 5 | U42: 8499 | V42: =U42/1.21 -> 7023.9669 | W42: =U42-X42 -> 7499 | X42: 1000 | Y42: =U42-Z42 -> 8499 | AA42: Basis | AB42: =U42/M42 -> 843.99206 | AC42: IP65 | AD42: IP67 | AE42: Ja | AF42: 700 | AG42: 200 | AH42: 350 | AI42: 950 | AJ42: 44 | AK42: 5 | AL42: Alleen Frank | AN42: IP65 = buitengeschikt, 1 fase geen verzwaring nodig, budget optie
B43: 2 | H43: =I43&" "&" "&J43&" "&M43&" ("&N43&")" -> HYXiPOWER HYX Hybride 15,11 (1 Fase) | I43: HYXiPOWER | J43: HYX Hybride | K43: 5.035 | L43: 3 | M43: =ROUND(K43*L43,2) -> 15.11 | N43: 1 Fase | O43: 0.98 | P43: 6000 | Q43: =P43 -> 6000 | R43: 0.7 | S43: 10 | T43: 5 | U43: 9999 | V43: =U43/1.21 -> 8263.6364 | W43: =U43-X43 -> 8999 | X43: 1000 | Y43: =U43-Z43 -> 9999 | AA43: Basis | AB43: =U43/M43 -> 661.74719 | AC43: IP65 | AD43: IP67 | AE43: Ja | AF43: 700 | AG43: 200 | AH43: 350 | AI43: 1300 | AJ43: 44 | AK43: 5 | AL43: Alleen Frank
B44: 2 | H44: =I44&" "&" "&J44&" "&M44&" ("&N44&")" -> HYXiPOWER HYX Hybride 20,14 (1 Fase) | I44: HYXiPOWER | J44: HYX Hybride | K44: 5.035 | L44: 4 | M44: =ROUND(K44*L44,2) -> 20.14 | N44: 1 Fase | O44: 0.98 | P44: 6000 | Q44: 6000 | R44: 0.7 | S44: 10 | T44: 5 | U44: 11499 | V44: =U44/1.21 -> 9503.3058 | W44: =U44-X44 -> 10499 | X44: 1000 | Y44: =U44-Z44 -> 11499 | AA44: Basis | AB44: =U44/M44 -> 570.95333 | AC44: IP65 | AD44: IP67 | AE44: Ja | AF44: 700 | AG44: 200 | AH44: 350 | AI44: 1650 | AJ44: 44 | AK44: 5 | AL44: Alleen Frank
B45: 2 | H45: =I45&" "&" "&J45&" "&M45&" ("&N45&")" -> HYXiPOWER HYX Hybride 25,18 (1 Fase) | I45: HYXiPOWER | J45: HYX Hybride | K45: 5.035 | L45: 5 | M45: =ROUND(K45*L45,2) -> 25.18 | N45: 1 Fase | O45: 0.98 | P45: 6000 | Q45: 6000 | R45: 0.7 | S45: 10 | T45: 5 | U45: 12999 | V45: =U45/1.21 -> 10742.975 | W45: =U45-X45 -> 11999 | X45: 1000 | Y45: =U45-Z45 -> 12999 | AA45: Basis | AB45: =U45/M45 -> 516.24305 | AC45: IP65 | AD45: PI67 | AE45: Ja | AF45: 700 | AG45: 200 | AH45: 350 | AI45: 2000 | AJ45: 44 | AK45: 5 | AL45: Alleen Frank | AN45: 5 modules hoge stack, maximum voor 1 fase
F46: 6 | H46: =I46&" "&" "&J46&" "&M46&" ("&N46&")" -> HYXiPOWER HYX Hybride 10,07 (3 Fase) | I46: HYXiPOWER | J46: HYX Hybride | K46: 5.035 | L46: 2 | M46: =ROUND(K46*L46,2) -> 10.07 | N46: 3 Fase | O46: 0.98 | P46: 6000 | Q46: =P46 -> 6000 | R46: 0.7 | S46: 10 | T46: 10 | U46: 8499 | V46: =U46/1.21 -> 7023.9669 | W46: =U46-X46 -> 7499 | X46: 1000 | Y46: =U46-Z46 -> 8499 | AA46: Basis | AB46: =U46/M46 -> 843.99206 | AC46: IP65 | AD46: IP67 | AE46: Ja | AF46: 700 | AG46: 200 | AH46: 350 | AI46: 950 | AJ46: 44 | AK46: 5 | AL46: Alleen Frank | AN46: IP65 = buitengeschikt, voor 3 fase
F47: 6 | H47: =I47&" "&" "&J47&" "&M47&" ("&N47&")" -> HYXiPOWER HYX Hybride 15,11 (3 Fase) | I47: HYXiPOWER | J47: HYX Hybride | K47: 5.035 | L47: 3 | M47: =ROUND(K47*L47,2) -> 15.11 | N47: 3 Fase | O47: 0.98 | P47: 6000 | Q47: =P47 -> 6000 | R47: 0.7 | S47: 10 | T47: 10 | U47: 9999 | V47: =U47/1.21 -> 8263.6364 | W47: =U47-X47 -> 8999 | X47: 1000 | Y47: =U47-Z47 -> 9999 | AA47: Basis | AB47: =U47/M47 -> 661.74719 | AC47: IP65 | AD47: IP67 | AE47: Ja | AF47: 700 | AG47: 200 | AH47: 350 | AI47: 1300 | AJ47: 44 | AK47: 5 | AL47: Alleen Frank
F48: 6 | H48: =I48&" "&" "&J48&" "&M48&" ("&N48&")" -> HYXiPOWER HYX Hybride 20,14 (3 Fase) | I48: HYXiPOWER | J48: HYX Hybride | K48: 5.035 | L48: 4 | M48: =ROUND(K48*L48,2) -> 20.14 | N48: 3 Fase | O48: 0.98 | P48: 6000 | Q48: 6000 | R48: 0.7 | S48: 10 | T48: 10 | U48: 11499 | V48: =U48/1.21 -> 9503.3058 | W48: =U48-X48 -> 10499 | X48: 1000 | Y48: =U48-Z48 -> 11499 | AA48: Basis | AB48: =U48/M48 -> 570.95333 | AC48: IP65 | AD48: IP67 | AE48: Ja | AF48: 700 | AG48: 200 | AH48: 350 | AI48: 1650 | AJ48: 44 | AK48: 5 | AL48: Alleen Frank
F49: 6 | H49: =I49&" "&" "&J49&" "&M49&" ("&N49&")" -> HYXiPOWER HYX Hybride 25,18 (3 Fase) | I49: HYXiPOWER | J49: HYX Hybride | K49: 5.035 | L49: 5 | M49: =ROUND(K49*L49,2) -> 25.18 | N49: 3 Fase | O49: 0.98 | P49: 6000 | Q49: 6000 | R49: 0.7 | S49: 10 | T49: 10 | U49: 12999 | V49: =U49/1.21 -> 10742.975 | W49: =U49-X49 -> 11999 | X49: 1000 | Y49: =U49-Z49 -> 12999 | AA49: Basis | AB49: =U49/M49 -> 516.24305 | AC49: IP65 | AD49: IP67 | AE49: Ja | AF49: 700 | AG49: 200 | AH49: 350 | AI49: 2000 | AJ49: 44 | AK49: 5 | AL49: Alleen Frank | AN49: 5 modules hoge stack
F50: 6 | H50: =I50&" "&" "&J50&" "&M50&" ("&N50&")" -> HYXiPOWER HYX Hybride 30,21 (3 Fase) | I50: HYXiPOWER | J50: HYX Hybride | K50: 5.035 | L50: 6 | M50: =ROUND(K50*L50,2) -> 30.21 | N50: 3 Fase | O50: 0.98 | P50: 6000 | Q50: 6000 | R50: 0.7 | S50: 10 | T50: 10 | U50: 15499 | V50: =U50/1.21 -> 12809.091 | W50: =U50-X50 -> 14499 | X50: 1000 | Y50: =U50-Z50 -> 13499 | Z50: 2000 | AA50: Basis | AB50: =U50/M50 -> 513.04204 | AC50: IP65 | AD50: IP67 | AE50: Ja | AF50: 1400 | AG50: 200 | AH50: 350 | AI50: 1350 | AJ50: 44 | AK50: 5 | AL50: Alleen Frank | AN50: BTW grens €13.999 overschreden, factuur gesplitst, dubbele rij
F51: 6 | H51: =I51&" "&" "&J51&" "&M51&" ("&N51&")" -> HYXiPOWER HYX Hybride 40,28 (3 Fase) | I51: HYXiPOWER | J51: HYX Hybride | K51: 5.035 | L51: 8 | M51: =ROUND(K51*L51,2) -> 40.28 | N51: 3 Fase | O51: 0.98 | P51: 6000 | Q51: 6000 | R51: 0.7 | S51: 10 | T51: 10 | U51: 18499 | V51: =U51/1.21 -> 15288.43 | W51: =U51-X51 -> 17499 | X51: 1000 | Y51: =U51-Z51 -> 18499 | AA51: Basis | AB51: =U51/M51 -> 459.26018 | AC51: IP65 | AD51: IP67 | AE51: Ja | AF51: 1400 | AG51: 200 | AH51: 350 | AI51: 1700 | AJ51: 44 | AK51: 5 | AL51: Alleen Frank | AN51: 8 modules dubbele rij | AO51: =Y51-Y51/1.21-5*15*M51-4*50 -> -10.429752
F52: 6 | H52: =I52&" "&" "&J52&" "&M52&" ("&N52&")" -> HYXiPOWER HYX Hybride 50,35 (3 Fase) | I52: HYXiPOWER | J52: HYX Hybride | K52: 5.035 | L52: 10 | M52: =ROUND(K52*L52,2) -> 50.35 | N52: 3 Fase | O52: 0.98 | P52: 6000 | Q52: 6000 | R52: 0.7 | S52: 10 | T52: 10 | U52: 21499 | V52: =U52/1.21 -> 17767.769 | W52: =U52-X52 -> 20499 | X52: 1000 | Y52: =U52-Z52 -> 21499 | AA52: Basis | AB52: =U52/M52 -> 426.99106 | AC52: IP65 | AD52: IP67 | AE52: Ja | AF52: 1400 | AG52: 200 | AH52: 350 | AI52: 2050 | AJ52: 44 | AK52: 5 | AL52: Alleen Frank | AN52: Grootste Hybride opstelling | AO52: =Y52-Y52/1.21-5*15*M52-4*50 -> -245.0186
G53: 7 | H53: =I53&" "&" "&J53&" "&M53&" ("&N53&")" -> HYXiPOWER HYX All-In-One 10,07 (3 Fase) | I53: HYXiPOWER | J53: HYX All-In-One | K53: 5.035 | L53: 2 | M53: =ROUND(K53*L53,2) -> 10.07 | N53: 3 Fase | O53: 0.98 | P53: 10000 | Q53: Onbeperkt | R53: 0.7 | S53: 10 | T53: 6 | U53: =11499+500 -> 11999 | V53: =U53/1.21 -> 9916.5289 | W53: =U53-X53 -> 10999 | X53: 1000 | Y53: =U53-Z53 -> 11999 | AA53: Volwaardig | AB53: =U53/M53 -> 1191.5591 | AC53: IP67 | AD53: IP67 | AE53: Ja | AF53: 700 | AG53: 200 | AH53: 350 | AI53: 1320 | AJ53: 50 | AK53: 5 | AL53: Alleen Frank | AN53: Complete onafhankelijkheid, onbeperkte cycli garantie
G54: 7 | H54: =I54&" "&" "&J54&" "&M54&" ("&N54&")" -> HYXiPOWER HYX All-In-One 15,11 (3 Fase) | I54: HYXiPOWER | J54: HYX All-In-One | K54: 5.035 | L54: 3 | M54: =ROUND(K54*L54,2) -> 15.11 | N54: 3 Fase | O54: 0.98 | P54: 10000 | Q54: Onbeperkt | R54: 0.7 | S54: 10 | T54: 8 | U54: =12999+500 -> 13499 | V54: =U54/1.21 -> 11156.198 | W54: =U54-X54 -> 12499 | X54: 1000 | Y54: =U54-Z54 -> 13499 | AA54: Volwaardig | AB54: =U54/M54 -> 893.38187 | AC54: IP67 | AD54: IP67 | AE54: Ja | AF54: 700 | AG54: 200 | AH54: 350 | AI54: 1670 | AJ54: 50 | AK54: 5 | AL54: Alleen Frank | AN54: Meer vermogen, onbeperkte cycli garantie
G55: 7 | H55: =I55&" "&" "&J55&" "&M55&" ("&N55&")" -> HYXiPOWER HYX All-In-One 20,14 (3 Fase) | I55: HYXiPOWER | J55: HYX All-In-One | K55: 5.035 | L55: 4 | M55: =ROUND(K55*L55,2) -> 20.14 | N55: 3 Fase | O55: 0.98 | P55: 10000 | Q55: Onbeperkt | R55: 0.7 | S55: 10 | T55: 11 | U55: =14499+500 -> 14999 | V55: =U55/1.21 -> 12395.868 | W55: =U55-X55 -> 13999 | X55: 1000 | Y55: =U55-Z55 -> 13999 | Z55: 1000 | AA55: Volwaardig | AB55: =U55/M55 -> 744.73684 | AC55: IP67 | AD55: IP67 | AE55: Ja | AF55: 700 | AG55: 200 | AH55: 350 | AI55: 2020 | AJ55: 50 | AK55: 5 | AL55: Alleen Frank | AN55: BTW grens €13.999 overschreden, factuur gesplitst
G56: 7 | H56: =I56&" "&" "&J56&" "&M56&" ("&N56&")" -> HYXiPOWER HYX All-In-One 25,18 (3 Fase) | I56: HYXiPOWER | J56: HYX All-In-One | K56: 5.035 | L56: 5 | M56: =ROUND(K56*L56,2) -> 25.18 | N56: 3 Fase | O56: 0.98 | P56: 10000 | Q56: Onbeperkt | R56: 0.7 | S56: 10 | T56: 13 | U56: =15999+500 -> 16499 | V56: =U56/1.21 -> 13635.537 | W56: =U56-X56 -> 14499 | X56: 2000 | Y56: =U56-Z56 -> 13999 | Z56: 2500 | AA56: Volwaardig | AB56: =U56/M56 -> 655.24226 | AC56: IP67 | AD56: IP67 | AE56: Ja | AF56: 700 | AG56: 200 | AH56: 350 | AI56: 2370 | AJ56: 50 | AK56: 5 | AL56: Alleen Frank | AN56: Hoogste vermogen 13kW, BTW grens €13.999 overschreden, factuur gesplitst

Sheet Keuzemenu
C1: Keuze ja/nee
C2: Ja
C3: Nee
D5: kWh per km
C6: Klasse
C7: A - Mini auto | D7: 0.15
C8: B - Compacte auto | D8: 0.2
C9: C - Middenklasse | D9: 0.25
C10: D - Grote auto | D10: 0.3
C11: E - Prestigewagen | D11: 0.4
C12: F - Luxewagens | D12: 0.4
C13: J - Off-road sportwagens | D13: 0.5
I16: Handel
C17: soort contract | H17: Start | I17: =IF(Calculator!P114<>"Alleen Zelfconsumptie","Ja","Nee") -> Ja
C18: Vast | H18: Toekomst | I18: =IF(Calculator!P116<>"Alleen Zelfconsumptie","Ja","Nee") -> Ja
C19: Variabel
C20: Dynamisch
C23: Leverancier | D23: opslag laag | E23: opslag terugl | F23: Extra rendement
C24: Frank Energie | D24: 0.02 | E24: 0 | F24: 0
C25: Hegg Energy | D25: 0.034 | E25: 0.034 | F25: 0.04
C26: Next Energy | D26: 0.02 | E26: 0 | F26: 0
R27: =Calculator!P114 -> Actief handelen | T27: =Calculator!P116 -> Actief handelen
D28: omvormer | E28: omvormer | F28: omvormer | G28: omvormer | H28: omvormer | I28: omvormer | J28: omvormer | K28: omvormer | L28: omvormer | M28: omvormer | N28: omvormer | O28: omvormer | P28: omvormer | R28: omvormer | T28: omvormer
D29: 5 | E29: 6 | F29: 8 | G29: 10 | H29: 11 | I29: 13 | J29: 20 | K29: 30 | L29: 40 | M29: 50 | N29: 60 | O29: 70 | P29: 80 | R29: =Calculator!R102 -> 10 | T29: =R29 -> 10
C30: Cycli per dag | D30: 2 | E30: =D30+1 -> 3 | F30: =E30+1 -> 4 | G30: =F30+1 -> 5 | H30: =G30+1 -> 6 | I30: =H30+1 -> 7 | J30: =I30+1 -> 8 | K30: =J30+1 -> 9 | L30: =K30+1 -> 10 | ... P30: =O30+1 -> 14 | R30: =HLOOKUP(R29,D29:P30,2,FALSE) -> 5 | T30: =HLOOKUP(T29,D29:P30,2,FALSE) -> 5
C31: Alleen zelfconsumptie | D31: 1 | E31: 1 | F31: 1 | G31: 1 | H31: 1 | I31: 1 | J31: =I31+0.2 -> 1.2 | K31: =J31+0.05 -> 1.25 | L31: 1 | M31: =K31+0.1 -> 1.35 | N31: 1 | O31: 1 | P31: 1 | R31: =VLOOKUP(R27,C31:P33,R30,FALSE) -> 1.5 | T31: =VLOOKUP(T27,C31:P33,T30,FALSE) -> 1.5
C32: Zelfconsumptie + Handel | D32: 1.25 | E32: 1.25 | F32: 1.25 | G32: 1.25 | H32: 1.25 | I32: 1.25 | J32: =I32+0.2 -> 1.45 | K32: =J32+0.05 -> 1.5 | L32: 1.25 | M32: =K32+0.1 -> 1.6 | N32: 1.25 | O32: 1.25 | P32: 1.25
C33: Actief handelen | D33: 1.5 | E33: 1.5 | F33: 1.5 | G33: 1.5 | H33: 1.5 | I33: 1.5 | J33: =I33+0.2 -> 1.7 | K33: =J33+0.05 -> 1.75 | L33: 1.5 | M33: =K33+0.1 -> 1.85 | N33: 1.5 | O33: 1.5 | P33: 1.5
C36: BTW
C37: Ja, particulier nieuw in KOR
C38: Ja, particulier al in KOR
C39: Ja, zakelijk
C40: Nee
C42: Particulier of zakelijk
C43: Particulier
C44: Zakelijk

Sheet Stamgegevens
A1: 1 | B1: =A1+1 -> 2 | C1: =B1+1 -> 3 | D1: =C1+1 -> 4 | E1: =D1+1 -> 5 | F1: =E1+1 -> 6 | G1: =F1+1 -> 7 | H1: =G1+1 -> 8 | I1: =H1+1 -> 9 | ... AE1: =AD1+1 -> 31
A2: Stamgegevens | D2: handmatige invoer | G2: zelfde als vorig jaar | K2: zelfde als vorig jaar + inflatie/aanpassing | Q2: Laatste jaar saldering | R2: 2026
S4: excl. eb. | T4: excl. eb. | Y4: correctie
D5: maximale | E5: af te dragen | F5: af te dragen | J5: energie | L5: energie | P5: vastrecht | Q5: vastrecht | S5: leverings | T5: leverings | W5: omreken | Y5: tarief | AA5: effectieve | AC5: correctie | AE5: uit
C6: BTW-% | D6: BTW | E6: BTW | F6: BTW | H6: jaarlijkse | J6: belasting | K6: vanaf | L6: belasting | M6: jaarlijkse | N6: percentage | P6: stroom | Q6: gas | S6: kosten | T6: kosten | W6: factor | Y6: terug | AA6: minuten | AC6: tarief | AE6: betalings
A7: jaar | C7: batterijen | D7: teruggave | E7: per kWh | F7: per 1000 Wp | H7: inflatie | J7: incl BTW | K7: KwH | L7: incl BTW | M7: aanpassing | N7: saldering | P7: nieuw | Q7: nieuw | S7: laag | T7: hoog | W7: gas | Y7: levering | AA7: per kwartier | AC7: handel | AE7: %
A8: 2025 | C8: 0.21 | D8: 2494 | E8: 15 | F8: 20 | H8: 0.032 | J8: 0.12286 | K8: 10000 | L8: 0.08394 | M8: 0 | N8: 1 | P8: 5.99 | Q8: 5.99 | S8: 0.01 | T8: 0.15 | W8: 3.5 | Y8: -0.02 | AA8: 14 | AC8: =IF(Calculator!R112<>"Next Energy",0.2,0.24) -> 0.2 | AE8: 0.85
A9: =A8+1 -> 2026 | C9: =C8 -> 0.21 | D9: =D8 -> 2494 | E9: =E8 -> 15 | F9: =F8 -> 20 | H9: 0.028 | J9: 0.11046 | K9: =K8 -> 10000 | L9: =L8*(1+M8) -> 0.08394 | M9: 0 | N9: 1 | P9: =P8*(1+H8) -> 6.18168 | Q9: =Q8*(1+H8) -> 6.18168 | S9: =S8*(1+H8) -> 0.01032 | T9: =T8*(1+H8) -> 0.1548 | W9: =W8 -> 3.5 | Y9: =Y8 -> -0.02 | AA9: =AA8 -> 14 | AC9: =AC8 -> 0.2 | AE9: =AE8 -> 0.85
A10: =A9+1 -> 2027 | C10: =C9 -> 0.21 | D10: =D9 -> 2494 | E10: =E9 -> 15 | F10: =F9 -> 20 | H10: 0.025 | J10: =J9*(1+M9) -> 0.11046 | K10: =K9 -> 10000 | L10: =L9*(1+M9) -> 0.08394 | M10: 0 | N10: 0 | P10: =P9*(1+H9) -> 6.354767 | Q10: =Q9*(1+H9) -> 6.354767 | S10: =S9*(1+H9) -> 0.01060896 | T10: =T9*(1+H9) -> 0.1591344 | W10: =W9 -> 3.5 | Y10: =Y9 -> -0.02 | AA10: =AA9 -> 14 | AC10: =AC9 -> 0.2 | AE10: =AE9 -> 0.85
A11: =A10+1 -> 2028 | C11: =C10 -> 0.21 | D11: =D10 -> 2494 | E11: =E10 -> 15 | F11: =F10 -> 20 | H11: =H10 -> 0.025 | J11: =J10*(1+M10) -> 0.11046 | K11: =K10 -> 10000 | L11: =L10*(1+M10) -> 0.08394 | M11: =M10 -> 0 | N11: =N10 -> 0 | P11: =P10*(1+H10) -> 6.5136362 | Q11: =Q10*(1+H10) -> 6.5136362 | S11: =S10*(1+H10) -> 0.010874184 | T11: =T10*(1+H10) -> 0.16311276 | W11: =W10 -> 3.5 | Y11: =Y10 -> -0.02 | AA11: =AA10 -> 14 | AC11: =AC10 -> 0.2 | AE11: =AE10 -> 0.85
A12: =A11+1 -> 2029 | C12: =C11 -> 0.21 | D12: =D11 -> 2494 | E12: =E11 -> 15 | F12: =F11 -> 20 | H12: =H11 -> 0.025 | J12: =J11*(1+M11) -> 0.11046 | K12: =K11 -> 10000 | L12: =L11*(1+M11) -> 0.08394 | M12: =M11 -> 0 | N12: =N11 -> 0 | P12: =P11*(1+H11) -> 6.6764771 | Q12: =Q11*(1+H11) -> 6.6764771 | S12: =S11*(1+H11) -> 0.011146039 | T12: =T11*(1+H11) -> 0.16719058 | W12: =W11 -> 3.5 | Y12: =Y11 -> -0.02 | AA12: =AA11 -> 14 | AC12: =AC11 -> 0.2 | AE12: =AE11 -> 0.85
A13: =A12+1 -> 2030 | C13: =C12 -> 0.21 | D13: =D12 -> 2494 | E13: =E12 -> 15 | F13: =F12 -> 20 | H13: =H12 -> 0.025 | J13: =J12*(1+M12) -> 0.11046 | K13: =K12 -> 10000 | L13: =L12*(1+M12) -> 0.08394 | M13: =M12 -> 0 | N13: =N12 -> 0 | P13: =P12*(1+H12) -> 6.843389 | Q13: =Q12*(1+H12) -> 6.843389 | S13: =S12*(1+H12) -> 0.01142469 | T13: =T12*(1+H12) -> 0.17137034 | W13: =W12 -> 3.5 | Y13: =Y12 -> -0.02 | AA13: =AA12 -> 14 | AC13: =AC12 -> 0.2 | AE13: =AE12 -> 0.85
A14: =A13+1 -> 2031 | C14: =C13 -> 0.21 | D14: =D13 -> 2494 | E14: =E13 -> 15 | F14: =F13 -> 20 | H14: =H13 -> 0.025 | J14: =J13*(1+M13) -> 0.11046 | K14: =K13 -> 10000 | L14: =L13*(1+M13) -> 0.08394 | M14: =M13 -> 0 | N14: =N13 -> 0 | P14: =P13*(1+H13) -> 7.0144738 | Q14: =Q13*(1+H13) -> 7.0144738 | S14: =S13*(1+H13) -> 0.011710307 | T14: =T13*(1+H13) -> 0.1756546 | W14: =W13 -> 3.5 | Y14: =Y13 -> -0.02 | AA14: =AA13 -> 14 | AC14: =AC13 -> 0.2 | AE14: =AE13 -> 0.85
A15: =A14+1 -> 2032 | C15: =C14 -> 0.21 | D15: =D14 -> 2494 | E15: =E14 -> 15 | F15: =F14 -> 20 | H15: =H14 -> 0.025 | J15: =J14*(1+M14) -> 0.11046 | K15: =K14 -> 10000 | L15: =L14*(1+M14) -> 0.08394 | M15: =M14 -> 0 | N15: =N14 -> 0 | P15: =P14*(1+H14) -> 7.1898356 | Q15: =Q14*(1+H14) -> 7.1898356 | S15: =S14*(1+H14) -> 0.012003064 | T15: =T14*(1+H14) -> 0.18004597 | W15: =W14 -> 3.5 | Y15: =Y14 -> -0.02 | AA15: =AA14 -> 14 | AC15: =AC14 -> 0.2 | AE15: =AE14 -> 0.85
A16: =A15+1 -> 2033 | C16: =C15 -> 0.21 | D16: =D15 -> 2494 | E16: =E15 -> 15 | F16: =F15 -> 20 | H16: =H15 -> 0.025 | J16: =J15*(1+M15) -> 0.11046 | K16: =K15 -> 10000 | L16: =L15*(1+M15) -> 0.08394 | M16: =M15 -> 0 | N16: =N15 -> 0 | P16: =P15*(1+H15) -> 7.3695815 | Q16: =Q15*(1+H15) -> 7.3695815 | S16: =S15*(1+H15) -> 0.012303141 | T16: =T15*(1+H15) -> 0.18454712 | W16: =W15 -> 3.5 | Y16: =Y15 -> -0.02 | AA16: =AA15 -> 14 | AC16: =AC15 -> 0.2 | AE16: =AE15 -> 0.85
A17: =A16+1 -> 2034 | C17: =C16 -> 0.21 | D17: =D16 -> 2494 | E17: =E16 -> 15 | F17: =F16 -> 20 | H17: =H16 -> 0.025 | J17: =J16*(1+M16) -> 0.11046 | K17: =K16 -> 10000 | L17: =L16*(1+M16) -> 0.08394 | M17: =M16 -> 0 | N17: =N16 -> 0 | P17: =P16*(1+H16) -> 7.553821 | Q17: =Q16*(1+H16) -> 7.553821 | S17: =S16*(1+H16) -> 0.01261072 | T17: =T16*(1+H16) -> 0.18916079 | W17: =W16 -> 3.5 | Y17: =Y16 -> -0.02 | AA17: =AA16 -> 14 | AC17: =AC16 -> 0.2 | AE17: =AE16 -> 0.85
A18: =A17+1 -> 2035 | C18: =C17 -> 0.21 | D18: =D17 -> 2494 | E18: =E17 -> 15 | F18: =F17 -> 20 | H18: =H17 -> 0.025 | J18: =J17*(1+M17) -> 0.11046 | K18: =K17 -> 10000 | L18: =L17*(1+M17) -> 0.08394 | M18: =M17 -> 0 | N18: =N17 -> 0 | P18: =P17*(1+H17) -> 7.7426666 | Q18: =Q17*(1+H17) -> 7.7426666 | S18: =S17*(1+H17) -> 0.012925988 | T18: =T17*(1+H17) -> 0.19388981 | W18: =W17 -> 3.5 | Y18: =Y17 -> -0.02 | AA18: =AA17 -> 14 | AC18: =AC17 -> 0.2 | AE18: =AE17 -> 0.85
A19: =A18+1 -> 2036 | C19: =C18 -> 0.21 | D19: =D18 -> 2494 | E19: =E18 -> 15 | F19: =F18 -> 20 | H19: =H18 -> 0.025 | J19: =J18*(1+M18) -> 0.11046 | K19: =K18 -> 10000 | L19: =L18*(1+M18) -> 0.08394 | M19: =M18 -> 0 | N19: =N18 -> 0 | P19: =P18*(1+H18) -> 7.9362332 | Q19: =Q18*(1+H18) -> 7.9362332 | S19: =S18*(1+H18) -> 0.013249137 | T19: =T18*(1+H18) -> 0.19873706 | W19: =W18 -> 3.5 | Y19: =Y18 -> -0.02 | AA19: =AA18 -> 14 | AC19: =AC18 -> 0.2 | AE19: =AE18 -> 0.85
A20: =A19+1 -> 2037 | C20: =C19 -> 0.21 | D20: =D19 -> 2494 | E20: =E19 -> 15 | F20: =F19 -> 20 | H20: =H19 -> 0.025 | J20: =J19*(1+M19) -> 0.11046 | K20: =K19 -> 10000 | L20: =L19*(1+M19) -> 0.08394 | M20: =M19 -> 0 | N20: =N19 -> 0 | P20: =P19*(1+H19) -> 8.1346391 | Q20: =Q19*(1+H19) -> 8.1346391 | S20: =S19*(1+H19) -> 0.013580366 | T20: =T19*(1+H19) -> 0.20370549 | W20: =W19 -> 3.5 | Y20: =Y19 -> -0.02 | AA20: =AA19 -> 14 | AC20: =AC19 -> 0.2 | AE20: =AE19 -> 0.85
A21: =A20+1 -> 2038 | C21: =C20 -> 0.21 | D21: =D20 -> 2494 | E21: =E20 -> 15 | F21: =F20 -> 20 | H21: =H20 -> 0.025 | J21: =J20*(1+M20) -> 0.11046 | K21: =K20 -> 10000 | L21: =L20*(1+M20) -> 0.08394 | M21: =M20 -> 0 | N21: =N20 -> 0 | P21: =P20*(1+H20) -> 8.338005 | Q21: =Q20*(1+H20) -> 8.338005 | S21: =S20*(1+H20) -> 0.013919875 | T21: =T20*(1+H20) -> 0.20879812 | W21: =W20 -> 3.5 | Y21: =Y20 -> -0.02 | AA21: =AA20 -> 14 | AC21: =AC20 -> 0.2 | AE21: =AE20 -> 0.85
A22: =A21+1 -> 2039 | C22: =C21 -> 0.21 | D22: =D21 -> 2494 | E22: =E21 -> 15 | F22: =F21 -> 20 | H22: =H21 -> 0.025 | J22: =J21*(1+M21) -> 0.11046 | K22: =K21 -> 10000 | L22: =L21*(1+M21) -> 0.08394 | M22: =M21 -> 0 | N22: =N21 -> 0 | P22: =P21*(1+H21) -> 8.5464552 | Q22: =Q21*(1+H21) -> 8.5464552 | S22: =S21*(1+H21) -> 0.014267872 | T22: =T21*(1+H21) -> 0.21401808 | W22: =W21 -> 3.5 | Y22: =Y21 -> -0.02 | AA22: =AA21 -> 14 | AC22: =AC21 -> 0.2 | AE22: =AE21 -> 0.85
... A36: =A35+1 -> 2053 | C36: =C35 -> 0.21 | D36: =D35 -> 2494 | E36: =E35 -> 15 | F36: =F35 -> 20 | H36: =H35 -> 0.025 | J36: =J35*(1+M35) -> 0.11046 | K36: =K35 -> 10000 | L36: =L35*(1+M35) -> 0.08394 | M36: =M35 -> 0 | N36: =N35 -> 0 | P36: =P35*(1+H35) -> 12.075917 | Q36: =Q35*(1+H35) -> 12.075917 | S36: =S35*(1+H35) -> 0.020160129 | T36: =T35*(1+H35) -> 0.30240194 | W36: =W35 -> 3.5 | Y36: =Y35 -> -0.02 | AA36: =AA35 -> 14 | AC36: =AC35 -> 0.2 | AE36: =AE35 -> 0.85
AC39: Ik heb AB7 aangepast ivm geen opslag next

Sheet BTW
C3: BTW-percentage batterijen | D3: =IF(D13="nee",0,VLOOKUP(Jaargegevens!$E$5,Stamgegevens!$A$8:$AE$36,Stamgegevens!$C$1)) -> 0.21 | E3: =IF(D3=0,0,D3/(1+D3)) -> 0.17355372 | H3: Geen BTW | J3: Geen teruggave BTW op aanschaf batterijen.
C5: factuur en btw-bedrag particulier | D5: =VLOOKUP(Calculator!M90,Producten!$H$7:$AA$1007,18,FALSE) -> 13999 | E5: =ROUND(D5*E3,0) -> 2430 | H5: BTW particulier maximaal | J5: =CONCATENATE("Maximaal € ",E9,CONCATENATE(" minus € ",E11," per kWh capaciteit (€ ",D21,").")) -> Maximaal € 2494 minus € 15 per kWh capaciteit (€ 328).
J6: =IF(D26=0,"","1e jaar : ") | K6: =IF(H26=0,"","1e jaar : ") -> 1e jaar : | T6: Calculator
C7: factuur en btw-bedrag zakelijk | D7: =Calculator!R125+Calculator!R127 -> 14999 | E7: =ROUND(D7*E3,0) -> 2603 | H7: BTW particulier alles | J7: =CONCATENATE("€ ",D19,CONCATENATE(" minus € ",E11," per kWh capaciteit (€ ",D21,").")) -> € 2430 minus € 15 per kWh capaciteit (€ 328). | T7: Klant | U7: BTW | V7: KOR | W7: KEY
T8: =Calculator!R137 -> Particulier | U8: =Calculator!R139 -> Ja | V8: =Calculator!R141 -> Nee | W8: =T8&U8&V8 -> ParticulierJaNee | X8: 0
C9: maximale BTW-teruggave | D9: =VLOOKUP(Jaargegevens!$E$5,Stamgegevens!$A$8:$AE$36,Stamgegevens!$D$1) -> 2494 | E9: =IF(D3=0,0,D9) -> 2494 | H9: BTW zakelijk geen KOR | J9: =CONCATENATE("1e jaar : € ",L19," minus af te dragen BTW teruglevering € ",L21," (schatting).") -> 1e jaar : € 2603 minus af te dragen BTW teruglevering € 328 (schatting).
T10: Teruggave | V10: =IF(T8="Zakelijk",Calculator!S144,IF(D38<0,0,Calculator!S144)) -> 2102
C11: af te dragen BTW per kWh | D11: =VLOOKUP(Jaargegevens!$E$5,Stamgegevens!$A$8:$AE$36,Stamgegevens!$E$1) -> 15 | E11: =IF(D3=0,0,D11) -> 15 | H11: BTW zakelijk KOR | J11: =CONCATENATE("1e jaar : € ",H19," minus af te dragen BTW teruglevering € ",O21," (schatting).") -> 1e jaar : € 2430 minus af te dragen BTW teruglevering € 328 (schatting). | T11: Kosten | V11: =IF(T8="Zakelijk",L21,IF(D38<0,0,SUM(D21:D22)+D29)) -> 378 | W11: Eind jaar | X11: =VLOOKUP(W8,W27:X34,2,FALSE)+Kosten!B6 -> 2025
T12: Per saldo | V12: =Kosten!J29 -> 2102
C13: BTW-teruggave | D13: =IF(T8="Zakelijk","ja",IF(Calculator!P114="Alleen zelfconsumptie","nee","ja")) -> ja | T13: De eenmalige investering voor de klant, inclusief teruggave BTW.
D16: particulier | H16: particulier/zakelijk | L16: zakelijk | O16: zakelijk | T16: Klant | U16: BTW | V16: KOR | W16: KEY
D17: nieuw | H17: nu in KOR | L17: niet in KOR | O17: wel in KOR | T17: Particulier | U17: Ja | V17: Nee | W17: =T17&U17&V17 -> ParticulierJaNee | X17: =D23 -> 2102
T18: Particulier | U18: Ja | V18: Ja | W18: =T18&U18&V18 -> ParticulierJaJa | X18: =H23 -> 2102
A19: BTW terug te ontvangen | D19: =E5 -> 2430 | H19: =E5 -> 2430 | L19: =E7 -> 2603 | O19: =L19 -> 2603 | T19: Particulier | U19: Nee | V19: Nee | W19: =T19&U19&V19 -> ParticulierNeeNee | X19: 0
T20: Particulier | U20: Nee | V20: Ja | W20: =T20&U20&V20 -> ParticulierNeeJa | X20: 0
A21: af te dragen batterij | C21: =Calculator!R92 -> 21.85 | D21: =ROUND(C21*E11,0) -> 328 | H21: =D21 -> 328 | L21: =H21 -> 328 | O21: =L21 -> 328 | T21: Zakelijk | U21: Ja | V21: Ja | W21: =T21&U21&V21 -> ZakelijkJaJa | X21: =H23 -> 2102
D22: - | H22: - | L22: - | O22: - | T22: Zakelijk | U22: Ja | V22: Nee | W22: =T22&U22&V22 -> ZakelijkJaNee | X22: =L23 -> 2275
A23: per saldo te ontvangen | D23: =D19-D21 -> 2102 | H23: =H19-H21 -> 2102 | L23: =L19-L21 -> 2275 | O23: =O19-O21 -> 2275 | T23: Zakelijk | U23: Nee | V23: Nee | W23: =T23&U23&V23 -> ZakelijkNeeNee | X23: 0
D24: = | H24: = | L24: = | O24: = | T24: Zakelijk | U24: Nee | V24: Ja | W24: =T24&U24&V24 -> ZakelijkNeeJa | X24: 0
A26: aantal jaren te betalen | D26: =IF(E5>E9,4,0) -> 0 | H26: =IF(D13="nee",0,IF(E5>E9,4,1)) -> 1 | L26: 19 | O26: =IF(E5>E9,4,1) -> 1 | T26: Klant | U26: BTW | V26: KOR | W26: KEY
D27: = | H27: = | L27: = | O27: = | T27: Particulier | U27: Ja | V27: Nee | W27: =T27&U27&V27 -> ParticulierJaNee | X27: =D26 -> 0
T28: Particulier | U28: Ja | V28: Ja | W28: =T28&U28&V28 -> ParticulierJaJa | X28: =H26 -> 1
A29: Kosten aangifte | D29: 50 | H29: 50 | L29: 0 | O29: 0 | T29: Particulier | U29: Nee | V29: Nee | W29: =T29&U29&V29 -> ParticulierNeeNee | X29: 0
D30: = | H30: = | L30: = | O30: = | T30: Particulier | U30: Nee | V30: Ja | W30: =T30&U30&V30 -> ParticulierNeeJa | X30: 0
T31: Zakelijk | U31: Ja | V31: Ja | W31: =T31&U31&V31 -> ZakelijkJaJa | X31: =H26 -> 1
B32: Aanpassingen | T32: Zakelijk | U32: Ja | V32: Nee | W32: =T32&U32&V32 -> ZakelijkJaNee | X32: =L26 -> 19
B33: Producten kolom P bedrag gebruiken voor BTW berekening | T33: Zakelijk | U33: Nee | V33: Nee | W33: =T33&U33&V33 -> ZakelijkNeeNee | X33: 0
B34: Als BTW is groter dan 2494 dan 5 jaar 15 euro per kWh | T34: Zakelijk | U34: Nee | V34: Ja | W34: =T34&U34&V34 -> ZakelijkNeeJa | X34: 0
B35: Als BTW is kleiner dan 2495 dan 1 jaar 15 euro per kWh
B38: Totaal | D38: =D23-D26*(D21+D29) -> 2102 | H38: =H23-H26*(H21+H29) -> 1724 | L38: =L23-L26*(L21+L29) -> -3957 | O38: =O23-O26*(O21+O29) -> 1947
D39: = | H39: = | L39: = | O39: =
D41: =IF(D38<0,"nadeel ! ","voordeel ") -> voordeel | H41: =IF(H38<0,"nadeel ! ","voordeel ") -> voordeel | L41: =IF(L38<0,"nadeel ! ","voordeel ") -> nadeel ! | O41: =IF(O38<0,"nadeel ! ","voordeel ") -> voordeel
B44: Klant | C44: BTW | D44: KOR | S44: rgl | T44: Klant | U44: BTW | V44: KOR | W44: KEY
A45: rg1 | B45: =IF(ISERROR(VLOOKUP($A45,INDIRECT($W$8),2,FALSE)),"?",VLOOKUP($A45,INDIRECT($W$8),2,FALSE)) -> Particulier | C45: =IF(ISERROR(VLOOKUP($A45,INDIRECT($W$8),3,FALSE)),"?",VLOOKUP($A45,INDIRECT($W$8),3,FALSE)) -> Ja | D45: =IF(ISERROR(VLOOKUP($A45,INDIRECT($W$8),4,FALSE)),"?",VLOOKUP($A45,INDIRECT($W$8),4,FALSE)) -> Nee | E45: =IF(ISERROR(VLOOKUP($A45,INDIRECT($W$8),6,FALSE)),"?",VLOOKUP($A45,INDIRECT($W$8),6,FALSE)) -> € 2430 minus € 15 per kWh capaciteit (€ 328). | S45: rg1 | T45: Particulier | U45: Ja | V45: Nee | W45: =T45&U45&V45 -> ParticulierJaNee | X45: =IF(D13="nee","Geen teruggave BTW op aanschaf batterijen",CONCATENATE(J6,IF(D19=E9,J5,J7))) -> € 2430 minus € 15 per kWh capaciteit (€ 328).
A46: rg2 | B46: =IF(ISERROR(VLOOKUP($A46,INDIRECT($W$8),2,FALSE)),"?",VLOOKUP($A46,INDIRECT($W$8),2,FALSE)) -> Particulier | C46: =IF(ISERROR(VLOOKUP($A46,INDIRECT($W$8),3,FALSE)),"?",VLOOKUP($A46,INDIRECT($W$8),3,FALSE)) -> Ja | D46: =IF(ISERROR(VLOOKUP($A46,INDIRECT($W$8),4,FALSE)),"?",VLOOKUP($A46,INDIRECT($W$8),4,FALSE)) -> Nee | E46: =IF(ISERROR(VLOOKUP($A46,INDIRECT($W$8),6,FALSE)),"?",VLOOKUP($A46,INDIRECT($W$8),6,FALSE)) | S46: rg2 | T46: Particulier | U46: Ja | V46: Nee | W46: =T46&U46&V46 -> ParticulierJaNee | X46: =IF(D26=0,"",CONCATENATE("Daarna nog ",D26," jaar € ",D21," af te dragen BTW."))
A47: rg3 | B47: =IF(ISERROR(VLOOKUP($A47,INDIRECT($W$8),2,FALSE)),"?",VLOOKUP($A47,INDIRECT($W$8),2,FALSE)) -> Particulier | C47: =IF(ISERROR(VLOOKUP($A47,INDIRECT($W$8),3,FALSE)),"?",VLOOKUP($A47,INDIRECT($W$8),3,FALSE)) -> Ja | D47: =IF(ISERROR(VLOOKUP($A47,INDIRECT($W$8),4,FALSE)),"?",VLOOKUP($A47,INDIRECT($W$8),4,FALSE)) -> Nee | E47: =IF(ISERROR(VLOOKUP($A47,INDIRECT($W$8),6,FALSE)),"?",VLOOKUP($A47,INDIRECT($W$8),6,FALSE)) | S47: rg3 | T47: Particulier | U47: Ja | V47: Nee | W47: =T47&U47&V47 -> ParticulierJaNee | X47: =IF(D26=0,"",CONCATENATE("Jaarlijkse kosten BTW-aangifte € ",D29))
A48: rg4 | B48: =IF(ISERROR(VLOOKUP($A48,INDIRECT($W$8),2,FALSE)),"?",VLOOKUP($A48,INDIRECT($W$8),2,FALSE)) -> Particulier | C48: =IF(ISERROR(VLOOKUP($A48,INDIRECT($W$8),3,FALSE)),"?",VLOOKUP($A48,INDIRECT($W$8),3,FALSE)) -> Ja | D48: =IF(ISERROR(VLOOKUP($A48,INDIRECT($W$8),4,FALSE)),"?",VLOOKUP($A48,INDIRECT($W$8),4,FALSE)) -> Nee | E48: =IF(ISERROR(VLOOKUP($A48,INDIRECT($W$8),6,FALSE)),"?",VLOOKUP($A48,INDIRECT($W$8),6,FALSE)) | S48: rg4 | T48: Particulier | U48: Ja | V48: Nee | W48: =T48&U48&V48 -> ParticulierJaNee | X48: =IF(D26=0,"",CONCATENATE("Totaal BTW-",D41,"per saldo € ",D38))
A49: rg5 | B49: =IF(ISERROR(VLOOKUP($A49,INDIRECT($W$8),2,FALSE)),"?",VLOOKUP($A49,INDIRECT($W$8),2,FALSE)) -> Particulier | C49: =IF(ISERROR(VLOOKUP($A49,INDIRECT($W$8),3,FALSE)),"?",VLOOKUP($A49,INDIRECT($W$8),3,FALSE)) -> Ja | D49: =IF(ISERROR(VLOOKUP($A49,INDIRECT($W$8),4,FALSE)),"?",VLOOKUP($A49,INDIRECT($W$8),4,FALSE)) -> Nee | E49: =IF(ISERROR(VLOOKUP($A49,INDIRECT($W$8),6,FALSE)),"?",VLOOKUP($A49,INDIRECT($W$8),6,FALSE)) | S49: rg5 | T49: Particulier | U49: Ja | V49: Nee | W49: =T49&U49&V49 -> ParticulierJaNee
A50: rg6 | B50: =IF(ISERROR(VLOOKUP($A50,INDIRECT($W$8),2,FALSE)),"?",VLOOKUP($A50,INDIRECT($W$8),2,FALSE)) -> Particulier | C50: =IF(ISERROR(VLOOKUP($A50,INDIRECT($W$8),3,FALSE)),"?",VLOOKUP($A50,INDIRECT($W$8),3,FALSE)) -> Ja | D50: =IF(ISERROR(VLOOKUP($A50,INDIRECT($W$8),4,FALSE)),"?",VLOOKUP($A50,INDIRECT($W$8),4,FALSE)) -> Nee | E50: =IF(ISERROR(VLOOKUP($A50,INDIRECT($W$8),6,FALSE)),"?",VLOOKUP($A50,INDIRECT($W$8),6,FALSE)) | S50: rg6 | T50: Particulier | U50: Ja | V50: Nee | W50: =T50&U50&V50 -> ParticulierJaNee | X50: =IF(D38<0,"In de berekening van de kosten wordt ervan uitgegaan, dat er","")
A51: rg7 | B51: =IF(ISERROR(VLOOKUP($A51,INDIRECT($W$8),2,FALSE)),"?",VLOOKUP($A51,INDIRECT($W$8),2,FALSE)) -> Particulier | C51: =IF(ISERROR(VLOOKUP($A51,INDIRECT($W$8),3,FALSE)),"?",VLOOKUP($A51,INDIRECT($W$8),3,FALSE)) -> Ja | D51: =IF(ISERROR(VLOOKUP($A51,INDIRECT($W$8),4,FALSE)),"?",VLOOKUP($A51,INDIRECT($W$8),4,FALSE)) -> Nee | E51: =IF(ISERROR(VLOOKUP($A51,INDIRECT($W$8),6,FALSE)),"?",VLOOKUP($A51,INDIRECT($W$8),6,FALSE)) | S51: rg7 | T51: Particulier | U51: Ja | V51: Nee | W51: =T51&U51&V51 -> ParticulierJaNee | X51: =IF(D38<0,"geen BTW teruggevraagd wordt, omdat dit geen voordeel oplevert","")
A52: rg8 | B52: =IF(ISERROR(VLOOKUP($A52,INDIRECT($W$8),2,FALSE)),"?",VLOOKUP($A52,INDIRECT($W$8),2,FALSE)) -> Particulier | C52: =IF(ISERROR(VLOOKUP($A52,INDIRECT($W$8),3,FALSE)),"?",VLOOKUP($A52,INDIRECT($W$8),3,FALSE)) -> Ja | D52: =IF(ISERROR(VLOOKUP($A52,INDIRECT($W$8),4,FALSE)),"?",VLOOKUP($A52,INDIRECT($W$8),4,FALSE)) -> Nee | E52: =IF(ISERROR(VLOOKUP($A52,INDIRECT($W$8),6,FALSE)),"?",VLOOKUP($A52,INDIRECT($W$8),6,FALSE)) -> 2102 | S52: rg8 | T52: Particulier | U52: Ja | V52: Nee | W52: =T52&U52&V52 -> ParticulierJaNee | X52: =MAX(0,D38) -> 2102
S54: rgl | T54: Klant | U54: BTW | V54: KOR | W54: KEY
S55: rg1 | T55: Particulier | U55: Ja | V55: Ja | W55: =T55&U55&V55 -> ParticulierJaJa | X55: =IF(D13="nee","Geen teruggave BTW op aanschaf batterijen",CONCATENATE(K6,IF(D19=E9,J5,J7))) -> 1e jaar : € 2430 minus € 15 per kWh capaciteit (€ 328).
S56: rg2 | T56: Particulier | U56: Ja | V56: Ja | W56: =T56&U56&V56 -> ParticulierJaJa | X56: =IF(H26=0,"",CONCATENATE("Daarna nog ",H26," jaar € ",H21," af te dragen BTW.")) -> Daarna nog 1 jaar € 328 af te dragen BTW.
S57: rg3 | T57: Particulier | U57: Ja | V57: Ja | W57: =T57&U57&V57 -> ParticulierJaJa | X57: =IF(H26=0,"",CONCATENATE("Jaarlijkse kosten BTW-aangifte € ",H29)) -> Jaarlijkse kosten BTW-aangifte € 50
S58: rg4 | T58: Particulier | U58: Ja | V58: Ja | W58: =T58&U58&V58 -> ParticulierJaJa | X58: =IF(H26=0,"",CONCATENATE("Totaal BTW-",H41,"per saldo € ",H38)) -> Totaal BTW-voordeel per saldo € 1724
S59: rg5 | T59: Particulier | U59: Ja | V59: Ja | W59: =T59&U59&V59 -> ParticulierJaJa
S60: rg6 | T60: Particulier | U60: Ja | V60: Ja | W60: =T60&U60&V60 -> ParticulierJaJa | X60: =IF(D38<0,"In de berekening van de kosten wordt ervan uitgegaan, dat er","")
S61: rg7 | T61: Particulier | U61: Ja | V61: Ja | W61: =T61&U61&V61 -> ParticulierJaJa | X61: =IF(D38<0,"geen BTW teruggevraagd wordt, omdat dit geen voordeel oplevert","")
S62: rg8 | T62: Particulier | U62: Ja | V62: Ja | W62: =T62&U62&V62 -> ParticulierJaJa | X62: =MAX(0,H38) -> 1724
S64: rgl | T64: Klant | U64: BTW | V64: KOR | W64: KEY
S65: rg1 | T65: Particulier | U65: Nee | V65: Nee | W65: =T65&U65&V65 -> ParticulierNeeNee | X65: =J3 -> Geen teruggave BTW op aanschaf batterijen.
S66: rg2 | T66: Particulier | U66: Nee | V66: Nee | W66: =T66&U66&V66 -> ParticulierNeeNee
S67: rg3 | T67: Particulier | U67: Nee | V67: Nee | W67: =T67&U67&V67 -> ParticulierNeeNee
S68: rg4 | T68: Particulier | U68: Nee | V68: Nee | W68: =T68&U68&V68 -> ParticulierNeeNee
S69: rg5 | T69: Particulier | U69: Nee | V69: Nee | W69: =T69&U69&V69 -> ParticulierNeeNee
S70: rg6 | T70: Particulier | U70: Nee | V70: Nee | W70: =T70&U70&V70 -> ParticulierNeeNee
S71: rg7 | T71: Particulier | U71: Nee | V71: Nee | W71: =T71&U71&V71 -> ParticulierNeeNee
S72: rg8 | T72: Particulier | U72: Nee | V72: Nee | W72: =T72&U72&V72 -> ParticulierNeeNee | X72: 0
S74: rgl | T74: Klant | U74: BTW | V74: KOR | W74: KEY
S75: rg1 | T75: Particulier | U75: Nee | V75: Ja | W75: =T75&U75&V75 -> ParticulierNeeJa | X75: =J3 -> Geen teruggave BTW op aanschaf batterijen.
S76: rg2 | T76: Particulier | U76: Nee | V76: Ja | W76: =T76&U76&V76 -> ParticulierNeeJa
S77: rg3 | T77: Particulier | U77: Nee | V77: Ja | W77: =T77&U77&V77 -> ParticulierNeeJa
S78: rg4 | T78: Particulier | U78: Nee | V78: Ja | W78: =T78&U78&V78 -> ParticulierNeeJa
S79: rg5 | T79: Particulier | U79: Nee | V79: Ja | W79: =T79&U79&V79 -> ParticulierNeeJa
S80: rg6 | T80: Particulier | U80: Nee | V80: Ja | W80: =T80&U80&V80 -> ParticulierNeeJa
S81: rg7 | T81: Particulier | U81: Nee | V81: Ja | W81: =T81&U81&V81 -> ParticulierNeeJa
S82: rg8 | T82: Particulier | U82: Nee | V82: Ja | W82: =T82&U82&V82 -> ParticulierNeeJa | X82: 0
S84: rgl | T84: Klant | U84: BTW | V84: KOR | W84: KEY
S85: rg1 | T85: Zakelijk | U85: Ja | V85: Ja | W85: =T85&U85&V85 -> ZakelijkJaJa | X85: =J11 -> 1e jaar : € 2430 minus af te dragen BTW teruglevering € 328 (schatting).
S86: rg2 | T86: Zakelijk | U86: Ja | V86: Ja | W86: =T86&U86&V86 -> ZakelijkJaJa | X86: =CONCATENATE("Daarna nog ",H26," jaar € ",L21," afdracht van BTW teruglevering (schatting).") -> Daarna nog 1 jaar € 328 afdracht van BTW teruglevering (schatting).
S87: rg3 | T87: Zakelijk | U87: Ja | V87: Ja | W87: =T87&U87&V87 -> ZakelijkJaJa | X87: =IF(O26=0,"",CONCATENATE("Totaal BTW-",O41,IF(O26=19,"in deze 20 jaar","")," per saldo € ",O38)) -> Totaal BTW-voordeel per saldo € 1947
S88: rg4 | T88: Zakelijk | U88: Ja | V88: Ja | W88: =T88&U88&V88 -> ZakelijkJaJa
S89: rg5 | T89: Zakelijk | U89: Ja | V89: Ja | W89: =T89&U89&V89 -> ZakelijkJaJa | X89: De zakelijke BTW is mede afhankelijk van andere factoren.
S90: rg6 | T90: Zakelijk | U90: Ja | V90: Ja | W90: =T90&U90&V90 -> ZakelijkJaJa | X90: Neem contact op met de accountant voor de exacte berekening.
S91: rg7 | T91: Zakelijk | U91: Ja | V91: Ja | W91: =T91&U91&V91 -> ZakelijkJaJa
S92: rg8 | T92: Zakelijk | U92: Ja | V92: Ja | W92: =T92&U92&V92 -> ZakelijkJaJa | X92: =O38 -> 1947
S94: rgl | T94: Klant | U94: BTW | V94: KOR | W94: KEY
S95: rg1 | T95: Zakelijk | U95: Ja | V95: Nee | W95: =T95&U95&V95 -> ZakelijkJaNee | X95: =J9 -> 1e jaar : € 2603 minus af te dragen BTW teruglevering € 328 (schatting).
S96: rg2 | T96: Zakelijk | U96: Ja | V96: Nee | W96: =T96&U96&V96 -> ZakelijkJaNee | X96: =CONCATENATE("Daarna nog ieder jaar € ",L21," afdracht van BTW teruglevering (schatting).") -> Daarna nog ieder jaar € 328 afdracht van BTW teruglevering (schatting).
S97: rg3 | T97: Zakelijk | U97: Ja | V97: Nee | W97: =T97&U97&V97 -> ZakelijkJaNee | X97: =IF(L26=0,"",CONCATENATE("Totaal BTW-",L41,"in deze 20 jaar per saldo € ",L38)) -> Totaal BTW-nadeel ! in deze 20 jaar per saldo € -3957
S98: rg4 | T98: Zakelijk | U98: Ja | V98: Nee | W98: =T98&U98&V98 -> ZakelijkJaNee
S99: rg5 | T99: Zakelijk | U99: Ja | V99: Nee | W99: =T99&U99&V99 -> ZakelijkJaNee | X99: De zakelijke BTW is mede afhankelijk van andere factoren.
S100: rg6 | T100: Zakelijk | U100: Ja | V100: Nee | W100: =T100&U100&V100 -> ZakelijkJaNee | X100: Neem contact op met de accountant voor de exacte berekening.
S101: rg7 | T101: Zakelijk | U101: Ja | V101: Nee | W101: =T101&U101&V101 -> ZakelijkJaNee
S102: rg8 | T102: Zakelijk | U102: Ja | V102: Nee | W102: =T102&U102&V102 -> ZakelijkJaNee | X102: =L38 -> -3957
S104: rgl | T104: Klant | U104: BTW | V104: KOR | W104: KEY
S105: rg1 | T105: Zakelijk | U105: Nee | V105: Nee | W105: =T105&U105&V105 -> ZakelijkNeeNee | X105: =J3 -> Geen teruggave BTW op aanschaf batterijen.
S106: rg2 | T106: Zakelijk | U106: Nee | V106: Nee | W106: =T106&U106&V106 -> ZakelijkNeeNee
S107: rg3 | T107: Zakelijk | U107: Nee | V107: Nee | W107: =T107&U107&V107 -> ZakelijkNeeNee
S108: rg4 | T108: Zakelijk | U108: Nee | V108: Nee | W108: =T108&U108&V108 -> ZakelijkNeeNee
S109: rg5 | T109: Zakelijk | U109: Nee | V109: Nee | W109: =T109&U109&V109 -> ZakelijkNeeNee
S110: rg6 | T110: Zakelijk | U110: Nee | V110: Nee | W110: =T110&U110&V110 -> ZakelijkNeeNee
S111: rg7 | T111: Zakelijk | U111: Nee | V111: Nee | W111: =T111&U111&V111 -> ZakelijkNeeNee
S112: rg8 | T112: Zakelijk | U112: Nee | V112: Nee | W112: =T112&U112&V112 -> ZakelijkNeeNee | X112: 0
S114: rgl | T114: Klant | U114: BTW | V114: KOR | W114: KEY
S115: rg1 | T115: Zakelijk | U115: Nee | V115: Ja | W115: =T115&U115&V115 -> ZakelijkNeeJa | X115: =J3 -> Geen teruggave BTW op aanschaf batterijen.
S116: rg2 | T116: Zakelijk | U116: Nee | V116: Ja | W116: =T116&U116&V116 -> ZakelijkNeeJa
S117: rg3 | T117: Zakelijk | U117: Nee | V117: Ja | W117: =T117&U117&V117 -> ZakelijkNeeJa
S118: rg4 | T118: Zakelijk | U118: Nee | V118: Ja | W118: =T118&U118&V118 -> ZakelijkNeeJa
...

Sheet Jaargegevens
L2: datum van gas af | M2: =IF(ISNUMBER(Calculator!R77),Calculator!R77,E3) -> 54789
D3: startdatum | E3: =IF(ISNUMBER(Calculator!R110),Calculator!R110,NOW()) -> 45992 | F3: =MONTH(E3)+1 -> 13 | L3: dagen tot van gas af | M3: =IF(M2<E3,0,M2-E3) -> 8797 | O3: =IF(M3=0,"al van gas af bij installatie batterijen", "")
D5: vanaf jaar | E5: =YEAR(E3) -> 2025 | L5: huidig contract dynamisch | M5: =IF(Calculator!R25<>"Dynamisch","nee","ja") -> nee
D7: verdeling jaar | E7: =Opbrengsten!C5 -> 0.084931507 | F7: =1-E7 -> 0.91506849 | L7: laatste jaar saldering | M7: =IF(M5="nee",Stamgegevens!R2,0) -> 2026
L9: energiebelasting dit jaar | M9: =VLOOKUP($A14,Stamgegevens!$A$8:$AE$36,Stamgegevens!$J$1) -> 0.12286
O10: excl. en.bel. | P10: excl. en.bel. | R10: handel | Z10: correctie
F11: energie | H11: energie | J11: energie | L11: vastrecht | M11: vastrecht | O11: leverings | P11: opslag | Q11: leverings | R11: leverings | S11: opslag | U11: dagen | V11: dagen | X11: omreken | Z11: tarief | AB11: effectieve | AD11: correctie | AF11: uit
D12: jaarlijkse | F12: belasting | G12: vanaf | H12: belasting | I12: percentage | J12: belasting | L12: stroom | M12: gas | O12: kosten | P12: kosten | Q12: kosten | R12: kosten | S12: terug | U12: tot van | V12: tot | X12: factor | Z12: terug | AB12: minuten | AD12: tarief | AF12: betalings
A13: jaar 1 | D13: inflatie | F13: incl BTW | G13: KwH | H13: incl BTW | I13: saldering | J13: na saldering | L13: nieuw | M13: nieuw | O13: laag | P13: laag | Q13: hoog | R13: hoog | S13: levering | U13: gas af | V13: el. auto | X13: gas | Z13: levering | AB13: per kwartier | AD13: handel | AF13: %
A14: =E5 -> 2025 | B14: 1 | D14: =VLOOKUP($A14,Stamgegevens!$A$8:$AE$36,Stamgegevens!$H$1) -> 0.032 | F14: =VLOOKUP($A14,Stamgegevens!$A$8:$AE$36,Stamgegevens!$J$1) -> 0.12286 | G14: =VLOOKUP($A14,Stamgegevens!$A$8:$AE$36,Stamgegevens!$K$1) -> 10000 | H14: =VLOOKUP($A14,Stamgegevens!$A$8:$AE$36,Stamgegevens!$L$1) -> 0.08394 | I14: =VLOOKUP($A14,Stamgegevens!$A$8:$AE$36,Stamgegevens!$N$1) -> 1 | J14: =F14*I14 -> 0.12286 | L14: =VLOOKUP($A14,Stamgegevens!$A$8:$AE$36,Stamgegevens!$P$1) -> 5.99 | M14: =VLOOKUP($A14,Stamgegevens!$A$8:$AE$36,Stamgegevens!$Q$1) -> 5.99 | O14: =VLOOKUP($A14,Stamgegevens!$A$8:$AE$36,Stamgegevens!$S$1) -> 0.01 | P14: =VLOOKUP(Calculator!R112,Keuzemenu!C24:E26,2) -> 0.02 | Q14: =VLOOKUP($A14,Stamgegevens!$A$8:$AE$36,Stamgegevens!$U$1) -> 0 | R14: =VLOOKUP($A14,Stamgegevens!$A$8:$AE$36,Stamgegevens!$T$1) -> 0.15 | S14: =VLOOKUP(Calculator!R112,Keuzemenu!C24:E26,3) -> 0 | U14: =IF($M$3=0,$M$3,$M$3-365*$E$7) -> 8766 | X14: =VLOOKUP($A14,Stamgegevens!$A$8:$AE$36,Stamgegevens!$W$1) -> 3.5 | Z14: =VLOOKUP($A14,Stamgegevens!$A$8:$AE$36,Stamgegevens!$Y$1) -> -0.02 | AB14: =VLOOKUP($A14,Stamgegevens!$A$8:$AE$36,Stamgegevens!$AA$1) -> 14 | AD14: =VLOOKUP($A14,Stamgegevens!$A$8:$AE$36,Stamgegevens!$AC$1) -> 0.2 | AF14: =VLOOKUP($A14,Stamgegevens!$A$8:$AE$36,Stamgegevens!$AE$1) -> 0.85
A15: =A14+1 -> 2026 | B15: 2 | D15: =VLOOKUP($A15,Stamgegevens!$A$8:$AE$36,Stamgegevens!$H$1) -> 0.028 | F15: =VLOOKUP($A15,Stamgegevens!$A$8:$AE$36,Stamgegevens!$J$1) -> 0.11046 | G15: =VLOOKUP($A15,Stamgegevens!$A$8:$AE$36,Stamgegevens!$K$1) -> 10000 | H15: =VLOOKUP($A15,Stamgegevens!$A$8:$AE$36,Stamgegevens!$L$1) -> 0.08394 | I15: =VLOOKUP($A15,Stamgegevens!$A$8:$AE$36,Stamgegevens!$N$1) -> 1 | J15: =F15*I15 -> 0.11046 | L15: =VLOOKUP($A15,Stamgegevens!$A$8:$AE$36,Stamgegevens!$P$1) -> 6.18168 | M15: =VLOOKUP($A15,Stamgegevens!$A$8:$AE$36,Stamgegevens!$Q$1) -> 6.18168 | O15: =VLOOKUP($A15,Stamgegevens!$A$8:$AE$36,Stamgegevens!$S$1) -> 0.01032 | P15: =P14 -> 0.02 | Q15: =VLOOKUP($A15,Stamgegevens!$A$8:$AE$36,Stamgegevens!$U$1) -> 0 | R15: =VLOOKUP($A15,Stamgegevens!$A$8:$AE$36,Stamgegevens!$T$1) -> 0.1548 | S15: =S14 -> 0 | U15: =IF($M$3=0,$M$3,U14-365) -> 8401 | X15: =VLOOKUP($A15,Stamgegevens!$A$8:$AE$36,Stamgegevens!$W$1) -> 3.5 | Z15: =VLOOKUP($A15,Stamgegevens!$A$8:$AE$36,Stamgegevens!$Y$1) -> -0.02 | AB15: =VLOOKUP($A15,Stamgegevens!$A$8:$AE$36,Stamgegevens!$AA$1) -> 14 | AD15: =VLOOKUP($A15,Stamgegevens!$A$8:$AE$36,Stamgegevens!$AC$1) -> 0.2 | AF15: =VLOOKUP($A15,Stamgegevens!$A$8:$AE$36,Stamgegevens!$AE$1) -> 0.85
A16: =A15+1 -> 2027 | B16: 3 | D16: =VLOOKUP($A16,Stamgegevens!$A$8:$AE$36,Stamgegevens!$H$1) -> 0.025 | F16: =VLOOKUP($A16,Stamgegevens!$A$8:$AE$36,Stamgegevens!$J$1) -> 0.11046 | G16: =VLOOKUP($A16,Stamgegevens!$A$8:$AE$36,Stamgegevens!$K$1) -> 10000 | H16: =VLOOKUP($A16,Stamgegevens!$A$8:$AE$36,Stamgegevens!$L$1) -> 0.08394 | I16: =VLOOKUP($A16,Stamgegevens!$A$8:$AE$36,Stamgegevens!$N$1) -> 0 | J16: =F16*I16 -> 0 | L16: =VLOOKUP($A16,Stamgegevens!$A$8:$AE$36,Stamgegevens!$P$1) -> 6.354767 | M16: =VLOOKUP($A16,Stamgegevens!$A$8:$AE$36,Stamgegevens!$Q$1) -> 6.354767 | O16: =VLOOKUP($A16,Stamgegevens!$A$8:$AE$36,Stamgegevens!$S$1) -> 0.01060896 | P16: =P15 -> 0.02 | Q16: =VLOOKUP($A16,Stamgegevens!$A$8:$AE$36,Stamgegevens!$U$1) -> 0 | R16: =VLOOKUP($A16,Stamgegevens!$A$8:$AE$36,Stamgegevens!$T$1) -> 0.1591344 | S16: =S15 -> 0 | U16: =IF($M$3=0,$M$3,U15-365) -> 8036 | X16: =VLOOKUP($A16,Stamgegevens!$A$8:$AE$36,Stamgegevens!$W$1) -> 3.5 | Z16: =VLOOKUP($A16,Stamgegevens!$A$8:$AE$36,Stamgegevens!$Y$1) -> -0.02 | AB16: =VLOOKUP($A16,Stamgegevens!$A$8:$AE$36,Stamgegevens!$AA$1) -> 14 | AD16: =VLOOKUP($A16,Stamgegevens!$A$8:$AE$36,Stamgegevens!$AC$1) -> 0.2 | AF16: =VLOOKUP($A16,Stamgegevens!$A$8:$AE$36,Stamgegevens!$AE$1) -> 0.85
A17: =A16+1 -> 2028 | B17: 4 | D17: =VLOOKUP($A17,Stamgegevens!$A$8:$AE$36,Stamgegevens!$H$1) -> 0.025 | F17: =VLOOKUP($A17,Stamgegevens!$A$8:$AE$36,Stamgegevens!$J$1) -> 0.11046 | G17: =VLOOKUP($A17,Stamgegevens!$A$8:$AE$36,Stamgegevens!$K$1) -> 10000 | H17: =VLOOKUP($A17,Stamgegevens!$A$8:$AE$36,Stamgegevens!$L$1) -> 0.08394 | I17: =VLOOKUP($A17,Stamgegevens!$A$8:$AE$36,Stamgegevens!$N$1) -> 0 | J17: =F17*I17 -> 0 | L17: =VLOOKUP($A17,Stamgegevens!$A$8:$AE$36,Stamgegevens!$P$1) -> 6.5136362 | M17: =VLOOKUP($A17,Stamgegevens!$A$8:$AE$36,Stamgegevens!$Q$1) -> 6.5136362 | O17: =VLOOKUP($A17,Stamgegevens!$A$8:$AE$36,Stamgegevens!$S$1) -> 0.010874184 | P17: =P16 -> 0.02 | Q17: =VLOOKUP($A17,Stamgegevens!$A$8:$AE$36,Stamgegevens!$U$1) -> 0 | R17: =VLOOKUP($A17,Stamgegevens!$A$8:$AE$36,Stamgegevens!$T$1) -> 0.16311276 | S17: =S16 -> 0 | U17: =IF($M$3=0,$M$3,U16-365) -> 7671 | X17: =VLOOKUP($A17,Stamgegevens!$A$8:$AE$36,Stamgegevens!$W$1) -> 3.5 | Z17: =VLOOKUP($A17,Stamgegevens!$A$8:$AE$36,Stamgegevens!$Y$1) -> -0.02 | AB17: =VLOOKUP($A17,Stamgegevens!$A$8:$AE$36,Stamgegevens!$AA$1) -> 14 | AD17: =VLOOKUP($A17,Stamgegevens!$A$8:$AE$36,Stamgegevens!$AC$1) -> 0.2 | AF17: =VLOOKUP($A17,Stamgegevens!$A$8:$AE$36,Stamgegevens!$AE$1) -> 0.85
A18: =A17+1 -> 2029 | B18: 5 | D18: =VLOOKUP($A18,Stamgegevens!$A$8:$AE$36,Stamgegevens!$H$1) -> 0.025 | F18: =VLOOKUP($A18,Stamgegevens!$A$8:$AE$36,Stamgegevens!$J$1) -> 0.11046 | G18: =VLOOKUP($A18,Stamgegevens!$A$8:$AE$36,Stamgegevens!$K$1) -> 10000 | H18: =VLOOKUP($A18,Stamgegevens!$A$8:$AE$36,Stamgegevens!$L$1) -> 0.08394 | I18: =VLOOKUP($A18,Stamgegevens!$A$8:$AE$36,Stamgegevens!$N$1) -> 0 | J18: =F18*I18 -> 0 | L18: =VLOOKUP($A18,Stamgegevens!$A$8:$AE$36,Stamgegevens!$P$1) -> 6.6764771 | M18: =VLOOKUP($A18,Stamgegevens!$A$8:$AE$36,Stamgegevens!$Q$1) -> 6.6764771 | O18: =VLOOKUP($A18,Stamgegevens!$A$8:$AE$36,Stamgegevens!$S$1) -> 0.011146039 | P18: =P17 -> 0.02 | Q18: =VLOOKUP($A18,Stamgegevens!$A$8:$AE$36,Stamgegevens!$U$1) -> 0 | R18: =VLOOKUP($A18,Stamgegevens!$A$8:$AE$36,Stamgegevens!$T$1) -> 0.16719058 | S18: =S17 -> 0 | U18: =IF($M$3=0,$M$3,U17-365) -> 7306 | X18: =VLOOKUP($A18,Stamgegevens!$A$8:$AE$36,Stamgegevens!$W$1) -> 3.5 | Z18: =VLOOKUP($A18,Stamgegevens!$A$8:$AE$36,Stamgegevens!$Y$1) -> -0.02 | AB18: =VLOOKUP($A18,Stamgegevens!$A$8:$AE$36,Stamgegevens!$AA$1) -> 14 | AD18: =VLOOKUP($A18,Stamgegevens!$A$8:$AE$36,Stamgegevens!$AC$1) -> 0.2 | AF18: =VLOOKUP($A18,Stamgegevens!$A$8:$AE$36,Stamgegevens!$AE$1) -> 0.85
A19: =A18+1 -> 2030 | B19: 6 | D19: =VLOOKUP($A19,Stamgegevens!$A$8:$AE$36,Stamgegevens!$H$1) -> 0.025 | F19: =VLOOKUP($A19,Stamgegevens!$A$8:$AE$36,Stamgegevens!$J$1) -> 0.11046 | G19: =VLOOKUP($A19,Stamgegevens!$A$8:$AE$36,Stamgegevens!$K$1) -> 10000 | H19: =VLOOKUP($A19,Stamgegevens!$A$8:$AE$36,Stamgegevens!$L$1) -> 0.08394 | I19: =VLOOKUP($A19,Stamgegevens!$A$8:$AE$36,Stamgegevens!$N$1) -> 0 | J19: =F19*I19 -> 0 | L19: =VLOOKUP($A19,Stamgegevens!$A$8:$AE$36,Stamgegevens!$P$1) -> 6.843389 | M19: =VLOOKUP($A19,Stamgegevens!$A$8:$AE$36,Stamgegevens!$Q$1) -> 6.843389 | O19: =VLOOKUP($A19,Stamgegevens!$A$8:$AE$36,Stamgegevens!$S$1) -> 0.01142469 | P19: =P18 -> 0.02 | Q19: =VLOOKUP($A19,Stamgegevens!$A$8:$AE$36,Stamgegevens!$U$1) -> 0 | R19: =VLOOKUP($A19,Stamgegevens!$A$8:$AE$36,Stamgegevens!$T$1) -> 0.17137034 | S19: =S18 -> 0 | U19: =IF($M$3=0,$M$3,U18-365) -> 6941 | X19: =VLOOKUP($A19,Stamgegevens!$A$8:$AE$36,Stamgegevens!$W$1) -> 3.5 | Z19: =VLOOKUP($A19,Stamgegevens!$A$8:$AE$36,Stamgegevens!$Y$1) -> -0.02 | AB19: =VLOOKUP($A19,Stamgegevens!$A$8:$AE$36,Stamgegevens!$AA$1) -> 14 | AD19: =VLOOKUP($A19,Stamgegevens!$A$8:$AE$36,Stamgegevens!$AC$1) -> 0.2 | AF19: =VLOOKUP($A19,Stamgegevens!$A$8:$AE$36,Stamgegevens!$AE$1) -> 0.85
A20: =A19+1 -> 2031 | B20: 7 | D20: =VLOOKUP($A20,Stamgegevens!$A$8:$AE$36,Stamgegevens!$H$1) -> 0.025 | F20: =VLOOKUP($A20,Stamgegevens!$A$8:$AE$36,Stamgegevens!$J$1) -> 0.11046 | G20: =VLOOKUP($A20,Stamgegevens!$A$8:$AE$36,Stamgegevens!$K$1) -> 10000 | H20: =VLOOKUP($A20,Stamgegevens!$A$8:$AE$36,Stamgegevens!$L$1) -> 0.08394 | I20: =VLOOKUP($A20,Stamgegevens!$A$8:$AE$36,Stamgegevens!$N$1) -> 0 | J20: =F20*I20 -> 0 | L20: =VLOOKUP($A20,Stamgegevens!$A$8:$AE$36,Stamgegevens!$P$1) -> 7.0144738 | M20: =VLOOKUP($A20,Stamgegevens!$A$8:$AE$36,Stamgegevens!$Q$1) -> 7.0144738 | O20: =VLOOKUP($A20,Stamgegevens!$A$8:$AE$36,Stamgegevens!$S$1) -> 0.011710307 | P20: =P19 -> 0.02 | Q20: =VLOOKUP($A20,Stamgegevens!$A$8:$AE$36,Stamgegevens!$U$1) -> 0 | R20: =VLOOKUP($A20,Stamgegevens!$A$8:$AE$36,Stamgegevens!$T$1) -> 0.1756546 | S20: =S19 -> 0 | U20: =IF($M$3=0,$M$3,U19-365) -> 6576 | X20: =VLOOKUP($A20,Stamgegevens!$A$8:$AE$36,Stamgegevens!$W$1) -> 3.5 | Z20: =VLOOKUP($A20,Stamgegevens!$A$8:$AE$36,Stamgegevens!$Y$1) -> -0.02 | AB20: =VLOOKUP($A20,Stamgegevens!$A$8:$AE$36,Stamgegevens!$AA$1) -> 14 | AD20: =VLOOKUP($A20,Stamgegevens!$A$8:$AE$36,Stamgegevens!$AC$1) -> 0.2 | AF20: =VLOOKUP($A20,Stamgegevens!$A$8:$AE$36,Stamgegevens!$AE$1) -> 0.85
A21: =A20+1 -> 2032 | B21: 8 | D21: =VLOOKUP($A21,Stamgegevens!$A$8:$AE$36,Stamgegevens!$H$1) -> 0.025 | F21: =VLOOKUP($A21,Stamgegevens!$A$8:$AE$36,Stamgegevens!$J$1) -> 0.11046 | G21: =VLOOKUP($A21,Stamgegevens!$A$8:$AE$36,Stamgegevens!$K$1) -> 10000 | H21: =VLOOKUP($A21,Stamgegevens!$A$8:$AE$36,Stamgegevens!$L$1) -> 0.08394 | I21: =VLOOKUP($A21,Stamgegevens!$A$8:$AE$36,Stamgegevens!$N$1) -> 0 | J21: =F21*I21 -> 0 | L21: =VLOOKUP($A21,Stamgegevens!$A$8:$AE$36,Stamgegevens!$P$1) -> 7.1898356 | M21: =VLOOKUP($A21,Stamgegevens!$A$8:$AE$36,Stamgegevens!$Q$1) -> 7.1898356 | O21: =VLOOKUP($A21,Stamgegevens!$A$8:$AE$36,Stamgegevens!$S$1) -> 0.012003064 | P21: =P20 -> 0.02 | Q21: =VLOOKUP($A21,Stamgegevens!$A$8:$AE$36,Stamgegevens!$U$1) -> 0 | R21: =VLOOKUP($A21,Stamgegevens!$A$8:$AE$36,Stamgegevens!$T$1) -> 0.18004597 | S21: =S20 -> 0 | U21: =IF($M$3=0,$M$3,U20-365) -> 6211 | X21: =VLOOKUP($A21,Stamgegevens!$A$8:$AE$36,Stamgegevens!$W$1) -> 3.5 | Z21: =VLOOKUP($A21,Stamgegevens!$A$8:$AE$36,Stamgegevens!$Y$1) -> -0.02 | AB21: =VLOOKUP($A21,Stamgegevens!$A$8:$AE$36,Stamgegevens!$AA$1) -> 14 | AD21: =VLOOKUP($A21,Stamgegevens!$A$8:$AE$36,Stamgegevens!$AC$1) -> 0.2 | AF21: =VLOOKUP($A21,Stamgegevens!$A$8:$AE$36,Stamgegevens!$AE$1) -> 0.85
A22: =A21+1 -> 2033 | B22: 9 | D22: =VLOOKUP($A22,Stamgegevens!$A$8:$AE$36,Stamgegevens!$H$1) -> 0.025 | F22: =VLOOKUP($A22,Stamgegevens!$A$8:$AE$36,Stamgegevens!$J$1) -> 0.11046 | G22: =VLOOKUP($A22,Stamgegevens!$A$8:$AE$36,Stamgegevens!$K$1) -> 10000 | H22: =VLOOKUP($A22,Stamgegevens!$A$8:$AE$36,Stamgegevens!$L$1) -> 0.08394 | I22: =VLOOKUP($A22,Stamgegevens!$A$8:$AE$36,Stamgegevens!$N$1) -> 0 | J22: =F22*I22 -> 0 | L22: =VLOOKUP($A22,Stamgegevens!$A$8:$AE$36,Stamgegevens!$P$1) -> 7.3695815 | M22: =VLOOKUP($A22,Stamgegevens!$A$8:$AE$36,Stamgegevens!$Q$1) -> 7.3695815 | O22: =VLOOKUP($A22,Stamgegevens!$A$8:$AE$36,Stamgegevens!$S$1) -> 0.012303141 | P22: =P21 -> 0.02 | Q22: =VLOOKUP($A22,Stamgegevens!$A$8:$AE$36,Stamgegevens!$U$1) -> 0 | R22: =VLOOKUP($A22,Stamgegevens!$A$8:$AE$36,Stamgegevens!$T$1) -> 0.18454712 | S22: =S21 -> 0 | U22: =IF($M$3=0,$M$3,U21-365) -> 5846 | X22: =VLOOKUP($A22,Stamgegevens!$A$8:$AE$36,Stamgegevens!$W$1) -> 3.5 | Z22: =VLOOKUP($A22,Stamgegevens!$A$8:$AE$36,Stamgegevens!$Y$1) -> -0.02 | AB22: =VLOOKUP($A22,Stamgegevens!$A$8:$AE$36,Stamgegevens!$AA$1) -> 14 | AD22: =VLOOKUP($A22,Stamgegevens!$A$8:$AE$36,Stamgegevens!$AC$1) -> 0.2 | AF22: =VLOOKUP($A22,Stamgegevens!$A$8:$AE$36,Stamgegevens!$AE$1) -> 0.85
A23: =A22+1 -> 2034 | B23: 10 | D23: =VLOOKUP($A23,Stamgegevens!$A$8:$AE$36,Stamgegevens!$H$1) -> 0.025 | F23: =VLOOKUP($A23,Stamgegevens!$A$8:$AE$36,Stamgegevens!$J$1) -> 0.11046 | G23: =VLOOKUP($A23,Stamgegevens!$A$8:$AE$36,Stamgegevens!$K$1) -> 10000 | H23: =VLOOKUP($A23,Stamgegevens!$A$8:$AE$36,Stamgegevens!$L$1) -> 0.08394 | I23: =VLOOKUP($A23,Stamgegevens!$A$8:$AE$36,Stamgegevens!$N$1) -> 0 | J23: =F23*I23 -> 0 | L23: =VLOOKUP($A23,Stamgegevens!$A$8:$AE$36,Stamgegevens!$P$1) -> 7.553821 | M23: =VLOOKUP($A23,Stamgegevens!$A$8:$AE$36,Stamgegevens!$Q$1) -> 7.553821 | O23: =VLOOKUP($A23,Stamgegevens!$A$8:$AE$36,Stamgegevens!$S$1) -> 0.01261072 | P23: =P22 -> 0.02 | Q23: =VLOOKUP($A23,Stamgegevens!$A$8:$AE$36,Stamgegevens!$U$1) -> 0 | R23: =VLOOKUP($A23,Stamgegevens!$A$8:$AE$36,Stamgegevens!$T$1) -> 0.18916079 | S23: =S22 -> 0 | U23: =IF($M$3=0,$M$3,U22-365) -> 5481 | X23: =VLOOKUP($A23,Stamgegevens!$A$8:$AE$36,Stamgegevens!$W$1) -> 3.5 | Z23: =VLOOKUP($A23,Stamgegevens!$A$8:$AE$36,Stamgegevens!$Y$1) -> -0.02 | AB23: =VLOOKUP($A23,Stamgegevens!$A$8:$AE$36,Stamgegevens!$AA$1) -> 14 | AD23: =VLOOKUP($A23,Stamgegevens!$A$8:$AE$36,Stamgegevens!$AC$1) -> 0.2 | AF23: =VLOOKUP($A23,Stamgegevens!$A$8:$AE$36,Stamgegevens!$AE$1) -> 0.85
A24: =A23+1 -> 2035 | B24: 11 | D24: =VLOOKUP($A24,Stamgegevens!$A$8:$AE$36,Stamgegevens!$H$1) -> 0.025 | F24: =VLOOKUP($A24,Stamgegevens!$A$8:$AE$36,Stamgegevens!$J$1) -> 0.11046 | G24: =VLOOKUP($A24,Stamgegevens!$A$8:$AE$36,Stamgegevens!$K$1) -> 10000 | H24: =VLOOKUP($A24,Stamgegevens!$A$8:$AE$36,Stamgegevens!$L$1) -> 0.08394 | I24: =VLOOKUP($A24,Stamgegevens!$A$8:$AE$36,Stamgegevens!$N$1) -> 0 | J24: =F24*I24 -> 0 | L24: =VLOOKUP($A24,Stamgegevens!$A$8:$AE$36,Stamgegevens!$P$1) -> 7.7426666 | M24: =VLOOKUP($A24,Stamgegevens!$A$8:$AE$36,Stamgegevens!$Q$1) -> 7.7426666 | O24: =VLOOKUP($A24,Stamgegevens!$A$8:$AE$36,Stamgegevens!$S$1) -> 0.012925988 | P24: =P23 -> 0.02 | Q24: =VLOOKUP($A24,Stamgegevens!$A$8:$AE$36,Stamgegevens!$U$1) -> 0 | R24: =VLOOKUP($A24,Stamgegevens!$A$8:$AE$36,Stamgegevens!$T$1) -> 0.19388981 | S24: =S23 -> 0 | U24: =IF($M$3=0,$M$3,U23-365) -> 5116 | X24: =VLOOKUP($A24,Stamgegevens!$A$8:$AE$36,Stamgegevens!$W$1) -> 3.5 | Z24: =VLOOKUP($A24,Stamgegevens!$A$8:$AE$36,Stamgegevens!$Y$1) -> -0.02 | AB24: =VLOOKUP($A24,Stamgegevens!$A$8:$AE$36,Stamgegevens!$AA$1) -> 14 | AD24: =VLOOKUP($A24,Stamgegevens!$A$8:$AE$36,Stamgegevens!$AC$1) -> 0.2 | AF24: =VLOOKUP($A24,Stamgegevens!$A$8:$AE$36,Stamgegevens!$AE$1) -> 0.85
A25: =A24+1 -> 2036 | B25: 12 | D25: =VLOOKUP($A25,Stamgegevens!$A$8:$AE$36,Stamgegevens!$H$1) -> 0.025 | F25: =VLOOKUP($A25,Stamgegevens!$A$8:$AE$36,Stamgegevens!$J$1) -> 0.11046 | G25: =VLOOKUP($A25,Stamgegevens!$A$8:$AE$36,Stamgegevens!$K$1) -> 10000 | H25: =VLOOKUP($A25,Stamgegevens!$A$8:$AE$36,Stamgegevens!$L$1) -> 0.08394 | I25: =VLOOKUP($A25,Stamgegevens!$A$8:$AE$36,Stamgegevens!$N$1) -> 0 | J25: =F25*I25 -> 0 | L25: =VLOOKUP($A25,Stamgegevens!$A$8:$AE$36,Stamgegevens!$P$1) -> 7.9362332 | M25: =VLOOKUP($A25,Stamgegevens!$A$8:$AE$36,Stamgegevens!$Q$1) -> 7.9362332 | O25: =VLOOKUP($A25,Stamgegevens!$A$8:$AE$36,Stamgegevens!$S$1) -> 0.013249137 | P25: =P24 -> 0.02 | Q25: =VLOOKUP($A25,Stamgegevens!$A$8:$AE$36,Stamgegevens!$U$1) -> 0 | R25: =VLOOKUP($A25,Stamgegevens!$A$8:$AE$36,Stamgegevens!$T$1) -> 0.19873706 | S25: =S24 -> 0 | U25: =IF($M$3=0,$M$3,U24-365) -> 4751 | X25: =VLOOKUP($A25,Stamgegevens!$A$8:$AE$36,Stamgegevens!$W$1) -> 3.5 | Z25: =VLOOKUP($A25,Stamgegevens!$A$8:$AE$36,Stamgegevens!$Y$1) -> -0.02 | AB25: =VLOOKUP($A25,Stamgegevens!$A$8:$AE$36,Stamgegevens!$AA$1) -> 14 | AD25: =VLOOKUP($A25,Stamgegevens!$A$8:$AE$36,Stamgegevens!$AC$1) -> 0.2 | AF25: =VLOOKUP($A25,Stamgegevens!$A$8:$AE$36,Stamgegevens!$AE$1) -> 0.85
A26: =A25+1 -> 2037 | B26: 13 | D26: =VLOOKUP($A26,Stamgegevens!$A$8:$AE$36,Stamgegevens!$H$1) -> 0.025 | F26: =VLOOKUP($A26,Stamgegevens!$A$8:$AE$36,Stamgegevens!$J$1) -> 0.11046 | G26: =VLOOKUP($A26,Stamgegevens!$A$8:$AE$36,Stamgegevens!$K$1) -> 10000 | H26: =VLOOKUP($A26,Stamgegevens!$A$8:$AE$36,Stamgegevens!$L$1) -> 0.08394 | I26: =VLOOKUP($A26,Stamgegevens!$A$8:$AE$36,Stamgegevens!$N$1) -> 0 | J26: =F26*I26 -> 0 | L26: =VLOOKUP($A26,Stamgegevens!$A$8:$AE$36,Stamgegevens!$P$1) -> 8.1346391 | M26: =VLOOKUP($A26,Stamgegevens!$A$8:$AE$36,Stamgegevens!$Q$1) -> 8.1346391 | O26: =VLOOKUP($A26,Stamgegevens!$A$8:$AE$36,Stamgegevens!$S$1) -> 0.013580366 | P26: =P25 -> 0.02 | Q26: =VLOOKUP($A26,Stamgegevens!$A$8:$AE$36,Stamgegevens!$U$1) -> 0 | R26: =VLOOKUP($A26,Stamgegevens!$A$8:$AE$36,Stamgegevens!$T$1) -> 0.20370549 | S26: =S25 -> 0 | U26: =IF($M$3=0,$M$3,U25-365) -> 4386 | X26: =VLOOKUP($A26,Stamgegevens!$A$8:$AE$36,Stamgegevens!$W$1) -> 3.5 | Z26: =VLOOKUP($A26,Stamgegevens!$A$8:$AE$36,Stamgegevens!$Y$1) -> -0.02 | AB26: =VLOOKUP($A26,Stamgegevens!$A$8:$AE$36,Stamgegevens!$AA$1) -> 14 | AD26: =VLOOKUP($A26,Stamgegevens!$A$8:$AE$36,Stamgegevens!$AC$1) -> 0.2 | AF26: =VLOOKUP($A26,Stamgegevens!$A$8:$AE$36,Stamgegevens!$AE$1) -> 0.85
... A33: =A32+1 -> 2044 | B33: 20 | D33: =VLOOKUP($A33,Stamgegevens!$A$8:$AE$36,Stamgegevens!$H$1) -> 0.025 | F33: =VLOOKUP($A33,Stamgegevens!$A$8:$AE$36,Stamgegevens!$J$1) -> 0.11046 | G33: =VLOOKUP($A33,Stamgegevens!$A$8:$AE$36,Stamgegevens!$K$1) -> 10000 | H33: =VLOOKUP($A33,Stamgegevens!$A$8:$AE$36,Stamgegevens!$L$1) -> 0.08394 | I33: =VLOOKUP($A33,Stamgegevens!$A$8:$AE$36,Stamgegevens!$N$1) -> 0 | J33: =F33*I33 -> 0 | L33: =VLOOKUP($A33,Stamgegevens!$A$8:$AE$36,Stamgegevens!$P$1) -> 9.6695296 | M33: =VLOOKUP($A33,Stamgegevens!$A$8:$AE$36,Stamgegevens!$Q$1) -> 9.6695296 | O33: =VLOOKUP($A33,Stamgegevens!$A$8:$AE$36,Stamgegevens!$S$1) -> 0.016142787 | P33: =P32 -> 0.02 | Q33: =VLOOKUP($A33,Stamgegevens!$A$8:$AE$36,Stamgegevens!$U$1) -> 0 | R33: =VLOOKUP($A33,Stamgegevens!$A$8:$AE$36,Stamgegevens!$T$1) -> 0.24214181 | S33: =S32 -> 0 | U33: =IF($M$3=0,$M$3,U32-365) -> 1831 | X33: =VLOOKUP($A33,Stamgegevens!$A$8:$AE$36,Stamgegevens!$W$1) -> 3.5 | Z33: =VLOOKUP($A33,Stamgegevens!$A$8:$AE$36,Stamgegevens!$Y$1) -> -0.02 | AB33: =VLOOKUP($A33,Stamgegevens!$A$8:$AE$36,Stamgegevens!$AA$1) -> 14 | AD33: =VLOOKUP($A33,Stamgegevens!$A$8:$AE$36,Stamgegevens!$AC$1) -> 0.2 | AF33: =VLOOKUP($A33,Stamgegevens!$A$8:$AE$36,Stamgegevens!$AE$1) -> 0.85
A34: =A33+1 -> 2045 | D34: =VLOOKUP($A34,Stamgegevens!$A$8:$AE$36,Stamgegevens!$H$1) -> 0.025 | F34: =VLOOKUP($A34,Stamgegevens!$A$8:$AE$36,Stamgegevens!$J$1) -> 0.11046 | G34: =VLOOKUP($A34,Stamgegevens!$A$8:$AE$36,Stamgegevens!$K$1) -> 10000 | H34: =VLOOKUP($A34,Stamgegevens!$A$8:$AE$36,Stamgegevens!$L$1) -> 0.08394 | I34: =VLOOKUP($A34,Stamgegevens!$A$8:$AE$36,Stamgegevens!$N$1) -> 0 | J34: =F34*I34 -> 0 | L34: =VLOOKUP($A34,Stamgegevens!$A$8:$AE$36,Stamgegevens!$P$1) -> 9.9112678 | M34: =VLOOKUP($A34,Stamgegevens!$A$8:$AE$36,Stamgegevens!$Q$1) -> 9.9112678 | O34: =VLOOKUP($A34,Stamgegevens!$A$8:$AE$36,Stamgegevens!$S$1) -> 0.016546357 | P34: =P33 -> 0.02 | Q34: =VLOOKUP($A34,Stamgegevens!$A$8:$AE$36,Stamgegevens!$U$1) -> 0 | R34: =VLOOKUP($A34,Stamgegevens!$A$8:$AE$36,Stamgegevens!$T$1) -> 0.24819535 | S34: =S33 -> 0 | U34: =IF($M$3=0,$M$3,U33-365) -> 1466 | X34: =VLOOKUP($A34,Stamgegevens!$A$8:$AE$36,Stamgegevens!$W$1) -> 3.5 | Z34: =VLOOKUP($A34,Stamgegevens!$A$8:$AE$36,Stamgegevens!$Y$1) -> -0.02 | AB34: =VLOOKUP($A34,Stamgegevens!$A$8:$AE$36,Stamgegevens!$AA$1) -> 14 | AD34: =VLOOKUP($A34,Stamgegevens!$A$8:$AE$36,Stamgegevens!$AC$1) -> 0.2 | AF34: =VLOOKUP($A34,Stamgegevens!$A$8:$AE$36,Stamgegevens!$AE$1) -> 0.85
A35: =A34+1 -> 2046 | D35: =VLOOKUP($A35,Stamgegevens!$A$8:$AE$36,Stamgegevens!$H$1) -> 0.025 | F35: =VLOOKUP($A35,Stamgegevens!$A$8:$AE$36,Stamgegevens!$J$1) -> 0.11046 | G35: =VLOOKUP($A35,Stamgegevens!$A$8:$AE$36,Stamgegevens!$K$1) -> 10000 | H35: =VLOOKUP($A35,Stamgegevens!$A$8:$AE$36,Stamgegevens!$L$1) -> 0.08394 | I35: =VLOOKUP($A35,Stamgegevens!$A$8:$AE$36,Stamgegevens!$N$1) -> 0 | J35: =F35*I35 -> 0 | L35: =VLOOKUP($A35,Stamgegevens!$A$8:$AE$36,Stamgegevens!$P$1) -> 10.15905 | M35: =VLOOKUP($A35,Stamgegevens!$A$8:$AE$36,Stamgegevens!$Q$1) -> 10.15905 | O35: =VLOOKUP($A35,Stamgegevens!$A$8:$AE$36,Stamgegevens!$S$1) -> 0.016960016 | P35: =P34 -> 0.02 | Q35: =VLOOKUP($A35,Stamgegevens!$A$8:$AE$36,Stamgegevens!$U$1) -> 0 | R35: =VLOOKUP($A35,Stamgegevens!$A$8:$AE$36,Stamgegevens!$T$1) -> 0.25440024 | S35: =S34 -> 0 | U35: =IF($M$3=0,$M$3,U34-365) -> 1101 | X35: =VLOOKUP($A35,Stamgegevens!$A$8:$AE$36,Stamgegevens!$W$1) -> 3.5 | Z35: =VLOOKUP($A35,Stamgegevens!$A$8:$AE$36,Stamgegevens!$Y$1) -> -0.02 | AB35: =VLOOKUP($A35,Stamgegevens!$A$8:$AE$36,Stamgegevens!$AA$1) -> 14 | AD35: =VLOOKUP($A35,Stamgegevens!$A$8:$AE$36,Stamgegevens!$AC$1) -> 0.2 | AF35: =VLOOKUP($A35,Stamgegevens!$A$8:$AE$36,Stamgegevens!$AE$1) -> 0.85

Sheet Degradatie
B1: definitief | L1: beoordeling cycli
B3: totaal aantal cycli | D3: =Opbrengsten!H32 -> 10950 | L3: totaal aantal cycli | N3: =Cycli!F30 -> 10950
B4: gegarandeerde cycli | D4: =Calculator!U98 -> 10000 | L4: gegarandeerde cycli | N4: =D4 -> 10000
B5: restcapaciteit na garantie | D5: =Calculator!R100 -> 0.7 | L5: restcapaciteit na garantie | N5: =D5 -> 0.7
B7: degradatie | D7: =((D3/D4)*(1-D5))*100 -> 32.85 | E7: procent | L7: degradatie | N7: =((N3/N4)*(1-N5))*100 -> 32.85 | O7: procent
B8: looptijd | D8: 20 | E8: jaar | L8: looptijd | N8: 20 | O8: jaar
B9: "fictieve rente" | D9: =RATE(D8,-D7/10,D7,0,0) -> 0.077546895 | L9: "fictieve rente" | N9: =RATE(N8,-N7/10,N7,0,0) -> 0.077546895
B10: batterij | D10: =Calculator!R92 -> 21.85 | E10: =Calculator!R94 -> 0.96 | F10: =D10*E10 -> 20.976 | L10: batterij | N10: =D10 -> 21.85 | O10: =E10 -> 0.96 | P10: =F10 -> 20.976
C13: degradatie | D13: % | E13: % | F13: degradatie | I13: cycli | M13: degradatie | N13: % | O13: % | P13: degradatie | S13: cycli
C14: annuïteit | D14: jaar 1 | E14: jaar 2 | F14: in jaar | G14: batterij | H14: gemiddeld | I14: per dag | J14: capaciteit | M14: annuïteit | N14: jaar 1 | O14: jaar 2 | P14: in jaar | Q14: batterij | R14: gemiddeld | S14: per dag | T14: capaciteit
G15: 1 | Q15: 1
B16: 1 | C16: =-(CUMIPMT($D$9,$D$8,$D$7,B16,B16,0))/100 -> 0.025474155 | E16: =Opbrengsten!C5 -> 0.084931507 | F16: =((C15*D16)+(C16*E16)) -> 0.0021635584 | G16: =G15-F16 -> 0.99783644 | H16: =(G15+G16)/2 -> 0.99891822 | I16: =Opbrengsten!F12 -> 1.5 | J16: =H16*$F$10*I16*365*E16 -> 974.32885 | L16: 1 | M16: =-(CUMIPMT($N$9,$N$8,$N$7,L16,L16,0))/100 -> 0.025474155 | O16: =E16 -> 0.084931507 | P16: =((M15*N16)+(M16*O16)) -> 0.0021635584 | Q16: =Q15-P16 -> 0.99783644 | R16: =(Q15+Q16)/2 -> 0.99891822 | S16: =Cycli!D10 -> 1.5 | T16: =R16*$F$10*S16*365*O16 -> 974.32885
B17: 2 | C17: =-(CUMIPMT($D$9,$D$8,$D$7,B17,B17,0))/100 -> 0.024902181 | D17: =1-E16 -> 0.91506849 | E17: =1-D17 -> 0.084931507 | F17: =((C16*D17)+(C17*E17)) -> 0.025425577 | G17: =G16-F17 -> 0.97241087 | H17: =(G16+G17)/2 -> 0.98512365 | I17: =Opbrengsten!F13 -> 1.5 | J17: =H17*$F$10*I17*365 -> 11313.515 | L17: 2 | M17: =-(CUMIPMT($N$9,$N$8,$N$7,L17,L17,0))/100 -> 0.024902181 | N17: =1-O16 -> 0.91506849 | O17: =1-N17 -> 0.084931507 | P17: =((M16*N17)+(M17*O17)) -> 0.025425577 | Q17: =Q16-P17 -> 0.97241087 | R17: =(Q16+Q17)/2 -> 0.98512365 | S17: =Cycli!D11 -> 1.5 | T17: =R17*$F$10*S16*365 -> 11313.515
B18: 3 | C18: =-(CUMIPMT($D$9,$D$8,$D$7,B18,B18,0))/100 -> 0.024285853 | D18: =1-E17 -> 0.91506849 | E18: =1-D18 -> 0.084931507 | F18: =((C17*D18)+(C18*E18)) -> 0.024849836 | G18: =G17-F18 -> 0.94756103 | H18: =(G17+G18)/2 -> 0.95998595 | I18: =Opbrengsten!F14 -> 1.5 | J18: =H18*$F$10*I18*365 -> 11024.824 | L18: 3 | M18: =-(CUMIPMT($N$9,$N$8,$N$7,L18,L18,0))/100 -> 0.024285853 | N18: =1-O17 -> 0.91506849 | O18: =1-N18 -> 0.084931507 | P18: =((M17*N18)+(M18*O18)) -> 0.024849836 | Q18: =Q17-P18 -> 0.94756103 | R18: =(Q17+Q18)/2 -> 0.95998595 | S18: =Cycli!D12 -> 1.5 | T18: =R18*$F$10*S17*365 -> 11024.824
B19: =B18+1 -> 4 | C19: =-(CUMIPMT($D$9,$D$8,$D$7,B19,B19,0))/100 -> 0.02362173 | D19: =1-E18 -> 0.91506849 | E19: =1-D19 -> 0.084931507 | F19: =((C18*D19)+(C19*E19)) -> 0.024229448 | G19: =G18-F19 -> 0.92333158 | H19: =(G18+G19)/2 -> 0.93544631 | I19: =Opbrengsten!F15 -> 1.5 | J19: =H19*$F$10*I19*365 -> 10743.002 | L19: =L18+1 -> 4 | M19: =-(CUMIPMT($N$9,$N$8,$N$7,L19,L19,0))/100 -> 0.02362173 | N19: =1-O18 -> 0.91506849 | O19: =1-N19 -> 0.084931507 | P19: =((M18*N19)+(M19*O19)) -> 0.024229448 | Q19: =Q18-P19 -> 0.92333158 | R19: =(Q18+Q19)/2 -> 0.93544631 | S19: =Cycli!D13 -> 1.5 | T19: =R19*$F$10*S18*365 -> 10743.002
B20: =B19+1 -> 5 | C20: =-(CUMIPMT($D$9,$D$8,$D$7,B20,B20,0))/100 -> 0.022906106 | D20: =1-E19 -> 0.91506849 | E20: =1-D20 -> 0.084931507 | F20: =((C19*D20)+(C20*E20)) -> 0.023560951 | G20: =G19-F20 -> 0.89977063 | H20: =(G19+G20)/2 -> 0.91155111 | I20: =Opbrengsten!F16 -> 1.5 | J20: =H20*$F$10*I20*365 -> 10468.581 | L20: =L19+1 -> 5 | M20: =-(CUMIPMT($N$9,$N$8,$N$7,L20,L20,0))/100 -> 0.022906106 | N20: =1-O19 -> 0.91506849 | O20: =1-N20 -> 0.084931507 | P20: =((M19*N20)+(M20*O20)) -> 0.023560951 | Q20: =Q19-P20 -> 0.89977063 | R20: =(Q19+Q20)/2 -> 0.91155111 | S20: =Cycli!D14 -> 1.5 | T20: =R20*$F$10*S19*365 -> 10468.581
B21: =B20+1 -> 6 | C21: =-(CUMIPMT($D$9,$D$8,$D$7,B21,B21,0))/100 -> 0.022134988 | D21: =1-E20 -> 0.91506849 | E21: =1-D21 -> 0.084931507 | F21: =((C20*D21)+(C21*E21)) -> 0.022840614 | G21: =G20-F21 -> 0.87693002 | H21: =(G20+G21)/2 -> 0.88835032 | I21: =Opbrengsten!F17 -> 1.5 | J21: =H21*$F$10*I21*365 -> 10202.135 | L21: =L20+1 -> 6 | M21: =-(CUMIPMT($N$9,$N$8,$N$7,L21,L21,0))/100 -> 0.022134988 | N21: =1-O20 -> 0.91506849 | O21: =1-N21 -> 0.084931507 | P21: =((M20*N21)+(M21*O21)) -> 0.022840614 | Q21: =Q20-P21 -> 0.87693002 | R21: =(Q20+Q21)/2 -> 0.88835032 | S21: =Cycli!D15 -> 1.5 | T21: =R21*$F$10*S20*365 -> 10202.135
B22: =B21+1 -> 7 | C22: =-(CUMIPMT($D$9,$D$8,$D$7,B22,B22,0))/100 -> 0.021304072 | D22: =1-E21 -> 0.91506849 | E22: =1-D22 -> 0.084931507 | F22: =((C21*D22)+(C22*E22)) -> 0.022064417 | G22: =G21-F22 -> 0.8548656 | H22: =(G21+G22)/2 -> 0.86589781 | I22: =Opbrengsten!F18 -> 1.5 | J22: =H22*$F$10*I22*365 -> 9944.2822 | L22: =L21+1 -> 7 | M22: =-(CUMIPMT($N$9,$N$8,$N$7,L22,L22,0))/100 -> 0.021304072 | N22: =1-O21 -> 0.91506849 | O22: =1-N22 -> 0.084931507 | P22: =((M21*N22)+(M22*O22)) -> 0.022064417 | Q22: =Q21-P22 -> 0.8548656 | R22: =(Q21+Q22)/2 -> 0.86589781 | S22: =Cycli!D16 -> 1.5 | T22: =R22*$F$10*S21*365 -> 9944.2822
B23: =B22+1 -> 8 | C23: =-(CUMIPMT($D$9,$D$8,$D$7,B23,B23,0))/100 -> 0.020408721 | D23: =1-E22 -> 0.91506849 | E23: =1-D23 -> 0.084931507 | F23: =((C22*D23)+(C23*E23)) -> 0.021228028 | G23: =G22-F23 -> 0.83363757 | H23: =(G22+G23)/2 -> 0.84425159 | I23: =Opbrengsten!F19 -> 1.5 | J23: =H23*$F$10*I23*365 -> 9695.6892 | L23: =L22+1 -> 8 | M23: =-(CUMIPMT($N$9,$N$8,$N$7,L23,L23,0))/100 -> 0.020408721 | N23: =1-O22 -> 0.91506849 | O23: =1-N23 -> 0.084931507 | P23: =((M22*N23)+(M23*O23)) -> 0.021228028 | Q23: =Q22-P23 -> 0.83363757 | R23: =(Q22+Q23)/2 -> 0.84425159 | S23: =Cycli!D17 -> 1.5 | T23: =R23*$F$10*S22*365 -> 9695.6892
B24: =B23+1 -> 9 | C24: =-(CUMIPMT($D$9,$D$8,$D$7,B24,B24,0))/100 -> 0.019443938 | D24: =1-E23 -> 0.91506849 | E24: =1-D24 -> 0.084931507 | F24: =((C23*D24)+(C24*E24)) -> 0.02032678 | G24: =G23-F24 -> 0.81331079 | H24: =(G23+G24)/2 -> 0.82347418 | I24: =Opbrengsten!F20 -> 1.5 | J24: =H24*$F$10*I24*365 -> 9457.074 | L24: =L23+1 -> 9 | M24: =-(CUMIPMT($N$9,$N$8,$N$7,L24,L24,0))/100 -> 0.019443938 | N24: =1-O23 -> 0.91506849 | O24: =1-N24 -> 0.084931507 | P24: =((M23*N24)+(M24*O24)) -> 0.02032678 | Q24: =Q23-P24 -> 0.81331079 | R24: =(Q23+Q24)/2 -> 0.82347418 | S24: =Cycli!D18 -> 1.5 | T24: =R24*$F$10*S23*365 -> 9457.074
B25: =B24+1 -> 10 | C25: =-(CUMIPMT($D$9,$D$8,$D$7,B25,B25,0))/100 -> 0.01840434 | D25: =1-E24 -> 0.91506849 | E25: =1-D25 -> 0.084931507 | F25: =((C24*D25)+(C25*E25)) -> 0.019355644 | G25: =G24-F25 -> 0.79395515 | H25: =(G24+G25)/2 -> 0.80363297 | I25: =Opbrengsten!F21 -> 1.5 | J25: =H25*$F$10*I25*365 -> 9229.2103 | L25: =L24+1 -> 10 | M25: =-(CUMIPMT($N$9,$N$8,$N$7,L25,L25,0))/100 -> 0.01840434 | N25: =1-O24 -> 0.91506849 | O25: =1-N25 -> 0.084931507 | P25: =((M24*N25)+(M25*O25)) -> 0.019355644 | Q25: =Q24-P25 -> 0.79395515 | R25: =(Q24+Q25)/2 -> 0.80363297 | S25: =Cycli!D19 -> 1.5 | T25: =R25*$F$10*S24*365 -> 9229.2103
B26: =B25+1 -> 11 | C26: =-(CUMIPMT($D$9,$D$8,$D$7,B26,B26,0))/100 -> 0.017284124 | D26: =1-E25 -> 0.91506849 | E26: =1-D26 -> 0.084931507 | F26: =((C25*D26)+(C26*E26)) -> 0.018309198 | G26: =G25-F26 -> 0.77564595 | H26: =(G25+G26)/2 -> 0.78480055 | I26: =Opbrengsten!F22 -> 1.5 | J26: =H26*$F$10*I26*365 -> 9012.932 | L26: =L25+1 -> 11 | M26: =-(CUMIPMT($N$9,$N$8,$N$7,L26,L26,0))/100 -> 0.017284124 | N26: =1-O25 -> 0.91506849 | O26: =1-N26 -> 0.084931507 | P26: =((M25*N26)+(M26*O26)) -> 0.018309198 | Q26: =Q25-P26 -> 0.77564595 | R26: =(Q25+Q26)/2 -> 0.78480055 | S26: =Cycli!D20 -> 1.5 | T26: =R26*$F$10*S25*365 -> 9012.932
B27: =B26+1 -> 12 | C27: =-(CUMIPMT($D$9,$D$8,$D$7,B27,B27,0))/100 -> 0.016077038 | D27: =1-E26 -> 0.91506849 | E27: =1-D27 -> 0.084931507 | F27: =((C26*D27)+(C27*E27)) -> 0.017181604 | G27: =G26-F27 -> 0.75846435 | H27: =(G26+G27)/2 -> 0.76705515 | I27: =Opbrengsten!F23 -> 1.5 | J27: =H27*$F$10*I27*365 -> 8809.1375 | L27: =L26+1 -> 12 | M27: =-(CUMIPMT($N$9,$N$8,$N$7,L27,L27,0))/100 -> 0.016077038 | N27: =1-O26 -> 0.91506849 | O27: =1-N27 -> 0.084931507 | P27: =((M26*N27)+(M27*O27)) -> 0.017181604 | Q27: =Q26-P27 -> 0.75846435 | R27: =(Q26+Q27)/2 -> 0.76705515 | S27: =Cycli!D21 -> 1.5 | T27: =R27*$F$10*S26*365 -> 8809.1375
B28: =B27+1 -> 13 | C28: =-(CUMIPMT($D$9,$D$8,$D$7,B28,B28,0))/100 -> 0.014776347 | D28: =1-E27 -> 0.91506849 | E28: =1-D28 -> 0.084931507 | F28: =((C27*D28)+(C28*E28)) -> 0.015966569 | G28: =G27-F28 -> 0.74249778 | H28: =(G27+G28)/2 -> 0.75048106 | I28: =Opbrengsten!F24 -> 1.5 | J28: =H28*$F$10*I28*365 -> 8618.7947 | L28: =L27+1 -> 13 | M28: =-(CUMIPMT($N$9,$N$8,$N$7,L28,L28,0))/100 -> 0.014776347 | N28: =1-O27 -> 0.91506849 | O28: =1-N28 -> 0.084931507 | P28: =((M27*N28)+(M28*O28)) -> 0.015966569 | Q28: =Q27-P28 -> 0.74249778 | R28: =(Q27+Q28)/2 -> 0.75048106 | S28: =Cycli!D22 -> 1.5 | T28: =R28*$F$10*S27*365 -> 8618.7947
B29: =B28+1 -> 14 | C29: =-(CUMIPMT($D$9,$D$8,$D$7,B29,B29,0))/100 -> 0.013374792 | D29: =1-E28 -> 0.91506849 | E29: =1-D29 -> 0.084931507 | F29: =((C28*D29)+(C29*E29)) -> 0.014657311 | G29: =G28-F29 -> 0.72784047 | H29: =(G28+G29)/2 -> 0.73516912 | I29: =Opbrengsten!F25 -> 1.5 | J29: =H29*$F$10*I29*365 -> 8442.9469 | L29: =L28+1 -> 14 | M29: =-(CUMIPMT($N$9,$N$8,$N$7,L29,L29,0))/100 -> 0.013374792 | N29: =1-O28 -> 0.91506849 | O29: =1-N29 -> 0.084931507 | P29: =((M28*N29)+(M29*O29)) -> 0.014657311 | Q29: =Q28-P29 -> 0.72784047 | R29: =(Q28+Q29)/2 -> 0.73516912 | S29: =Cycli!D23 -> 1.5 | T29: =R29*$F$10*S28*365 -> 8442.9469
B30: =B29+1 -> 15 | C30: =-(CUMIPMT($D$9,$D$8,$D$7,B30,B30,0))/100 -> 0.01186455 | D30: =1-E29 -> 0.91506849 | E30: =1-D30 -> 0.084931507 | F30: =((C29*D30)+(C30*E30)) -> 0.013246524 | G30: =G29-F30 -> 0.71459394 | H30: =(G29+G30)/2 -> 0.7212172 | I30: =Opbrengsten!F26 -> 1.5 | J30: =H30*$F$10*I30*365 -> 8282.718 | L30: =L29+1 -> 15 | M30: =-(CUMIPMT($N$9,$N$8,$N$7,L30,L30,0))/100 -> 0.01186455 | N30: =1-O29 -> 0.91506849 | O30: =1-N30 -> 0.084931507 | P30: =((M29*N30)+(M30*O30)) -> 0.013246524 | Q30: =Q29-P30 -> 0.71459394 | R30: =(Q29+Q30)/2 -> 0.7212172 | S30: =Cycli!D24 -> 1.5 | T30: =R30*$F$10*S29*365 -> 8282.718
... B35: =B34+1 -> 20 | C35: =-(CUMIPMT($D$9,$D$8,$D$7,B35,B35,0))/100 -> 0.0023640878 | D35: =1-E34 -> 0.91506849 | E35: =1-D35 -> 0.084931507 | F35: =((C34*D35)+(C35*E35)) -> 0.0043717056 | G35: =G34-F35 -> 0.6736633 | H35: =(G34+G35)/2 -> 0.67584916 | I35: =Opbrengsten!F31 -> 1.5 | J35: =H35*$F$10*I35*365 -> 7761.695 | L35: =L34+1 -> 20 | M35: =-(CUMIPMT($N$9,$N$8,$N$7,L35,L35,0))/100 -> 0.0023640878 | N35: =1-O34 -> 0.91506849 | O35: =1-N35 -> 0.084931507 | P35: =((M34*N35)+(M35*O35)) -> 0.0043717056 | Q35: =Q34-P35 -> 0.6736633 | R35: =(Q34+Q35)/2 -> 0.67584916 | S35: =Cycli!D29 -> 1.5 | T35: =R35*$F$10*S34*365 -> 7761.695
B36: =B35+1 -> 21 | D36: =1-E35 -> 0.91506849 | F36: =((C35*D36)+(C36*E36)) -> 0.0021633023 | G36: =G35-F36 -> 0.6715 | H36: =(G35+G36)/2 -> 0.67258165 | I36: =Opbrengsten!F32 -> 1.5 | J36: =H36*$F$10*I36*365*D36 -> 7068.1444 | L36: =L35+1 -> 21 | N36: =1-O35 -> 0.91506849 | P36: =((M35*N36)+(M36*O36)) -> 0.0021633023 | Q36: =Q35-P36 -> 0.6715 | R36: =(Q35+Q36)/2 -> 0.67258165 | S36: =Cycli!D30 -> 1.5 | T36: =R36*$F$10*S35*365*N36 -> 7068.1444
C38: =SUM(C16:C37) -> 0.3285 | F38: =SUM(F16:F37) -> 0.3285 | J38: =SUM(J16:J37) -> 182934.39 | M38: =SUM(M16:M37) -> 0.3285 | P38: =SUM(P16:P37) -> 0.3285 | T38: =SUM(T16:T37) -> 182934.39
I40: 1 | J40: =J38/E10 -> 190556.66 | S40: 1 | T40: =T38/E10 -> 190556.66

Sheet Cycli
A2: Datum | D2: =Opbrengsten!C2 -> 45992
A3: Einde jaar | D3: =Opbrengsten!C3 -> 46022
A4: Dagen in jaar | D4: =Opbrengsten!C4 -> 31 | E4: =Opbrengsten!D4 -> 334
A5: Jaar % | D5: =Opbrengsten!C5 -> 0.084931507 | E5: =Opbrengsten!D5 -> 0.91506849
A8: Jaar | B8: Kalenderjaren | D8: cycli per dag | E8: Cycli per jaar | F8: Cycli cumulatief | G8: Roundtrip Efficiency | H8: Degradatie per jaar | I8: Degradatie Cumulatief | J8: Capaciteit % | K8: Capaciteit | L8: Capaciteit beschikbaar | M8: Opgeslagen zonnepanelen | N8: Capaciteit over | O8: Verbruik van net | P8: Capaciteit over voor handel | Q8: cycli per dag aangepast
A10: 1 | B10: =Jaargegevens!A14 -> 2025 | D10: =IF(Calculator!$R$118>0,IF(B10<Calculator!$R$118,Calculator!$U$114,Calculator!$U$116),Calculator!$U$114) -> 1.5 | E10: =D10*365*D5 -> 46.5 | F10: =SUM($E$10:E10) -> 46.5 | G10: =Calculator!$R$94 -> 0.96 | H10: =Degradatie!P16 -> 0.0021635584 | I10: =SUM(H$8:H10) -> 0.0021635584 | J10: =(1+(1-I10))/2 -> 0.99891822 | K10: =J10*Calculator!$R$92 -> 21.826363 | L10: =K10*E10 -> 1014.9259 | M10: =Calculator!$R$32*D5 -> 212.32877 | N10: =L10-M10 -> 802.59712 | O10: =Calculator!$R$30*D5 -> 297.26027 | P10: =N10-O10 -> 505.33684 | Q10: =IF(D10=Keuzemenu!$D$31,D10,IF(N10<0,Keuzemenu!$D$31,IF(P10<0,MIN(D10,Keuzemenu!$D$32),D10))) -> 1.5
A11: 2 | B11: =Jaargegevens!A15 -> 2026 | D11: =IF(Calculator!$R$118>0,IF(B11<Calculator!$R$118,Calculator!$U$114,Calculator!$U$116),Calculator!$U$114) -> 1.5 | E11: =D11*365 -> 547.5 | F11: =SUM($E$10:E11) -> 594 | G11: =Calculator!$R$94 -> 0.96 | H11: =Degradatie!P17 -> 0.025425577 | I11: =SUM(H$8:H11) -> 0.027589135 | J11: =((1-I10)+(1-I11))/2 -> 0.98512365 | K11: =J11*Calculator!$R$92 -> 21.524952 | L11: =K11*E11 -> 11784.911 | M11: =Calculator!$R$32 -> 2500 | N11: =L11-M11 -> 9284.9111 | O11: =Calculator!$R$30 -> 3500 | P11: =N11-O11 -> 5784.9111 | Q11: =IF(D11=Keuzemenu!$D$31,D11,IF(N11<0,Keuzemenu!$D$31,IF(P11<0,MIN(D11,Keuzemenu!$D$32),D11))) -> 1.5
A12: 3 | B12: =Jaargegevens!A16 -> 2027 | D12: =IF(Calculator!$R$118>0,IF(B12<Calculator!$R$118,Calculator!$U$114,Calculator!$U$116),Calculator!$U$114) -> 1.5 | E12: =D12*365 -> 547.5 | F12: =SUM($E$10:E12) -> 1141.5 | G12: =Calculator!$R$94 -> 0.96 | H12: =Degradatie!P18 -> 0.024849836 | I12: =SUM(H$8:H12) -> 0.05243897 | J12: =((1-I11)+(1-I12))/2 -> 0.95998595 | K12: =J12*Calculator!$R$92 -> 20.975693 | L12: =K12*E12 -> 11484.192 | M12: =Calculator!$R$32 -> 2500 | N12: =L12-M12 -> 8984.1919 | O12: =Calculator!$R$30 -> 3500 | P12: =N12-O12 -> 5484.1919 | Q12: =IF(D12=Keuzemenu!$D$31,D12,IF(N12<0,Keuzemenu!$D$31,IF(P12<0,MIN(D12,Keuzemenu!$D$32),D12))) -> 1.5
A13: 4 | B13: =Jaargegevens!A17 -> 2028 | D13: =IF(Calculator!$R$118>0,IF(B13<Calculator!$R$118,Calculator!$U$114,Calculator!$U$116),Calculator!$U$114) -> 1.5 | E13: =D13*365 -> 547.5 | F13: =SUM($E$10:E13) -> 1689 | G13: =Calculator!$R$94 -> 0.96 | H13: =Degradatie!P19 -> 0.024229448 | I13: =SUM(H$8:H13) -> 0.076668418 | J13: =((1-I12)+(1-I13))/2 -> 0.93544631 | K13: =J13*Calculator!$R$92 -> 20.439502 | L13: =K13*E13 -> 11190.627 | M13: =Calculator!$R$32 -> 2500 | N13: =L13-M13 -> 8690.6272 | O13: =Calculator!$R$30 -> 3500 | P13: =N13-O13 -> 5190.6272 | Q13: =IF(D13=Keuzemenu!$D$31,D13,IF(N13<0,Keuzemenu!$D$31,IF(P13<0,MIN(D13,Keuzemenu!$D$32),D13))) -> 1.5
A14: 5 | B14: =Jaargegevens!A18 -> 2029 | D14: =IF(Calculator!$R$118>0,IF(B14<Calculator!$R$118,Calculator!$U$114,Calculator!$U$116),Calculator!$U$114) -> 1.5 | E14: =D14*365 -> 547.5 | F14: =SUM($E$10:E14) -> 2236.5 | G14: =Calculator!$R$94 -> 0.96 | H14: =Degradatie!P20 -> 0.023560951 | I14: =SUM(H$8:H14) -> 0.10022937 | J14: =((1-I13)+(1-I14))/2 -> 0.91155111 | K14: =J14*Calculator!$R$92 -> 19.917392 | L14: =K14*E14 -> 10904.772 | M14: =Calculator!$R$32 -> 2500 | N14: =L14-M14 -> 8404.7719 | O14: =Calculator!$R$30 -> 3500 | P14: =N14-O14 -> 4904.7719 | Q14: =IF(D14=Keuzemenu!$D$31,D14,IF(N14<0,Keuzemenu!$D$31,IF(P14<0,MIN(D14,Keuzemenu!$D$32),D14))) -> 1.5
A15: 6 | B15: =Jaargegevens!A19 -> 2030 | D15: =IF(Calculator!$R$118>0,IF(B15<Calculator!$R$118,Calculator!$U$114,Calculator!$U$116),Calculator!$U$114) -> 1.5 | E15: =D15*365 -> 547.5 | F15: =SUM($E$10:E15) -> 2784 | G15: =Calculator!$R$94 -> 0.96 | H15: =Degradatie!P21 -> 0.022840614 | I15: =SUM(H$8:H15) -> 0.12306998 | J15: =((1-I14)+(1-I15))/2 -> 0.88835032 | K15: =J15*Calculator!$R$92 -> 19.410455 | L15: =K15*E15 -> 10627.224 | M15: =Calculator!$R$32 -> 2500 | N15: =L15-M15 -> 8127.2239 | O15: =Calculator!$R$30 -> 3500 | P15: =N15-O15 -> 4627.2239 | Q15: =IF(D15=Keuzemenu!$D$31,D15,IF(N15<0,Keuzemenu!$D$31,IF(P15<0,MIN(D15,Keuzemenu!$D$32),D15))) -> 1.5
A16: 7 | B16: =Jaargegevens!A20 -> 2031 | D16: =IF(Calculator!$R$118>0,IF(B16<Calculator!$R$118,Calculator!$U$114,Calculator!$U$116),Calculator!$U$114) -> 1.5 | E16: =D16*365 -> 547.5 | F16: =SUM($E$10:E16) -> 3331.5 | G16: =Calculator!$R$94 -> 0.96 | H16: =Degradatie!P22 -> 0.022064417 | I16: =SUM(H$8:H16) -> 0.1451344 | J16: =((1-I15)+(1-I16))/2 -> 0.86589781 | K16: =J16*Calculator!$R$92 -> 18.919867 | L16: =K16*E16 -> 10358.627 | M16: =Calculator!$R$32 -> 2500 | N16: =L16-M16 -> 7858.6273 | O16: =Calculator!$R$30 -> 3500 | P16: =N16-O16 -> 4358.6273 | Q16: =IF(D16=Keuzemenu!$D$31,D16,IF(N16<0,Keuzemenu!$D$31,IF(P16<0,MIN(D16,Keuzemenu!$D$32),D16))) -> 1.5
A17: 8 | B17: =Jaargegevens!A21 -> 2032 | D17: =IF(Calculator!$R$118>0,IF(B17<Calculator!$R$118,Calculator!$U$114,Calculator!$U$116),Calculator!$U$114) -> 1.5 | E17: =D17*365 -> 547.5 | F17: =SUM($E$10:E17) -> 3879 | G17: =Calculator!$R$94 -> 0.96 | H17: =Degradatie!P23 -> 0.021228028 | I17: =SUM(H$8:H17) -> 0.16636243 | J17: =((1-I16)+(1-I17))/2 -> 0.84425159 | K17: =J17*Calculator!$R$92 -> 18.446897 | L17: =K17*E17 -> 10099.676 | M17: =Calculator!$R$32 -> 2500 | N17: =L17-M17 -> 7599.6762 | O17: =Calculator!$R$30 -> 3500 | P17: =N17-O17 -> 4099.6762 | Q17: =IF(D17=Keuzemenu!$D$31,D17,IF(N17<0,Keuzemenu!$D$31,IF(P17<0,MIN(D17,Keuzemenu!$D$32),D17))) -> 1.5
A18: 9 | B18: =Jaargegevens!A22 -> 2033 | D18: =IF(Calculator!$R$118>0,IF(B18<Calculator!$R$118,Calculator!$U$114,Calculator!$U$116),Calculator!$U$114) -> 1.5 | E18: =D18*365 -> 547.5 | F18: =SUM($E$10:E18) -> 4426.5 | G18: =Calculator!$R$94 -> 0.96 | H18: =Degradatie!P24 -> 0.02032678 | I18: =SUM(H$8:H18) -> 0.18668921 | J18: =((1-I17)+(1-I18))/2 -> 0.82347418 | K18: =J18*Calculator!$R$92 -> 17.992911 | L18: =K18*E18 -> 9851.1187 | M18: =Calculator!$R$32 -> 2500 | N18: =L18-M18 -> 7351.1187 | O18: =Calculator!$R$30 -> 3500 | P18: =N18-O18 -> 3851.1187 | Q18: =IF(D18=Keuzemenu!$D$31,D18,IF(N18<0,Keuzemenu!$D$31,IF(P18<0,MIN(D18,Keuzemenu!$D$32),D18))) -> 1.5
A19: 10 | B19: =Jaargegevens!A23 -> 2034 | D19: =IF(Calculator!$R$118>0,IF(B19<Calculator!$R$118,Calculator!$U$114,Calculator!$U$116),Calculator!$U$114) -> 1.5 | E19: =D19*365 -> 547.5 | F19: =SUM($E$10:E19) -> 4974 | G19: =Calculator!$R$94 -> 0.96 | H19: =Degradatie!P25 -> 0.019355644 | I19: =SUM(H$8:H19) -> 0.20604485 | J19: =((1-I18)+(1-I19))/2 -> 0.80363297 | K19: =J19*Calculator!$R$92 -> 17.55938 | L19: =K19*E19 -> 9613.7608 | M19: =Calculator!$R$32 -> 2500 | N19: =L19-M19 -> 7113.7608 | O19: =Calculator!$R$30 -> 3500 | P19: =N19-O19 -> 3613.7608 | Q19: =IF(D19=Keuzemenu!$D$31,D19,IF(N19<0,Keuzemenu!$D$31,IF(P19<0,MIN(D19,Keuzemenu!$D$32),D19))) -> 1.5
A20: 11 | B20: =Jaargegevens!A24 -> 2035 | D20: =IF(Calculator!$R$118>0,IF(B20<Calculator!$R$118,Calculator!$U$114,Calculator!$U$116),Calculator!$U$114) -> 1.5 | E20: =D20*365 -> 547.5 | F20: =SUM($E$10:E20) -> 5521.5 | G20: =Calculator!$R$94 -> 0.96 | H20: =Degradatie!P26 -> 0.018309198 | I20: =SUM(H$8:H20) -> 0.22435405 | J20: =((1-I19)+(1-I20))/2 -> 0.78480055 | K20: =J20*Calculator!$R$92 -> 17.147892 | L20: =K20*E20 -> 9388.4709 | M20: =Calculator!$R$32 -> 2500 | N20: =L20-M20 -> 6888.4709 | O20: =Calculator!$R$30 -> 3500 | P20: =N20-O20 -> 3388.4709 | Q20: =IF(D20=Keuzemenu!$D$31,D20,IF(N20<0,Keuzemenu!$D$31,IF(P20<0,MIN(D20,Keuzemenu!$D$32),D20))) -> 1.5
A21: 12 | B21: =Jaargegevens!A25 -> 2036 | D21: =IF(Calculator!$R$118>0,IF(B21<Calculator!$R$118,Calculator!$U$114,Calculator!$U$116),Calculator!$U$114) -> 1.5 | E21: =D21*365 -> 547.5 | F21: =SUM($E$10:E21) -> 6069 | G21: =Calculator!$R$94 -> 0.96 | H21: =Degradatie!P27 -> 0.017181604 | I21: =SUM(H$8:H21) -> 0.24153565 | J21: =((1-I20)+(1-I21))/2 -> 0.76705515 | K21: =J21*Calculator!$R$92 -> 16.760155 | L21: =K21*E21 -> 9176.1849 | M21: =Calculator!$R$32 -> 2500 | N21: =L21-M21 -> 6676.1849 | O21: =Calculator!$R$30 -> 3500 | P21: =N21-O21 -> 3176.1849 | Q21: =IF(D21=Keuzemenu!$D$31,D21,IF(N21<0,Keuzemenu!$D$31,IF(P21<0,MIN(D21,Keuzemenu!$D$32),D21))) -> 1.5
A22: 13 | B22: =Jaargegevens!A26 -> 2037 | D22: =IF(Calculator!$R$118>0,IF(B22<Calculator!$R$118,Calculator!$U$114,Calculator!$U$116),Calculator!$U$114) -> 1.5 | E22: =D22*365 -> 547.5 | F22: =SUM($E$10:E22) -> 6616.5 | G22: =Calculator!$R$94 -> 0.96 | H22: =Degradatie!P28 -> 0.015966569 | I22: =SUM(H$8:H22) -> 0.25750222 | J22: =((1-I21)+(1-I22))/2 -> 0.75048106 | K22: =J22*Calculator!$R$92 -> 16.398011 | L22: =K22*E22 -> 8977.9111 | M22: =Calculator!$R$32 -> 2500 | N22: =L22-M22 -> 6477.9111 | O22: =Calculator!$R$30 -> 3500 | P22: =N22-O22 -> 2977.9111 | Q22: =IF(D22=Keuzemenu!$D$31,D22,IF(N22<0,Keuzemenu!$D$31,IF(P22<0,MIN(D22,Keuzemenu!$D$32),D22))) -> 1.5
... A29: 20 | B29: =Jaargegevens!A33 -> 2044 | D29: =IF(Calculator!$R$118>0,IF(B29<Calculator!$R$118,Calculator!$U$114,Calculator!$U$116),Calculator!$U$114) -> 1.5 | E29: =D29*365 -> 547.5 | F29: =SUM($E$10:E29) -> 10449 | G29: =Calculator!$R$94 -> 0.96 | H29: =Degradatie!P35 -> 0.0043717056 | I29: =SUM(H$8:H29) -> 0.3263367 | J29: =((1-I28)+(1-I29))/2 -> 0.67584916 | K29: =J29*Calculator!$R$92 -> 14.767304 | L29: =K29*E29 -> 8085.099 | M29: =Calculator!$R$32 -> 2500 | N29: =L29-M29 -> 5585.099 | O29: =Calculator!$R$30 -> 3500 | P29: =N29-O29 -> 2085.099 | Q29: =IF(D29=Keuzemenu!$D$31,D29,IF(N29<0,Keuzemenu!$D$31,IF(P29<0,MIN(D29,Keuzemenu!$D$32),D29))) -> 1.5
A30: 21 | B30: =Jaargegevens!A34 -> 2045 | D30: =IF(Calculator!$R$118>0,IF(B30<Calculator!$R$118,Calculator!$U$114,Calculator!$U$116),Calculator!$U$114) -> 1.5 | E30: =D30*365*E5 -> 501 | F30: =SUM($E$10:E30) -> 10950 | G30: =Calculator!$R$94 -> 0.96 | H30: =Degradatie!P36 -> 0.0021633023 | I30: =SUM(H$8:H30) -> 0.3285 | J30: =((1-I29)+(1-I30))/2 -> 0.67258165 | K30: =J30*Calculator!$R$92 -> 14.695909 | L30: =K30*E30 -> 7362.6504 | M30: =Calculator!$R$32*E5 -> 2287.6712 | N30: =L30-M30 -> 5074.9792 | O30: =Calculator!$R$30*E5 -> 3202.7397 | P30: =N30-O30 -> 1872.2395 | Q30: =IF(D30=Keuzemenu!$D$31,D30,IF(N30<0,Keuzemenu!$D$31,IF(P30<0,MIN(D30,Keuzemenu!$D$32),D30))) -> 1.5

Sheet Opbrengsten
BP1: =IF(BH1-BE1-BI1>0,BH1-BE1-BI1,0) -> 0
A2: Datum | C2: =Jaargegevens!E3 -> 45992 | BN2: HIER ZIT DE OMVORMER CAPACITEIT IN MEEGEREKEND
A3: Einde jaar | C3: =DATEVALUE(CONCATENATE("31/12/",YEAR(C2))) -> 46022
A4: Dagen in jaar | C4: =C3-C2+1 -> 31 | D4: =365-C4 -> 334
A5: Jaar % | C5: =C4/365 -> 0.084931507 | D5: =1-C5 -> 0.91506849 | F5: Batterij | U5: Vastrecht | X5: Stroomtarieven | AP5: Stroomverbruik | BG5: Nieuwe situatie
F7: Cycli | K7: Degradatie | P7: Capaciteit | U7: Vastrecht | X7: Huidig contract | AD7: Dynamisch contract laag | AH7: Dynamisch contract hoog | AL7: Dynamisch contract gemiddeld | AP7: Stroom | AT7: Gas | AY7: Huidige situatie | BG7: Teruglevering | BL7: Handel | BX7: Opbrengsten | CH7: Correctie energiebelasting | CP7: kosten laden batterijen | CV7: opbrengst ontladen batterijen | DJ7: opbrengsten | DN7: totaal
A8: WAS | C8: afh van jaren vlgs calc | D8: invoer | F8: cycli per dag | G8: cycli per dag in calc x 365 | I8: in calc | K8: in calc | L8: in calc | M8: F/J x (1 - K) | P8: 1 - M | Q8: cap in calc x O | R8: cycli x cap F x P | U8: 12 x (vastr str + vastr gas) in calc | V8: als vastr gas >0; 12 x 2 x 5,99; 12 x 5,99 | X8: lev.kst incl bel - bel. na 1e jr +infl | Y8: invoer + infl | Z8: lev.kst in calc; na 1e jr lev.kst + bel | AA8: in calc | AB8: in calc | AD8: invoer + infl | AE8: X | AF8: AC + AD | AH8: invoer + infl | AI8: X | AJ8: AG + AH | AL8: invoer + infl | AM8: X | AN8: AG + AH | AP8: in calc | AQ8: extra gas auto AR + AW | AR8: AK + AL | AT8: in calc afh van jaar overstap | AU8: in calc afh van AO | AV8: invoer | AW8: AP x AQ | AY8: totaal verbruik - direct verbruik AM - BB | AZ8: in calc | BA8: in calc ber niet nodig | BB8: in calc ber niet nodig | BC8: in calc ber niet nodig | BD8: totaal verbruik AY + BB | BE8: totaal verbruik - direct verbruik BD - BB | BG8: opwek - direct verbruik AZ - BB | BH8: Q | BI8: minimum BG en BH | BJ8: lev.kst hoog - 0,02 vanaf jr3 - bel AI - | BL8: in calc | BM8: invoer | BN8: verm in calc /4 < cap(P); verm in cal x (eff min/60); cap (P) | BO8: afh van handelen 365 x 24 x 4 x volume (BN) | BP8: capaciteit beschikbaar - opgeslagen BH - BI | BQ8: minimum BO - BP | BR8: lev.kst incl bel laag AE | BS8: lev.kst incl bel hoog AI + 0,20 | BT8: vergoeding - lev.kst vanaf 3e jr - belasting | BU8: invoer | BV8: winst x uitbet% | BX8: eff verlies x opslag jaar x ink handel | BY8: inkoop x verschil lev.kst nu en lev.kst laag BE x (Y - AE) | BZ8: teruglevering x terugl.verg BC x BJ | CA8: volume handel x uitbet handel BQ x BV | CC8: vastrecht nu - vastrecht oud | CD8: totaal BX t/m CB | CW8: 1 - RTE x capaciteit | DF8: inkoop + uitbetaald | DL8: vastrecht nu - vastrecht oud
A9: GEWIJZIGD | B9: nieuw | D9: uit jaargegevens | G9: in 1e jaar niet naar tijdsgelang | P9: gemiddelde capaciteit | V9: uit jaargegevens | Y9: uit jaargegevens | AD9: uit jaargegevens | AH9: uit jaargegevens | AL9: uit jaargegevens | AT9: uit jaargegevens | AV9: uit jaargegevens | BA9: uit calculatie | BB9: uit calculatie | BC9: uit calculatie | BG9: BC | BJ9: uit jaargegevens | BM9: uit jaargegevens | BP9: BH - BE - Bi | BS9: uit jaargegevens | BU9: uit jaargegevens | BY9: 1e jaar niet naar tijdsgelang | BZ9: BC x AA | CP9: CG + CR | CQ9: BC | CR9: CS - CT | CS9: AE | CT9: CU x CV | CY9: AY | CZ9: AI | DA9: AY x AI | DB9: CT | DC9: BJ | DD9: AY x AI | DE9: CY - CZ - DC | DF9: BR + BV | DG9: DF x DG | DH9: DB + DE + DH | DN9: DH + DJ + DK
A10: Jaar | B10: Kalenderjaren | C10: Garantie | D10: Inflatie | F10: cycli per dag | G10: Cycli per jaar | H10: Cycli cumulatief | I10: Roundtrip Efficiency | K10: Garantie | L10: Restcapaciteit | M10: Degradatie per jaar | N10: Degradatie Cumulatief | P10: Capaciteit % | Q10: Capaciteit | R10: Opslag per jaar | S10: Opslag Cumulatief | U10: Vastrecht huidige situatie | V10: Vastrecht nieuwe situatie | X10: Leveringskosten (exclusief belasting) | Y10: Energiebelasting | Z10: Leveringskosten (inclusief belasting) | AA10: Terugleverkosten | AB10: Terugleververgoeding nieuw | AD10: Leveringskosten (exclusief belasting) | AE10: Energiebelasting | AF10: Leveringskosten (inclusief belasting) | AH10: Leveringskosten (exclusief belasting) | AI10: Energiebelasting | AJ10: Leveringskosten (inclusief belasting) | AL10: Leveringskosten (exclusief belasting) | AM10: Energiebelasting | AN10: Leveringskosten (inclusief belasting) | AP10: Huidig verbruik | AQ10: Extra verbruik | AR10: Totaal verbruik | AT10: dagen van het gas af | AU10: Afname gasverbruik | AV10: Omrekenfactor (kWh per m3) | AW10: Toename stroomverbruik | AY10: Verbruik | AZ10: Opwek | BA10: Direct verbruik % | BB10: Direct verbruik | BC10: Teruglevering | BD10: Totaal verbruik | BE10: Inkoop | BG10: Capaciteit gewenst | BH10: Capaciteit beschikbaar | BI10: Opgeslagen | BJ10: Terugleververgoeding | BL10: Handelen | BM10: Effectieve minuten per kwartier | BN10: Volume per handelsmoment | BO10: Volume potentieel | BP10: Capaciteit beschikbaar | BQ10: Volume verhandeld | BR10: Inkoopkosten | BS10: Terugleververgoeding | BT10: Winst | BU10: Uitbetaalpercentage | BV10: Uitbetaling aan klant | BX10: Efficiëntie batterij (verlies) | BY10: Eigen verbruik | BZ10: Teruglevering | CA10: Handel | CB10: Correctie energiebelasting | CC10: Vastrecht | CD10: Opbrengsten per jaar | CE10: Opbrengsten Cumulatief | CH10: totale capaciteit | CI10: uit zonnepanelen | CJ10: inkoop | CK10: grens lagere energiebelasting | CL10: verschil (groter dan 0) | CM10: verschil energiebelasting | CN10: correctie energiebelasting | CP10: maximale capaciteit = te laden | CQ10: uit zonnepanelen | CR10: in te kopen | CS10: inkoopprijs laag | CT10: inkoop | CV10: maximale capaciteit | CW10: efficientie verlies | CX10: te ontladen (na RTE) | CY10: eigen gebruik | CZ10: hoog tarief | DA10: niet in te kopen tegen hoog tarief | DB10: teruglevering | DC10: terugleververgoeding | DD10: niet in te kopen tegen hoog tarief | DE10: resteert voor handel | DF10: verkoopprijs | DG10: verrkoop tegen hoogtarief | DH10: totaal verkoop | DJ10: verkoop minus inkoop | DK10: Correctie energiebelasting | DL10: Vastrecht | DN10: netto opbrengst
A12: 1 | B12: =Jaargegevens!A14 -> 2025 | C12: =IF(A12>Calculator!$R$96,"Nee",IF(H11<K12,"Ja","Nee")) -> Ja | D12: =Jaargegevens!D14 -> 0.032 | F12: =Cycli!Q10 -> 1.5 | G12: =F12*365*C5 -> 46.5 | H12: =SUM(G$12:G12) -> 46.5 | I12: =Calculator!$R$94 -> 0.96 | K12: =Calculator!R98 -> 10000 | L12: =Calculator!$R$100 -> 0.7 | M12: =Degradatie!$F16 -> 0.0021635584 | N12: =SUM(M$10:M12) -> 0.0021635584 | P12: =(1+(1-N12))/2 -> 0.99891822 | Q12: =P12*Calculator!$R$92 -> 21.826363 | R12: =Q12*G12 -> 1014.9259 | S12: =SUM(R$12:R12) -> 1014.9259 | U12: =(12*Calculator!S45+12*Calculator!R73)*C5 -> 15.267288 | V12: =IF(Calculator!$R$73>0,(Jaargegevens!L14+Jaargegevens!M14)*12*C5,Jaargegevens!L14*12*C5) -> 12.209753 | X12: =Z12-Y12 -> 0.05714 | Y12: =Jaargegevens!F14 -> 0.12286 | Z12: =Calculator!S47 -> 0.18 | AA12: =IF(Calculator!R25="Dynamisch",Opbrengsten!Z12,Calculator!S49) -> 0.15 | AB12: =IF(Calculator!$R$25="Dynamisch",0,Calculator!S51) -> 0.14 | AD12: =Jaargegevens!O14+Jaargegevens!P14 -> 0.03 | AE12: =Y12 -> 0.12286 | AF12: =SUM(AD12:AE12) -> 0.15286 | AH12: =Jaargegevens!R14 -> 0.15 | AI12: =Y12 -> 0.12286 | AJ12: =SUM(AH12:AI12) -> 0.27286 | AL12: =(AD12+AH12)/2 -> 0.09 | AM12: =AE12 -> 0.12286 | AN12: =SUM(AL12:AM12) -> 0.21286 | AP12: =Calculator!$R$38*C5 -> 382.19178 | AQ12: =AW12 -> 0 | AR12: =SUM(AP12:AQ12) -> 382.19178 | AT12: =MIN(MAX(0,-Jaargegevens!U14),365) -> 0 | AU12: =MAX(0,(Opbrengsten!AT12/365)*Calculator!$R$71) -> 0 | AV12: =Jaargegevens!X14 -> 3.5 | AW12: =AV12*AU12 -> 0 | AY12: =AR12-BB12 -> 297.26027 | AZ12: =Calculator!$R$34*C5 -> 297.26027 | BA12: =Calculator!$V$36 -> 0.28571429 | BB12: =Calculator!$R$36*C5 -> 84.931507 | BC12: =MIN(Calculator!$R$32*C5,R12) -> 212.32877 | BD12: =AY12+BB12 -> 382.19178 | BE12: =MIN(BD12-BB12,R12-BC12) -> 297.26027 | BG12: =BC12 -> 212.32877 | BH12: =R12 -> 1014.9259 | BI12: =MIN(BG12:BH12) -> 212.32877 | BJ12: =IF(B12<=Jaargegevens!$M$7,Calculator!$S$49,AH12+Jaargegevens!S14+Jaargegevens!J14) -> 0.15 | BL12: =IF(Calculator!$R$118<=B12,Keuzemenu!$I$18,Keuzemenu!$I$17) -> Ja | BM12: =Jaargegevens!AB14 -> 14 | BN12: =IF(Calculator!R$102/4<Q12,Calculator!R$102*(BM12/60),Q12) -> 2.3333333 | BO12: =IF(BL12="Ja",365*24*4*BN12*C5,0) -> 6944 | BP12: =MAX(0,BH12-BE12-BI12) -> 505.33684 | BQ12: =MAX(0,MIN(BO12:BP12)) -> 505.33684 | BR12: =AF12 -> 0.15286 | BS12: =Jaargegevens!R14+Jaargegevens!AD14+Jaargegevens!J14 -> 0.47286 | BT12: =BS12-BR12 -> 0.32 | BU12: =Jaargegevens!AF14 -> 0.85 | BV12: =BT12*BU12 -> 0.272 | BX12: =-(((1-I12)*R12)*(BR12+BV12)) -> -17.248056 | BY12: =(BE12*(AJ12-AF12)) -> 35.671233 | BZ12: =BC12*BJ12 -> 31.849315 | CA12: =(BQ12*BV12) -> 137.45162 | CB12: =CN12 -> 0 | CC12: =(U12-V12) -> 3.0575342 | CD12: =ROUND(SUM(BX12:CC12),0) -> 191 | CE12: =IF(CD12<>"",SUM(CD$12:CD12),"") -> 191 | CH12: =R12 -> 1014.9259 | CI12: =BC12 -> 212.32877 | CJ12: =CH12-CI12 -> 802.59712 | CK12: =Jaargegevens!G14 -> 10000 | CL12: =MAX(CJ12-CK12,0) -> 0 | CM12: =Jaargegevens!F14-Jaargegevens!H14 -> 0.03892 | CN12: =CL12*CM12 -> 0 | CP12: =R12 -> 1014.9259 | CQ12: =BC12 -> 212.32877 | CR12: =CP12-CQ12 -> 802.59712 | CS12: =AF12 -> 0.15286 | CT12: =CR12*CS12 -> 122.685 | CV12: =CP12 -> 1014.9259 | CW12: =(1-I12)*CV12 -> 40.597035 | CX12: =CV12-CW12 -> 974.32885 | CY12: =AY12 -> 297.26027 | CZ12: =AJ12 -> 0.27286 | DA12: =CY12*CZ12 -> 81.110438 | DB12: =CQ12 -> 212.32877 | DC12: =BJ12 -> 0.15 | DD12: =DB12*DC12 -> 31.849315 | DE12: =IF(CX12-CY12-DB12>0,CX12-CY12-DB12,0) -> 464.73981 | DF12: =BR12+BV12 -> 0.42486 | DG12: =DE12*DF12 -> 197.44936 | DH12: =DA12+DD12+DG12 -> 310.40911 | DJ12: =DH12-CT12 -> 187.72411 | DK12: =CB12 -> 0 | DL12: =CC12 -> 3.0575342 | DN12: =SUM(DI12:DM12) -> 190.78165
A13: 2 | B13: =Jaargegevens!A15 -> 2026 | C13: =IF(A13>Calculator!$R$96,"Nee",IF(H12<K13,"Ja","Nee")) -> Ja | D13: =Jaargegevens!D15 -> 0.028 | F13: =Cycli!Q11 -> 1.5 | G13: =F13*365 -> 547.5 | H13: =SUM(G$12:G13) -> 594 | I13: =Calculator!$R$94 -> 0.96 | K13: =K12 -> 10000 | L13: =Calculator!$R$100 -> 0.7 | M13: =Degradatie!F17 -> 0.025425577 | N13: =SUM(M$10:M13) -> 0.027589135 | P13: =((1-N12)+(1-N13))/2 -> 0.98512365 | Q13: =P13*Calculator!$R$92 -> 21.524952 | R13: =Q13*G13 -> 11784.911 | S13: =SUM(R$12:R13) -> 12799.837 | U13: =(12*Calculator!S45+12*Calculator!R73)*(1+D12) -> 185.51232 | V13: =IF(Calculator!$R$73>0,(Jaargegevens!L15+Jaargegevens!M15)*12,Jaargegevens!L15*12) -> 148.36032 | X13: =X12*(1+$D12) -> 0.05896848 | Y13: =Jaargegevens!F15 -> 0.11046 | Z13: =SUM(X13:Y13) -> 0.16942848 | AA13: =IF(Calculator!$R$25="Dynamisch",Opbrengsten!Z13,AA12*(1+D12)) -> 0.1548 | AB13: =IF(Calculator!$R$25="Dynamisch",0,AB12*(1+D12)) -> 0.14448 | AD13: =Jaargegevens!O15+Jaargegevens!P15 -> 0.03032 | AE13: =Y13 -> 0.11046 | AF13: =SUM(AD13:AE13) -> 0.14078 | AH13: =Jaargegevens!R15 -> 0.1548 | AI13: =Y13 -> 0.11046 | AJ13: =SUM(AH13:AI13) -> 0.26526 | AL13: =(AD13+AH13)/2 -> 0.09256 | AM13: =AE13 -> 0.11046 | AN13: =SUM(AL13:AM13) -> 0.20302 | AP13: =Calculator!$R$38 -> 4500 | AQ13: =AW13 -> 0 | AR13: =SUM(AP13:AQ13) -> 4500 | AT13: =MIN(MAX(0,-Jaargegevens!U15),365) -> 0 | AU13: =MAX(0,(Opbrengsten!AT13/365)*Calculator!$R$71) -> 0 | AV13: =Jaargegevens!X15 -> 3.5 | AW13: =AV13*AU13 -> 0 | AY13: =AR13-BB13 -> 3500 | AZ13: =Calculator!$R$34 -> 3500 | BA13: =Calculator!$V$36 -> 0.28571429 | BB13: =Calculator!$R$36 -> 1000 | BC13: =MIN(Calculator!$R$32,R13) -> 2500 | BD13: =AY13+BB13 -> 4500 | BE13: =MIN(BD13-BB13,R13-BC13) -> 3500 | BG13: =BC13 -> 2500 | BH13: =R13 -> 11784.911 | BI13: =MIN(BG13:BH13) -> 2500 | BJ13: =IF(B13<=Jaargegevens!$M$7,Calculator!$S$49,AH13+Jaargegevens!S15+Jaargegevens!J15) -> 0.15 | BL13: =IF(Calculator!$R$118<=B13,Keuzemenu!$I$18,Keuzemenu!$I$17) -> Ja | BM13: =Jaargegevens!AB15 -> 14 | BN13: =IF(Calculator!R$102/4<Q13,Calculator!R$102*(BM13/60),Q13) -> 2.3333333 | BO13: =IF(BL13="Ja",365*24*4*BN13,0) -> 81760 | BP13: =MAX(0,BH13-BE13-BI13) -> 5784.9111 | BQ13: =MAX(0,MIN(BO13:BP13)) -> 5784.9111 | BR13: =AF13 -> 0.14078 | BS13: =Jaargegevens!R15+Jaargegevens!AD15+Jaargegevens!J15 -> 0.46526 | BT13: =BS13-BR13 -> 0.32448 | BU13: =Jaargegevens!AF15 -> 0.85 | BV13: =BT13*BU13 -> 0.275808 | BX13: =-(((1-I13)*R13)*(BR13+BV13)) -> -196.3781 | BY13: =(BE13*(AJ13-AF13)) -> 435.68 | BZ13: =BC13*BJ13 -> 375 | CA13: =BQ13*BV13 -> 1595.5248 | CB13: =CN13 -> 0 | CC13: =U13-V13 -> 37.152 | CD13: =ROUND(SUM(BX13:CC13),0) -> 2247 | CE13: =IF(CD13<>"",SUM(CD$12:CD13),"") -> 2438 | CH13: =R13 -> 11784.911 | CI13: =BC13 -> 2500 | CJ13: =CH13-CI13 -> 9284.9111 | CK13: =Jaargegevens!G15 -> 10000 | CL13: =MAX(CJ13-CK13,0) -> 0 | CM13: =Jaargegevens!F15-Jaargegevens!H15 -> 0.02652 | CN13: =CL13*CM13 -> 0 | CP13: =R13 -> 11784.911 | CQ13: =BC13 -> 2500 | CR13: =CP13-CQ13 -> 9284.9111 | CS13: =AF13 -> 0.14078 | CT13: =CR13*CS13 -> 1307.1298 | CV13: =CP13 -> 11784.911 | CW13: =(1-I13)*CV13 -> 471.39644 | CX13: =CV13-CW13 -> 11313.515 | CY13: =AY13 -> 3500 | CZ13: =AJ13 -> 0.26526 | DA13: =CY13*CZ13 -> 928.41 | DB13: =CQ13 -> 2500 | DC13: =BJ13 -> 0.15 | DD13: =DB13*DC13 -> 375 | DE13: =IF(CX13-CY13-DB13>0,CX13-CY13-DB13,0) -> 5313.5147 | DF13: =BR13+BV13 -> 0.416588 | DG13: =DE13*DF13 -> 2213.5465 | DH13: =DA13+DD13+DG13 -> 3516.9565 | DJ13: =DH13-CT13 -> 2209.8267 | DK13: =CB13 -> 0 | DL13: =CC13 -> 37.152 | DN13: =ROUND(SUM(DI13:DM13),0) -> 2247
A14: 3 | B14: =Jaargegevens!A16 -> 2027 | C14: =IF(A14>Calculator!$R$96,"Nee",IF(H13<K14,"Ja","Nee")) -> Ja | D14: =Jaargegevens!D16 -> 0.025 | F14: =Cycli!Q12 -> 1.5 | G14: =F14*365 -> 547.5 | H14: =SUM(G$12:G14) -> 1141.5 | I14: =Calculator!$R$94 -> 0.96 | K14: =K13 -> 10000 | L14: =Calculator!$R$100 -> 0.7 | M14: =Degradatie!F18 -> 0.024849836 | N14: =SUM(M$10:M14) -> 0.05243897 | P14: =((1-N13)+(1-N14))/2 -> 0.95998595 | Q14: =P14*Calculator!$R$92 -> 20.975693 | R14: =Q14*G14 -> 11484.192 | S14: =SUM(R$12:R14) -> 24284.029 | U14: =U13*(1+D13) -> 190.70666 | V14: =IF(Calculator!$R$73>0,(Jaargegevens!L16+Jaargegevens!M16)*12,Jaargegevens!L16*12) -> 152.51441 | X14: =X13*(1+$D13) -> 0.060619597 | Y14: =Jaargegevens!F16 -> 0.11046 | Z14: =SUM(X14:Y14) -> 0.1710796 | AA14: =IF(Calculator!$R$25="Dynamisch",Opbrengsten!Z14,AA13*(1+D13)) -> 0.1591344 | AB14: =IF(Calculator!$R$25="Dynamisch",0,AB13*(1+D13)) -> 0.14852544 | AD14: =Jaargegevens!O16+Jaargegevens!P16 -> 0.03060896 | AE14: =Y14 -> 0.11046 | AF14: =SUM(AD14:AE14) -> 0.14106896 | AH14: =Jaargegevens!R16 -> 0.1591344 | AI14: =Y14 -> 0.11046 | AJ14: =SUM(AH14:AI14) -> 0.2695944 | AL14: =(AD14+AH14)/2 -> 0.09487168 | AM14: =AE14 -> 0.11046 | AN14: =SUM(AL14:AM14) -> 0.20533168 | AP14: =Calculator!$R$38 -> 4500 | AQ14: =AW14 -> 0 | AR14: =SUM(AP14:AQ14) -> 4500 | AT14: =MIN(MAX(0,-Jaargegevens!U16),365) -> 0 | AU14: =MAX(0,(Opbrengsten!AT14/365)*Calculator!$R$71) -> 0 | AV14: =Jaargegevens!X16 -> 3.5 | AW14: =AV14*AU14 -> 0 | AY14: =AR14-BB14 -> 3500 | AZ14: =Calculator!$R$34 -> 3500 | BA14: =Calculator!$V$36 -> 0.28571429 | BB14: =Calculator!$R$36 -> 1000 | BC14: =MIN(Calculator!$R$32,R14) -> 2500 | BD14: =AY14+BB14 -> 4500 | BE14: =MIN(BD14-BB14,R14-BC14) -> 3500 | BG14: =BC14 -> 2500 | BH14: =R14 -> 11484.192 | BI14: =MIN(BG14:BH14) -> 2500 | BJ14: =IF(B14<=Jaargegevens!$M$7,Calculator!$S$49,AH14+Jaargegevens!S16+Jaargegevens!J16) -> 0.1591344 | BL14: =IF(Calculator!$R$118<=B14,Keuzemenu!$I$18,Keuzemenu!$I$17) -> Ja | BM14: =Jaargegevens!AB16 -> 14 | BN14: =IF(Calculator!R$102/4<Q14,Calculator!R$102*(BM14/60),Q14) -> 2.3333333 | BO14: =IF(BL14="Ja",365*24*4*BN14,0) -> 81760 | BP14: =MAX(0,BH14-BE14-BI14) -> 5484.1919 | BQ14: =MAX(0,MIN(BO14:BP14)) -> 5484.1919 | BR14: =AF14 -> 0.14106896 | BS14: =Jaargegevens!R16+Jaargegevens!AD16+Jaargegevens!J16 -> 0.3591344 | BT14: =BS14-BR14 -> 0.21806544 | BU14: =Jaargegevens!AF16 -> 0.85 | BV14: =BT14*BU14 -> 0.18535562 | BX14: =-(((1-I14)*R14)*(BR14+BV14)) -> -149.9489 | BY14: =(BE14*(AJ14-AF14)) -> 449.83904 | BZ14: =BC14*BJ14 -> 397.836 | CA14: =BQ14*BV14 -> 1016.5258 | CB14: =CN14 -> 0 | CC14: =U14-V14 -> 38.192256 | CD14: =ROUND(SUM(BX14:CC14),0) -> 1752 | CE14: =IF(CD14<>"",SUM(CD$12:CD14),"") -> 4190 | CH14: =R14 -> 11484.192 | CI14: =BC14 -> 2500 | CJ14: =CH14-CI14 -> 8984.1919 | CK14: =Jaargegevens!G16 -> 10000 | CL14: =MAX(CJ14-CK14,0) -> 0 | CM14: =Jaargegevens!F16-Jaargegevens!H16 -> 0.02652 | CN14: =CL14*CM14 -> 0 | CP14: =R14 -> 11484.192 | CQ14: =BC14 -> 2500 | CR14: =CP14-CQ14 -> 8984.1919 | CS14: =AF14 -> 0.14106896 | CT14: =CR14*CS14 -> 1267.3906 | CV14: =CP14 -> 11484.192 | CW14: =(1-I14)*CV14 -> 459.36768 | CX14: =CV14-CW14 -> 11024.824 | CY14: =AY14 -> 3500 | CZ14: =AJ14 -> 0.2695944 | DA14: =CY14*CZ14 -> 943.5804 | DB14: =CQ14 -> 2500 | DC14: =BJ14 -> 0.1591344 | DD14: =DB14*DC14 -> 397.836 | DE14: =IF(CX14-CY14-DB14>0,CX14-CY14-DB14,0) -> 5024.8242 | DF14: =BR14+BV14 -> 0.32642458 | DG14: =DE14*DF14 -> 1640.2262 | DH14: =DA14+DD14+DG14 -> 2981.6426 | DJ14: =DH14-CT14 -> 1714.2519 | DK14: =CB14 -> 0 | DL14: =CC14 -> 38.192256 | DN14: =ROUND(SUM(DI14:DM14),0) -> 1752
A15: 4 | B15: =Jaargegevens!A17 -> 2028 | C15: =IF(A15>Calculator!$R$96,"Nee",IF(H14<K15,"Ja","Nee")) -> Ja | D15: =Jaargegevens!D17 -> 0.025 | F15: =Cycli!Q13 -> 1.5 | G15: =F15*365 -> 547.5 | H15: =SUM(G$12:G15) -> 1689 | I15: =Calculator!$R$94 -> 0.96 | K15: =K14 -> 10000 | L15: =Calculator!$R$100 -> 0.7 | M15: =Degradatie!F19 -> 0.024229448 | N15: =SUM(M$10:M15) -> 0.076668418 | P15: =((1-N14)+(1-N15))/2 -> 0.93544631 | Q15: =P15*Calculator!$R$92 -> 20.439502 | R15: =Q15*G15 -> 11190.627 | S15: =SUM(R$12:R15) -> 35474.656 | U15: =U14*(1+D14) -> 195.47433 | V15: =IF(Calculator!$R$73>0,(Jaargegevens!L17+Jaargegevens!M17)*12,Jaargegevens!L17*12) -> 156.32727 | X15: =X14*(1+$D14) -> 0.062135087 | Y15: =Jaargegevens!F17 -> 0.11046 | Z15: =SUM(X15:Y15) -> 0.17259509 | AA15: =IF(Calculator!$R$25="Dynamisch",Opbrengsten!Z15,AA14*(1+D14)) -> 0.16311276 | AB15: =IF(Calculator!$R$25="Dynamisch",0,AB14*(1+D14)) -> 0.15223858 | AD15: =Jaargegevens!O17+Jaargegevens!P17 -> 0.030874184 | AE15: =Y15 -> 0.11046 | AF15: =SUM(AD15:AE15) -> 0.14133418 | AH15: =Jaargegevens!R17 -> 0.16311276 | AI15: =Y15 -> 0.11046 | AJ15: =SUM(AH15:AI15) -> 0.27357276 | AL15: =(AD15+AH15)/2 -> 0.096993472 | AM15: =AE15 -> 0.11046 | AN15: =SUM(AL15:AM15) -> 0.20745347 | AP15: =Calculator!$R$38 -> 4500 | AQ15: =AW15 -> 0 | AR15: =SUM(AP15:AQ15) -> 4500 | AT15: =MIN(MAX(0,-Jaargegevens!U17),365) -> 0 | AU15: =MAX(0,(Opbrengsten!AT15/365)*Calculator!$R$71) -> 0 | AV15: =Jaargegevens!X17 -> 3.5 | AW15: =AV15*AU15 -> 0 | AY15: =AR15-BB15 -> 3500 | AZ15: =Calculator!$R$34 -> 3500 | BA15: =Calculator!$V$36 -> 0.28571429 | BB15: =Calculator!$R$36 -> 1000 | BC15: =MIN(Calculator!$R$32,R15) -> 2500 | BD15: =AY15+BB15 -> 4500 | BE15: =MIN(BD15-BB15,R15-BC15) -> 3500 | BG15: =BC15 -> 2500 | BH15: =R15 -> 11190.627 | BI15: =MIN(BG15:BH15) -> 2500 | BJ15: =IF(B15<=Jaargegevens!$M$7,Calculator!$S$49,AH15+Jaargegevens!S17+Jaargegevens!J17) -> 0.16311276 | BL15: =IF(Calculator!$R$118<=B15,Keuzemenu!$I$18,Keuzemenu!$I$17) -> Ja | BM15: =Jaargegevens!AB17 -> 14 | BN15: =IF(Calculator!R$102/4<Q15,Calculator!R$102*(BM15/60),Q15) -> 2.3333333 | BO15: =IF(BL15="Ja",365*24*4*BN15,0) -> 81760 | BP15: =MAX(0,BH15-BE15-BI15) -> 5190.6272 | BQ15: =MAX(0,MIN(BO15:BP15)) -> 5190.6272 | BR15: =AF15 -> 0.14133418 | BS15: =Jaargegevens!R17+Jaargegevens!AD17+Jaargegevens!J17 -> 0.36311276 | BT15: =BS15-BR15 -> 0.22177858 | BU15: =Jaargegevens!AF17 -> 0.85 | BV15: =BT15*BU15 -> 0.18851179 | BX15: =-(((1-I15)*R15)*(BR15+BV15)) -> -147.64733 | BY15: =(BE15*(AJ15-AF15)) -> 462.83502 | BZ15: =BC15*BJ15 -> 407.7819 | CA15: =BQ15*BV15 -> 978.49443 | CB15: =CN15 -> 0 | CC15: =U15-V15 -> 39.147062 | CD15: =ROUND(SUM(BX15:CC15),0) -> 1741 | CE15: =IF(CD15<>"",SUM(CD$12:CD15),"") -> 5931 | CH15: =R15 -> 11190.627 | CI15: =BC15 -> 2500 | CJ15: =CH15-CI15 -> 8690.6272 | CK15: =Jaargegevens!G17 -> 10000 | CL15: =MAX(CJ15-CK15,0) -> 0 | CM15: =Jaargegevens!F17-Jaargegevens!H17 -> 0.02652 | CN15: =CL15*CM15 -> 0 | CP15: =R15 -> 11190.627 | CQ15: =BC15 -> 2500 | CR15: =CP15-CQ15 -> 8690.6272 | CS15: =AF15 -> 0.14133418 | CT15: =CR15*CS15 -> 1228.2827 | CV15: =CP15 -> 11190.627 | CW15: =(1-I15)*CV15 -> 447.62509 | CX15: =CV15-CW15 -> 10743.002 | CY15: =AY15 -> 3500 | CZ15: =AJ15 -> 0.27357276 | DA15: =CY15*CZ15 -> 957.50466 | DB15: =CQ15 -> 2500 | DC15: =BJ15 -> 0.16311276 | DD15: =DB15*DC15 -> 407.7819 | DE15: =IF(CX15-CY15-DB15>0,CX15-CY15-DB15,0) -> 4743.0021 | DF15: =BR15+BV15 -> 0.32984597 | DG15: =DE15*DF15 -> 1564.4602 | DH15: =DA15+DD15+DG15 -> 2929.7467 | DJ15: =DH15-CT15 -> 1701.464 | DK15: =CB15 -> 0 | DL15: =CC15 -> 39.147062 | DN15: =ROUND(SUM(DI15:DM15),0) -> 1741
A16: 5 | B16: =Jaargegevens!A18 -> 2029 | C16: =IF(A16>Calculator!$R$96,"Nee",IF(H15<K16,"Ja","Nee")) -> Ja | D16: =Jaargegevens!D18 -> 0.025 | F16: =Cycli!Q14 -> 1.5 | G16: =F16*365 -> 547.5 | H16: =SUM(G$12:G16) -> 2236.5 | I16: =Calculator!$R$94 -> 0.96 | K16: =K15 -> 10000 | L16: =Calculator!$R$100 -> 0.7 | M16: =Degradatie!F20 -> 0.023560951 | N16: =SUM(M$10:M16) -> 0.10022937 | P16: =((1-N15)+(1-N16))/2 -> 0.91155111 | Q16: =P16*Calculator!$R$92 -> 19.917392 | R16: =Q16*G16 -> 10904.772 | S16: =SUM(R$12:R16) -> 46379.428 | U16: =U15*(1+D15) -> 200.36119 | V16: =IF(Calculator!$R$73>0,(Jaargegevens!L18+Jaargegevens!M18)*12,Jaargegevens!L18*12) -> 160.23545 | X16: =X15*(1+$D15) -> 0.063688465 | Y16: =Jaargegevens!F18 -> 0.11046 | Z16: =SUM(X16:Y16) -> 0.17414846 | AA16: =IF(Calculator!$R$25="Dynamisch",Opbrengsten!Z16,AA15*(1+D15)) -> 0.16719058 | AB16: =IF(Calculator!$R$25="Dynamisch",0,AB15*(1+D15)) -> 0.15604454 | AD16: =Jaargegevens!O18+Jaargegevens!P18 -> 0.031146039 | AE16: =Y16 -> 0.11046 | AF16: =SUM(AD16:AE16) -> 0.14160604 | AH16: =Jaargegevens!R18 -> 0.16719058 | AI16: =Y16 -> 0.11046 | AJ16: =SUM(AH16:AI16) -> 0.27765058 | AL16: =(AD16+AH16)/2 -> 0.099168309 | AM16: =AE16 -> 0.11046 | AN16: =SUM(AL16:AM16) -> 0.20962831 | AP16: =Calculator!$R$38 -> 4500 | AQ16: =AW16 -> 0 | AR16: =SUM(AP16:AQ16) -> 4500 | AT16: =MIN(MAX(0,-Jaargegevens!U18),365) -> 0 | AU16: =MAX(0,(Opbrengsten!AT16/365)*Calculator!$R$71) -> 0 | AV16: =Jaargegevens!X18 -> 3.5 | AW16: =AV16*AU16 -> 0 | AY16: =AR16-BB16 -> 3500 | AZ16: =Calculator!$R$34 -> 3500 | BA16: =Calculator!$V$36 -> 0.28571429 | BB16: =Calculator!$R$36 -> 1000 | BC16: =MIN(Calculator!$R$32,R16) -> 2500 | BD16: =AY16+BB16 -> 4500 | BE16: =MIN(BD16-BB16,R16-BC16) -> 3500 | BG16: =BC16 -> 2500 | BH16: =R16 -> 10904.772 | BI16: =MIN(BG16:BH16) -> 2500 | BJ16: =IF(B16<=Jaargegevens!$M$7,Calculator!$S$49,AH16+Jaargegevens!S18+Jaargegevens!J18) -> 0.16719058 | BL16: =IF(Calculator!$R$118<=B16,Keuzemenu!$I$18,Keuzemenu!$I$17) -> Ja | BM16: =Jaargegevens!AB18 -> 14 | BN16: =IF(Calculator!R$102/4<Q16,Calculator!R$102*(BM16/60),Q16) -> 2.3333333 | BO16: =IF(BL16="Ja",365*24*4*BN16,0) -> 81760 | BP16: =MAX(0,BH16-BE16-BI16) -> 4904.7719 | BQ16: =MAX(0,MIN(BO16:BP16)) -> 4904.7719 | BR16: =AF16 -> 0.14160604 | BS16: =Jaargegevens!R18+Jaargegevens!AD18+Jaargegevens!J18 -> 0.36719058 | BT16: =BS16-BR16 -> 0.22558454 | BU16: =Jaargegevens!AF18 -> 0.85 | BV16: =BT16*BU16 -> 0.19174686 | BX16: =-(((1-I16)*R16)*(BR16+BV16)) -> -145.40549 | BY16: =(BE16*(AJ16-AF16)) -> 476.15589 | BZ16: =BC16*BJ16 -> 417.97645 | CA16: =BQ16*BV16 -> 940.47462 | CB16: =CN16 -> 0 | CC16: =U16-V16 -> 40.125739 | CD16: =ROUND(SUM(BX16:CC16),0) -> 1729 | CE16: =IF(CD16<>"",SUM(CD$12:CD16),"") -> 7660 | CH16: =R16 -> 10904.772 | CI16: =BC16 -> 2500 | CJ16: =CH16-CI16 -> 8404.7719 | CK16: =Jaargegevens!G18 -> 10000 | CL16: =MAX(CJ16-CK16,0) -> 0 | CM16: =Jaargegevens!F18-Jaargegevens!H18 -> 0.02652 | CN16: =CL16*CM16 -> 0 | CP16: =R16 -> 10904.772 | CQ16: =BC16 -> 2500 | CR16: =CP16-CQ16 -> 8404.7719 | CS16: =AF16 -> 0.14160604 | CT16: =CR16*CS16 -> 1190.1665 | CV16: =CP16 -> 10904.772 | CW16: =(1-I16)*CV16 -> 436.19088 | CX16: =CV16-CW16 -> 10468.581 | CY16: =AY16 -> 3500 | CZ16: =AJ16 -> 0.27765058 | DA16: =CY16*CZ16 -> 971.77703 | DB16: =CQ16 -> 2500 | DC16: =BJ16 -> 0.16719058 | DD16: =DB16*DC16 -> 417.97645 | DE16: =IF(CX16-CY16-DB16>0,CX16-CY16-DB16,0) -> 4468.5811 | DF16: =BR16+BV16 -> 0.3333529 | DG16: =DE16*DF16 -> 1489.6144 | DH16: =DA16+DD16+DG16 -> 2879.3679 | DJ16: =DH16-CT16 -> 1689.2015 | DK16: =CB16 -> 0 | DL16: =CC16 -> 40.125739 | DN16: =ROUND(SUM(DI16:DM16),0) -> 1729
A17: 6 | B17: =Jaargegevens!A19 -> 2030 | C17: =IF(A17>Calculator!$R$96,"Nee",IF(H16<K17,"Ja","Nee")) -> Ja | D17: =Jaargegevens!D19 -> 0.025 | F17: =Cycli!Q15 -> 1.5 | G17: =F17*365 -> 547.5 | H17: =SUM(G$12:G17) -> 2784 | I17: =Calculator!$R$94 -> 0.96 | K17: =K16 -> 10000 | L17: =Calculator!$R$100 -> 0.7 | M17: =Degradatie!F21 -> 0.022840614 | N17: =SUM(M$10:M17) -> 0.12306998 | P17: =((1-N16)+(1-N17))/2 -> 0.88835032 | Q17: =P17*Calculator!$R$92 -> 19.410455 | R17: =Q17*G17 -> 10627.224 | S17: =SUM(R$12:R17) -> 57006.652 | U17: =U16*(1+D16) -> 205.37022 | V17: =IF(Calculator!$R$73>0,(Jaargegevens!L19+Jaargegevens!M19)*12,Jaargegevens!L19*12) -> 164.24134 | X17: =X16*(1+$D16) -> 0.065280676 | Y17: =Jaargegevens!F19 -> 0.11046 | Z17: =SUM(X17:Y17) -> 0.17574068 | AA17: =IF(Calculator!$R$25="Dynamisch",Opbrengsten!Z17,AA16*(1+D16)) -> 0.17137034 | AB17: =IF(Calculator!$R$25="Dynamisch",0,AB16*(1+D16)) -> 0.15994565 | AD17: =Jaargegevens!O19+Jaargegevens!P19 -> 0.03142469 | AE17: =Y17 -> 0.11046 | AF17: =SUM(AD17:AE17) -> 0.14188469 | AH17: =Jaargegevens!R19 -> 0.17137034 | AI17: =Y17 -> 0.11046 | AJ17: =SUM(AH17:AI17) -> 0.28183034 | AL17: =(AD17+AH17)/2 -> 0.10139752 | AM17: =AE17 -> 0.11046 | AN17: =SUM(AL17:AM17) -> 0.21185752 | AP17: =Calculator!$R$38 -> 4500 | AQ17: =AW17 -> 0 | AR17: =SUM(AP17:AQ17) -> 4500 | AT17: =MIN(MAX(0,-Jaargegevens!U19),365) -> 0 | AU17: =MAX(0,(Opbrengsten!AT17/365)*Calculator!$R$71) -> 0 | AV17: =Jaargegevens!X19 -> 3.5 | AW17: =AV17*AU17 -> 0 | AY17: =AR17-BB17 -> 3500 | AZ17: =Calculator!$R$34 -> 3500 | BA17: =Calculator!$V$36 -> 0.28571429 | BB17: =Calculator!$R$36 -> 1000 | BC17: =MIN(Calculator!$R$32,R17) -> 2500 | BD17: =AY17+BB17 -> 4500 | BE17: =MIN(BD17-BB17,R17-BC17) -> 3500 | BG17: =BC17 -> 2500 | BH17: =R17 -> 10627.224 | BI17: =MIN(BG17:BH17) -> 2500 | BJ17: =IF(B17<=Jaargegevens!$M$7,Calculator!$S$49,AH17+Jaargegevens!S19+Jaargegevens!J19) -> 0.17137034 | BL17: =IF(Calculator!$R$118<=B17,Keuzemenu!$I$18,Keuzemenu!$I$17) -> Ja | BM17: =Jaargegevens!AB19 -> 14 | BN17: =IF(Calculator!R$102/4<Q17,Calculator!R$102*(BM17/60),Q17) -> 2.3333333 | BO17: =IF(BL17="Ja",365*24*4*BN17,0) -> 81760 | BP17: =MAX(0,BH17-BE17-BI17) -> 4627.2239 | BQ17: =MAX(0,MIN(BO17:BP17)) -> 4627.2239 | BR17: =AF17 -> 0.14188469 | BS17: =Jaargegevens!R19+Jaargegevens!AD19+Jaargegevens!J19 -> 0.37137034 | BT17: =BS17-BR17 -> 0.22948565 | BU17: =Jaargegevens!AF19 -> 0.85 | BV17: =BT17*BU17 -> 0.19506281 | BX17: =-(((1-I17)*R17)*(BR17+BV17)) -> -143.23266 | BY17: =(BE17*(AJ17-AF17)) -> 489.80979 | BZ17: =BC17*BJ17 -> 428.42586 | CA17: =BQ17*BV17 -> 902.59928 | CB17: =CN17 -> 0 | CC17: =U17-V17 -> 41.128882 | CD17: =ROUND(SUM(BX17:CC17),0) -> 1719 | CE17: =IF(CD17<>"",SUM(CD$12:CD17),"") -> 9379 | CH17: =R17 -> 10627.224 | CI17: =BC17 -> 2500 | CJ17: =CH17-CI17 -> 8127.2239 | CK17: =Jaargegevens!G19 -> 10000 | CL17: =MAX(CJ17-CK17,0) -> 0 | CM17: =Jaargegevens!F19-Jaargegevens!H19 -> 0.02652 | CN17: =CL17*CM17 -> 0 | CP17: =R17 -> 10627.224 | CQ17: =BC17 -> 2500 | CR17: =CP17-CQ17 -> 8127.2239 | CS17: =AF17 -> 0.14188469 | CT17: =CR17*CS17 -> 1153.1286 | CV17: =CP17 -> 10627.224 | CW17: =(1-I17)*CV17 -> 425.08896 | CX17: =CV17-CW17 -> 10202.135 | CY17: =AY17 -> 3500 | CZ17: =AJ17 -> 0.28183034 | DA17: =CY17*CZ17 -> 986.4062 | DB17: =CQ17 -> 2500 | DC17: =BJ17 -> 0.17137034 | DD17: =DB17*DC17 -> 428.42586 | DE17: =IF(CX17-CY17-DB17>0,CX17-CY17-DB17,0) -> 4202.1349 | DF17: =BR17+BV17 -> 0.3369475 | DG17: =DE17*DF17 -> 1415.8988 | DH17: =DA17+DD17+DG17 -> 2830.7309 | DJ17: =DH17-CT17 -> 1677.6023 | DK17: =CB17 -> 0 | DL17: =CC17 -> 41.128882 | DN17: =ROUND(SUM(DI17:DM17),0) -> 1719
A18: 7 | B18: =Jaargegevens!A20 -> 2031 | C18: =IF(A18>Calculator!$R$96,"Nee",IF(H17<K18,"Ja","Nee")) -> Ja | D18: =Jaargegevens!D20 -> 0.025 | F18: =Cycli!Q16 -> 1.5 | G18: =F18*365 -> 547.5 | H18: =SUM(G$12:G18) -> 3331.5 | I18: =Calculator!$R$94 -> 0.96 | K18: =K17 -> 10000 | L18: =Calculator!$R$100 -> 0.7 | M18: =Degradatie!F22 -> 0.022064417 | N18: =SUM(M$10:M18) -> 0.1451344 | P18: =((1-N17)+(1-N18))/2 -> 0.86589781 | Q18: =P18*Calculator!$R$92 -> 18.919867 | R18: =Q18*G18 -> 10358.627 | S18: =SUM(R$12:R18) -> 67365.279 | U18: =U17*(1+D17) -> 210.50448 | V18: =IF(Calculator!$R$73>0,(Jaargegevens!L20+Jaargegevens!M20)*12,Jaargegevens!L20*12) -> 168.34737 | X18: =X17*(1+$D17) -> 0.066912693 | Y18: =Jaargegevens!F20 -> 0.11046 | Z18: =SUM(X18:Y18) -> 0.17737269 | AA18: =IF(Calculator!$R$25="Dynamisch",Opbrengsten!Z18,AA17*(1+D17)) -> 0.1756546 | AB18: =IF(Calculator!$R$25="Dynamisch",0,AB17*(1+D17)) -> 0.1639443 | AD18: =Jaargegevens!O20+Jaargegevens!P20 -> 0.031710307 | AE18: =Y18 -> 0.11046 | AF18: =SUM(AD18:AE18) -> 0.14217031 | AH18: =Jaargegevens!R20 -> 0.1756546 | AI18: =Y18 -> 0.11046 | AJ18: =SUM(AH18:AI18) -> 0.2861146 | AL18: =(AD18+AH18)/2 -> 0.10368245 | AM18: =AE18 -> 0.11046 | AN18: =SUM(AL18:AM18) -> 0.21414245 | AP18: =Calculator!$R$38 -> 4500 | AQ18: =AW18 -> 0 | AR18: =SUM(AP18:AQ18) -> 4500 | AT18: =MIN(MAX(0,-Jaargegevens!U20),365) -> 0 | AU18: =MAX(0,(Opbrengsten!AT18/365)*Calculator!$R$71) -> 0 | AV18: =Jaargegevens!X20 -> 3.5 | AW18: =AV18*AU18 -> 0 | AY18: =AR18-BB18 -> 3500 | AZ18: =Calculator!$R$34 -> 3500 | BA18: =Calculator!$V$36 -> 0.28571429 | BB18: =Calculator!$R$36 -> 1000 | BC18: =MIN(Calculator!$R$32,R18) -> 2500 | BD18: =AY18+BB18 -> 4500 | BE18: =MIN(BD18-BB18,R18-BC18) -> 3500 | BG18: =BC18 -> 2500 | BH18: =R18 -> 10358.627 | BI18: =MIN(BG18:BH18) -> 2500 | BJ18: =IF(B18<=Jaargegevens!$M$7,Calculator!$S$49,AH18+Jaargegevens!S20+Jaargegevens!J20) -> 0.1756546 | BL18: =IF(Calculator!$R$118<=B18,Keuzemenu!$I$18,Keuzemenu!$I$17) -> Ja | BM18: =Jaargegevens!AB20 -> 14 | BN18: =IF(Calculator!R$102/4<Q18,Calculator!R$102*(BM18/60),Q18) -> 2.3333333 | BO18: =IF(BL18="Ja",365*24*4*BN18,0) -> 81760 | BP18: =MAX(0,BH18-BE18-BI18) -> 4358.6273 | BQ18: =MAX(0,MIN(BO18:BP18)) -> 4358.6273 | BR18: =AF18 -> 0.14217031 | BS18: =Jaargegevens!R20+Jaargegevens!AD20+Jaargegevens!J20 -> 0.3756546 | BT18: =BS18-BR18 -> 0.2334843 | BU18: =Jaargegevens!AF20 -> 0.85 | BV18: =BT18*BU18 -> 0.19846165 | BX18: =-(((1-I18)*R18)*(BR18+BV18)) -> -141.13918 | BY18: =(BE18*(AJ18-AF18)) -> 503.80503 | BZ18: =BC18*BJ18 -> 439.13651 | CA18: =BQ18*BV18 -> 865.02036 | CB18: =CN18 -> 0 | CC18: =U18-V18 -> 42.157104 | CD18: =ROUND(SUM(BX18:CC18),0) -> 1709 | CE18: =IF(CD18<>"",SUM(CD$12:CD18),"") -> 11088 | CH18: =R18 -> 10358.627 | CI18: =BC18 -> 2500 | CJ18: =CH18-CI18 -> 7858.6273 | CK18: =Jaargegevens!G20 -> 10000 | CL18: =MAX(CJ18-CK18,0) -> 0 | CM18: =Jaargegevens!F20-Jaargegevens!H20 -> 0.02652 | CN18: =CL18*CM18 -> 0 | CP18: =R18 -> 10358.627 | CQ18: =BC18 -> 2500 | CR18: =CP18-CQ18 -> 7858.6273 | CS18: =AF18 -> 0.14217031 | CT18: =CR18*CS18 -> 1117.2634 | CV18: =CP18 -> 10358.627 | CW18: =(1-I18)*CV18 -> 414.34509 | CX18: =CV18-CW18 -> 9944.2822 | CY18: =AY18 -> 3500 | CZ18: =AJ18 -> 0.2861146 | DA18: =CY18*CZ18 -> 1001.4011 | DB18: =CQ18 -> 2500 | DC18: =BJ18 -> 0.1756546 | DD18: =DB18*DC18 -> 439.13651 | DE18: =IF(CX18-CY18-DB18>0,CX18-CY18-DB18,0) -> 3944.2822 | DF18: =BR18+BV18 -> 0.34063196 | DG18: =DE18*DF18 -> 1343.5486 | DH18: =DA18+DD18+DG18 -> 2784.0862 | DJ18: =DH18-CT18 -> 1666.8227 | DK18: =CB18 -> 0 | DL18: =CC18 -> 42.157104 | DN18: =ROUND(SUM(DI18:DM18),0) -> 1709
A19: 8 | B19: =Jaargegevens!A21 -> 2032 | C19: =IF(A19>Calculator!$R$96,"Nee",IF(H18<K19,"Ja","Nee")) -> Ja | D19: =Jaargegevens!D21 -> 0.025 | F19: =Cycli!Q17 -> 1.5 | G19: =F19*365 -> 547.5 | H19: =SUM(G$12:G19) -> 3879 | I19: =Calculator!$R$94 -> 0.96 | K19: =K18 -> 10000 | L19: =Calculator!$R$100 -> 0.7 | M19: =Degradatie!F23 -> 0.021228028 | N19: =SUM(M$10:M19) -> 0.16636243 | P19: =((1-N18)+(1-N19))/2 -> 0.84425159 | Q19: =P19*Calculator!$R$92 -> 18.446897 | R19: =Q19*G19 -> 10099.676 | S19: =SUM(R$12:R19) -> 77464.955 | U19: =U18*(1+D18) -> 215.76709 | V19: =IF(Calculator!$R$73>0,(Jaargegevens!L21+Jaargegevens!M21)*12,Jaargegevens!L21*12) -> 172.55605 | X19: =X18*(1+$D18) -> 0.06858551 | Y19: =Jaargegevens!F21 -> 0.11046 | Z19: =SUM(X19:Y19) -> 0.17904551 | AA19: =IF(Calculator!$R$25="Dynamisch",Opbrengsten!Z19,AA18*(1+D18)) -> 0.18004597 | AB19: =IF(Calculator!$R$25="Dynamisch",0,AB18*(1+D18)) -> 0.1680429 | AD19: =Jaargegevens!O21+Jaargegevens!P21 -> 0.032003064 | AE19: =Y19 -> 0.11046 | AF19: =SUM(AD19:AE19) -> 0.14246306 | AH19: =Jaargegevens!R21 -> 0.18004597 | AI19: =Y19 -> 0.11046 | AJ19: =SUM(AH19:AI19) -> 0.29050597 | AL19: =(AD19+AH19)/2 -> 0.10602452 | AM19: =AE19 -> 0.11046 | AN19: =SUM(AL19:AM19) -> 0.21648452 | AP19: =Calculator!$R$38 -> 4500 | AQ19: =AW19 -> 0 | AR19: =SUM(AP19:AQ19) -> 4500 | AT19: =MIN(MAX(0,-Jaargegevens!U21),365) -> 0 | AU19: =MAX(0,(Opbrengsten!AT19/365)*Calculator!$R$71) -> 0 | AV19: =Jaargegevens!X21 -> 3.5 | AW19: =AV19*AU19 -> 0 | AY19: =AR19-BB19 -> 3500 | AZ19: =Calculator!$R$34 -> 3500 | BA19: =Calculator!$V$36 -> 0.28571429 | BB19: =Calculator!$R$36 -> 1000 | BC19: =MIN(Calculator!$R$32,R19) -> 2500 | BD19: =AY19+BB19 -> 4500 | BE19: =MIN(BD19-BB19,R19-BC19) -> 3500 | BG19: =BC19 -> 2500 | BH19: =R19 -> 10099.676 | BI19: =MIN(BG19:BH19) -> 2500 | BJ19: =IF(B19<=Jaargegevens!$M$7,Calculator!$S$49,AH19+Jaargegevens!S21+Jaargegevens!J21) -> 0.18004597 | BL19: =IF(Calculator!$R$118<=B19,Keuzemenu!$I$18,Keuzemenu!$I$17) -> Ja | BM19: =Jaargegevens!AB21 -> 14 | BN19: =IF(Calculator!R$102/4<Q19,Calculator!R$102*(BM19/60),Q19) -> 2.3333333 | BO19: =IF(BL19="Ja",365*24*4*BN19,0) -> 81760 | BP19: =MAX(0,BH19-BE19-BI19) -> 4099.6762 | BQ19: =MAX(0,MIN(BO19:BP19)) -> 4099.6762 | BR19: =AF19 -> 0.14246306 | BS19: =Jaargegevens!R21+Jaargegevens!AD21+Jaargegevens!J21 -> 0.38004597 | BT19: =BS19-BR19 -> 0.2375829 | BU19: =Jaargegevens!AF21 -> 0.85 | BV19: =BT19*BU19 -> 0.20194547 | BX19: =-(((1-I19)*R19)*(BR19+BV19)) -> -139.13659 | BY19: =(BE19*(AJ19-AF19)) -> 518.15016 | BZ19: =BC19*BJ19 -> 450.11492 | CA19: =BQ19*BV19 -> 827.91103 | CB19: =CN19 -> 0 | CC19: =U19-V19 -> 43.211032 | CD19: =ROUND(SUM(BX19:CC19),0) -> 1700 | CE19: =IF(CD19<>"",SUM(CD$12:CD19),"") -> 12788 | CH19: =R19 -> 10099.676 | CI19: =BC19 -> 2500 | CJ19: =CH19-CI19 -> 7599.6762 | CK19: =Jaargegevens!G21 -> 10000 | CL19: =MAX(CJ19-CK19,0) -> 0 | CM19: =Jaargegevens!F21-Jaargegevens!H21 -> 0.02652 | CN19: =CL19*CM19 -> 0 | CP19: =R19 -> 10099.676 | CQ19: =BC19 -> 2500 | CR19: =CP19-CQ19 -> 7599.6762 | CS19: =AF19 -> 0.14246306 | CT19: =CR19*CS19 -> 1082.6732 | CV19: =CP19 -> 10099.676 | CW19: =(1-I19)*CV19 -> 403.98705 | CX19: =CV19-CW19 -> 9695.6892 | CY19: =AY19 -> 3500 | CZ19: =AJ19 -> 0.29050597 | DA19: =CY19*CZ19 -> 1016.7709 | DB19: =CQ19 -> 2500 | DC19: =BJ19 -> 0.18004597 | DD19: =DB19*DC19 -> 450.11492 | DE19: =IF(CX19-CY19-DB19>0,CX19-CY19-DB19,0) -> 3695.6892 | DF19: =BR19+BV19 -> 0.34440853 | DG19: =DE19*DF19 -> 1272.8269 | DH19: =DA19+DD19+DG19 -> 2739.7127 | DJ19: =DH19-CT19 -> 1657.0395 | DK19: =CB19 -> 0 | DL19: =CC19 -> 43.211032 | DN19: =ROUND(SUM(DI19:DM19),0) -> 1700
A20: 9 | B20: =Jaargegevens!A22 -> 2033 | C20: =IF(A20>Calculator!$R$96,"Nee",IF(H19<K20,"Ja","Nee")) -> Ja | D20: =Jaargegevens!D22 -> 0.025 | F20: =Cycli!Q18 -> 1.5 | G20: =F20*365 -> 547.5 | H20: =SUM(G$12:G20) -> 4426.5 | I20: =Calculator!$R$94 -> 0.96 | K20: =K19 -> 10000 | L20: =Calculator!$R$100 -> 0.7 | M20: =Degradatie!F24 -> 0.02032678 | N20: =SUM(M$10:M20) -> 0.18668921 | P20: =((1-N19)+(1-N20))/2 -> 0.82347418 | Q20: =P20*Calculator!$R$92 -> 17.992911 | R20: =Q20*G20 -> 9851.1187 | S20: =SUM(R$12:R20) -> 87316.074 | U20: =U19*(1+D19) -> 221.16126 | V20: =IF(Calculator!$R$73>0,(Jaargegevens!L22+Jaargegevens!M22)*12,Jaargegevens!L22*12) -> 176.86996 | X20: =X19*(1+$D19) -> 0.070300148 | Y20: =Jaargegevens!F22 -> 0.11046 | Z20: =SUM(X20:Y20) -> 0.18076015 | AA20: =IF(Calculator!$R$25="Dynamisch",Opbrengsten!Z20,AA19*(1+D19)) -> 0.18454712 | AB20: =IF(Calculator!$R$25="Dynamisch",0,AB19*(1+D19)) -> 0.17224398 | AD20: =Jaargegevens!O22+Jaargegevens!P22 -> 0.032303141 | AE20: =Y20 -> 0.11046 | AF20: =SUM(AD20:AE20) -> 0.14276314 | AH20: =Jaargegevens!R22 -> 0.18454712 | AI20: =Y20 -> 0.11046 | AJ20: =SUM(AH20:AI20) -> 0.29500712 | AL20: =(AD20+AH20)/2 -> 0.10842513 | AM20: =AE20 -> 0.11046 | AN20: =SUM(AL20:AM20) -> 0.21888513 | AP20: =Calculator!$R$38 -> 4500 | AQ20: =AW20 -> 0 | AR20: =SUM(AP20:AQ20) -> 4500 | AT20: =MIN(MAX(0,-Jaargegevens!U22),365) -> 0 | AU20: =MAX(0,(Opbrengsten!AT20/365)*Calculator!$R$71) -> 0 | AV20: =Jaargegevens!X22 -> 3.5 | AW20: =AV20*AU20 -> 0 | AY20: =AR20-BB20 -> 3500 | AZ20: =Calculator!$R$34 -> 3500 | BA20: =Calculator!$V$36 -> 0.28571429 | BB20: =Calculator!$R$36 -> 1000 | BC20: =MIN(Calculator!$R$32,R20) -> 2500 | BD20: =AY20+BB20 -> 4500 | BE20: =MIN(BD20-BB20,R20-BC20) -> 3500 | BG20: =BC20 -> 2500 | BH20: =R20 -> 9851.1187 | BI20: =MIN(BG20:BH20) -> 2500 | BJ20: =IF(B20<=Jaargegevens!$M$7,Calculator!$S$49,AH20+Jaargegevens!S22+Jaargegevens!J22) -> 0.18454712 | BL20: =IF(Calculator!$R$118<=B20,Keuzemenu!$I$18,Keuzemenu!$I$17) -> Ja | BM20: =Jaargegevens!AB22 -> 14 | BN20: =IF(Calculator!R$102/4<Q20,Calculator!R$102*(BM20/60),Q20) -> 2.3333333 | BO20: =IF(BL20="Ja",365*24*4*BN20,0) -> 81760 | BP20: =MAX(0,BH20-BE20-BI20) -> 3851.1187 | BQ20: =MAX(0,MIN(BO20:BP20)) -> 3851.1187 | BR20: =AF20 -> 0.14276314 | BS20: =Jaargegevens!R22+Jaargegevens!AD22+Jaargegevens!J22 -> 0.38454712 | BT20: =BS20-BR20 -> 0.24178398 | BU20: =Jaargegevens!AF22 -> 0.85 | BV20: =BT20*BU20 -> 0.20551638 | BX20: =-(((1-I20)*R20)*(BR20+BV20)) -> -137.23772 | BY20: =(BE20*(AJ20-AF20)) -> 532.85391 | BZ20: =BC20*BJ20 -> 461.36779 | CA20: =BQ20*BV20 -> 791.46797 | CB20: =CN20 -> 0 | CC20: =U20-V20 -> 44.291308 | CD20: =ROUND(SUM(BX20:CC20),0) -> 1693 | CE20: =IF(CD20<>"",SUM(CD$12:CD20),"") -> 14481 | CH20: =R20 -> 9851.1187 | CI20: =BC20 -> 2500 | CJ20: =CH20-CI20 -> 7351.1187 | CK20: =Jaargegevens!G22 -> 10000 | CL20: =MAX(CJ20-CK20,0) -> 0 | CM20: =Jaargegevens!F22-Jaargegevens!H22 -> 0.02652 | CN20: =CL20*CM20 -> 0 | CP20: =R20 -> 9851.1187 | CQ20: =BC20 -> 2500 | CR20: =CP20-CQ20 -> 7351.1187 | CS20: =AF20 -> 0.14276314 | CT20: =CR20*CS20 -> 1049.4688 | CV20: =CP20 -> 9851.1187 | CW20: =(1-I20)*CV20 -> 394.04475 | CX20: =CV20-CW20 -> 9457.074 | CY20: =AY20 -> 3500 | CZ20: =AJ20 -> 0.29500712 | DA20: =CY20*CZ20 -> 1032.5249 | DB20: =CQ20 -> 2500 | DC20: =BJ20 -> 0.18454712 | DD20: =DB20*DC20 -> 461.36779 | DE20: =IF(CX20-CY20-DB20>0,CX20-CY20-DB20,0) -> 3457.074 | DF20: =BR20+BV20 -> 0.34827952 | DG20: =DE20*DF20 -> 1204.0281 | DH20: =DA20+DD20+DG20 -> 2697.9208 | DJ20: =DH20-CT20 -> 1648.452 | DK20: =CB20 -> 0 | DL20: =CC20 -> 44.291308 | DN20: =ROUND(SUM(DI20:DM20),0) -> 1693
A21: 10 | B21: =Jaargegevens!A23 -> 2034 | C21: =IF(A21>Calculator!$R$96,"Nee",IF(H20<K21,"Ja","Nee")) -> Ja | D21: =Jaargegevens!D23 -> 0.025 | F21: =Cycli!Q19 -> 1.5 | G21: =F21*365 -> 547.5 | H21: =SUM(G$12:G21) -> 4974 | I21: =Calculator!$R$94 -> 0.96 | K21: =K20 -> 10000 | L21: =Calculator!$R$100 -> 0.7 | M21: =Degradatie!F25 -> 0.019355644 | N21: =SUM(M$10:M21) -> 0.20604485 | P21: =((1-N20)+(1-N21))/2 -> 0.80363297 | Q21: =P21*Calculator!$R$92 -> 17.55938 | R21: =Q21*G21 -> 9613.7608 | S21: =SUM(R$12:R21) -> 96929.835 | U21: =U20*(1+D20) -> 226.6903 | V21: =IF(Calculator!$R$73>0,(Jaargegevens!L23+Jaargegevens!M23)*12,Jaargegevens!L23*12) -> 181.29171 | X21: =X20*(1+$D20) -> 0.072057652 | Y21: =Jaargegevens!F23 -> 0.11046 | Z21: =SUM(X21:Y21) -> 0.18251765 | AA21: =IF(Calculator!$R$25="Dynamisch",Opbrengsten!Z21,AA20*(1+D20)) -> 0.18916079 | AB21: =IF(Calculator!$R$25="Dynamisch",0,AB20*(1+D20)) -> 0.17655007 | AD21: =Jaargegevens!O23+Jaargegevens!P23 -> 0.03261072 | AE21: =Y21 -> 0.11046 | AF21: =SUM(AD21:AE21) -> 0.14307072 | AH21: =Jaargegevens!R23 -> 0.18916079 | AI21: =Y21 -> 0.11046 | AJ21: =SUM(AH21:AI21) -> 0.29962079 | AL21: =(AD21+AH21)/2 -> 0.11088576 | AM21: =AE21 -> 0.11046 | AN21: =SUM(AL21:AM21) -> 0.22134576 | AP21: =Calculator!$R$38 -> 4500 | AQ21: =AW21 -> 0 | AR21: =SUM(AP21:AQ21) -> 4500 | AT21: =MIN(MAX(0,-Jaargegevens!U23),365) -> 0 | AU21: =MAX(0,(Opbrengsten!AT21/365)*Calculator!$R$71) -> 0 | AV21: =Jaargegevens!X23 -> 3.5 | AW21: =AV21*AU21 -> 0 | AY21: =AR21-BB21 -> 3500 | AZ21: =Calculator!$R$34 -> 3500 | BA21: =Calculator!$V$36 -> 0.28571429 | BB21: =Calculator!$R$36 -> 1000 | BC21: =MIN(Calculator!$R$32,R21) -> 2500 | BD21: =AY21+BB21 -> 4500 | BE21: =MIN(BD21-BB21,R21-BC21) -> 3500 | BG21: =BC21 -> 2500 | BH21: =R21 -> 9613.7608 | BI21: =MIN(BG21:BH21) -> 2500 | BJ21: =IF(B21<=Jaargegevens!$M$7,Calculator!$S$49,AH21+Jaargegevens!S23+Jaargegevens!J23) -> 0.18916079 | BL21: =IF(Calculator!$R$118<=B21,Keuzemenu!$I$18,Keuzemenu!$I$17) -> Ja | BM21: =Jaargegevens!AB23 -> 14 | BN21: =IF(Calculator!R$102/4<Q21,Calculator!R$102*(BM21/60),Q21) -> 2.3333333 | BO21: =IF(BL21="Ja",365*24*4*BN21,0) -> 81760 | BP21: =MAX(0,BH21-BE21-BI21) -> 3613.7608 | BQ21: =MAX(0,MIN(BO21:BP21)) -> 3613.7608 | BR21: =AF21 -> 0.14307072 | BS21: =Jaargegevens!R23+Jaargegevens!AD23+Jaargegevens!J23 -> 0.38916079 | BT21: =BS21-BR21 -> 0.24609007 | BU21: =Jaargegevens!AF23 -> 0.85 | BV21: =BT21*BU21 -> 0.20917656 | BX21: =-(((1-I21)*R21)*(BR21+BV21)) -> -135.45684 | BY21: =(BE21*(AJ21-AF21)) -> 547.92526 | BZ21: =BC21*BJ21 -> 472.90199 | CA21: =BQ21*BV21 -> 755.91406 | CB21: =CN21 -> 0 | CC21: =U21-V21 -> 45.398591 | CD21: =ROUND(SUM(BX21:CC21),0) -> 1687 | CE21: =IF(CD21<>"",SUM(CD$12:CD21),"") -> 16168 | CH21: =R21 -> 9613.7608 | CI21: =BC21 -> 2500 | CJ21: =CH21-CI21 -> 7113.7608 | CK21: =Jaargegevens!G23 -> 10000 | CL21: =MAX(CJ21-CK21,0) -> 0 | CM21: =Jaargegevens!F23-Jaargegevens!H23 -> 0.02652 | CN21: =CL21*CM21 -> 0 | CP21: =R21 -> 9613.7608 | CQ21: =BC21 -> 2500 | CR21: =CP21-CQ21 -> 7113.7608 | CS21: =AF21 -> 0.14307072 | CT21: =CR21*CS21 -> 1017.7709 | CV21: =CP21 -> 9613.7608 | CW21: =(1-I21)*CV21 -> 384.55043 | CX21: =CV21-CW21 -> 9229.2103 | CY21: =AY21 -> 3500 | CZ21: =AJ21 -> 0.29962079 | DA21: =CY21*CZ21 -> 1048.6728 | DB21: =CQ21 -> 2500 | DC21: =BJ21 -> 0.18916079 | DD21: =DB21*DC21 -> 472.90199 | DE21: =IF(CX21-CY21-DB21>0,CX21-CY21-DB21,0) -> 3229.2103 | DF21: =BR21+BV21 -> 0.35224728 | DG21: =DE21*DF21 -> 1137.4806 | DH21: =DA21+DD21+DG21 -> 2659.0553 | DJ21: =DH21-CT21 -> 1641.2845 | DK21: =CB21 -> 0 | DL21: =CC21 -> 45.398591 | DN21: =ROUND(SUM(DI21:DM21),0) -> 1687
A22: 11 | B22: =Jaargegevens!A24 -> 2035 | C22: =IF(A22>Calculator!$R$96,"Nee",IF(H21<K22,"Ja","Nee")) -> Nee | D22: =Jaargegevens!D24 -> 0.025 | F22: =Cycli!Q20 -> 1.5 | G22: =F22*365 -> 547.5 | H22: =SUM(G$12:G22) -> 5521.5 | I22: =Calculator!$R$94 -> 0.96 | K22: =K21 -> 10000 | L22: =Calculator!$R$100 -> 0.7 | M22: =Degradatie!F26 -> 0.018309198 | N22: =SUM(M$10:M22) -> 0.22435405 | P22: =((1-N21)+(1-N22))/2 -> 0.78480055 | Q22: =P22*Calculator!$R$92 -> 17.147892 | R22: =Q22*G22 -> 9388.4709 | S22: =SUM(R$12:R22) -> 106318.31 | U22: =U21*(1+D21) -> 232.35755 | V22: =IF(Calculator!$R$73>0,(Jaargegevens!L24+Jaargegevens!M24)*12,Jaargegevens!L24*12) -> 185.824 | X22: =X21*(1+$D21) -> 0.073859093 | Y22: =Jaargegevens!F24 -> 0.11046 | Z22: =SUM(X22:Y22) -> 0.18431909 | AA22: =IF(Calculator!$R$25="Dynamisch",Opbrengsten!Z22,AA21*(1+D21)) -> 0.19388981 | AB22: =IF(Calculator!$R$25="Dynamisch",0,AB21*(1+D21)) -> 0.18096383 | AD22: =Jaargegevens!O24+Jaargegevens!P24 -> 0.032925988 | AE22: =Y22 -> 0.11046 | AF22: =SUM(AD22:AE22) -> 0.14338599 | AH22: =Jaargegevens!R24 -> 0.19388981 | AI22: =Y22 -> 0.11046 | AJ22: =SUM(AH22:AI22) -> 0.30434981 | AL22: =(AD22+AH22)/2 -> 0.1134079 | AM22: =AE22 -> 0.11046 | AN22: =SUM(AL22:AM22) -> 0.2238679 | AP22: =Calculator!$R$38 -> 4500 | AQ22: =AW22 -> 0 | AR22: =SUM(AP22:AQ22) -> 4500 | AT22: =MIN(MAX(0,-Jaargegevens!U24),365) -> 0 | AU22: =MAX(0,(Opbrengsten!AT22/365)*Calculator!$R$71) -> 0 | AV22: =Jaargegevens!X24 -> 3.5 | AW22: =AV22*AU22 -> 0 | AY22: =AR22-BB22 -> 3500 | AZ22: =Calculator!$R$34 -> 3500 | BA22: =Calculator!$V$36 -> 0.28571429 | BB22: =Calculator!$R$36 -> 1000 | BC22: =MIN(Calculator!$R$32,R22) -> 2500 | BD22: =AY22+BB22 -> 4500 | BE22: =MIN(BD22-BB22,R22-BC22) -> 3500 | BG22: =BC22 -> 2500 | BH22: =R22 -> 9388.4709 | BI22: =MIN(BG22:BH22) -> 2500 | BJ22: =IF(B22<=Jaargegevens!$M$7,Calculator!$S$49,AH22+Jaargegevens!S24+Jaargegevens!J24) -> 0.19388981 | BL22: =IF(Calculator!$R$118<=B22,Keuzemenu!$I$18,Keuzemenu!$I$17) -> Ja | BM22: =Jaargegevens!AB24 -> 14 | BN22: =IF(Calculator!R$102/4<Q22,Calculator!R$102*(BM22/60),Q22) -> 2.3333333 | BO22: =IF(BL22="Ja",365*24*4*BN22,0) -> 81760 | BP22: =MAX(0,BH22-BE22-BI22) -> 3388.4709 | BQ22: =MAX(0,MIN(BO22:BP22)) -> 3388.4709 | BR22: =AF22 -> 0.14338599 | BS22: =Jaargegevens!R24+Jaargegevens!AD24+Jaargegevens!J24 -> 0.39388981 | BT22: =BS22-BR22 -> 0.25050383 | BU22: =Jaargegevens!AF24 -> 0.85 | BV22: =BT22*BU22 -> 0.21292825 | BX22: =-(((1-I22)*R22)*(BR22+BV22)) -> -133.80983 | BY22: =(BE22*(AJ22-AF22)) -> 563.37339 | BZ22: =BC22*BJ22 -> 484.72454 | CA22: =BQ22*BV22 -> 721.50118 | CB22: =CN22 -> 0 | CC22: =U22-V22 -> 46.533555 | CD22: =ROUND(SUM(BX22:CC22),0) -> 1682 | CE22: =IF(CD22<>"",SUM(CD$12:CD22),"") -> 17850 | CH22: =R22 -> 9388.4709 | CI22: =BC22 -> 2500 | CJ22: =CH22-CI22 -> 6888.4709 | CK22: =Jaargegevens!G24 -> 10000 | CL22: =MAX(CJ22-CK22,0) -> 0 | CM22: =Jaargegevens!F24-Jaargegevens!H24 -> 0.02652 | CN22: =CL22*CM22 -> 0 | CP22: =R22 -> 9388.4709 | CQ22: =BC22 -> 2500 | CR22: =CP22-CQ22 -> 6888.4709 | CS22: =AF22 -> 0.14338599 | CT22: =CR22*CS22 -> 987.7102 | CV22: =CP22 -> 9388.4709 | CW22: =(1-I22)*CV22 -> 375.53884 | CX22: =CV22-CW22 -> 9012.932 | CY22: =AY22 -> 3500 | CZ22: =AJ22 -> 0.30434981 | DA22: =CY22*CZ22 -> 1065.2243 | DB22: =CQ22 -> 2500 | DC22: =BJ22 -> 0.19388981 | DD22: =DB22*DC22 -> 484.72454 | DE22: =IF(CX22-CY22-DB22>0,CX22-CY22-DB22,0) -> 3012.932 | DF22: =BR22+BV22 -> 0.35631424 | DG22: =DE22*DF22 -> 1073.5506 | DH22: =DA22+DD22+DG22 -> 2623.4995 | DJ22: =DH22-CT22 -> 1635.7893 | DK22: =CB22 -> 0 | DL22: =CC22 -> 46.533555 | DN22: =ROUND(SUM(DI22:DM22),0) -> 1682
A23: 12 | B23: =Jaargegevens!A25 -> 2036 | C23: =IF(A23>Calculator!$R$96,"Nee",IF(H22<K23,"Ja","Nee")) -> Nee | D23: =Jaargegevens!D25 -> 0.025 | F23: =Cycli!Q21 -> 1.5 | G23: =F23*365 -> 547.5 | H23: =SUM(G$12:G23) -> 6069 | I23: =Calculator!$R$94 -> 0.96 | K23: =K22 -> 10000 | L23: =Calculator!$R$100 -> 0.7 | M23: =Degradatie!F27 -> 0.017181604 | N23: =SUM(M$10:M23) -> 0.24153565 | P23: =((1-N22)+(1-N23))/2 -> 0.76705515 | Q23: =P23*Calculator!$R$92 -> 16.760155 | R23: =Q23*G23 -> 9176.1849 | S23: =SUM(R$12:R23) -> 115494.49 | U23: =U22*(1+D22) -> 238.16649 | V23: =IF(Calculator!$R$73>0,(Jaargegevens!L25+Jaargegevens!M25)*12,Jaargegevens!L25*12) -> 190.4696 | X23: =X22*(1+$D22) -> 0.07570557 | Y23: =Jaargegevens!F25 -> 0.11046 | Z23: =SUM(X23:Y23) -> 0.18616557 | AA23: =IF(Calculator!$R$25="Dynamisch",Opbrengsten!Z23,AA22*(1+D22)) -> 0.19873706 | AB23: =IF(Calculator!$R$25="Dynamisch",0,AB22*(1+D22)) -> 0.18548792 | AD23: =Jaargegevens!O25+Jaargegevens!P25 -> 0.033249137 | AE23: =Y23 -> 0.11046 | AF23: =SUM(AD23:AE23) -> 0.14370914 | AH23: =Jaargegevens!R25 -> 0.19873706 | AI23: =Y23 -> 0.11046 | AJ23: =SUM(AH23:AI23) -> 0.30919706 | AL23: =(AD23+AH23)/2 -> 0.1159931 | AM23: =AE23 -> 0.11046 | AN23: =SUM(AL23:AM23) -> 0.2264531 | AP23: =Calculator!$R$38 -> 4500 | AQ23: =AW23 -> 0 | AR23: =SUM(AP23:AQ23) -> 4500 | AT23: =MIN(MAX(0,-Jaargegevens!U25),365) -> 0 | AU23: =MAX(0,(Opbrengsten!AT23/365)*Calculator!$R$71) -> 0 | AV23: =Jaargegevens!X25 -> 3.5 | AW23: =AV23*AU23 -> 0 | AY23: =AR23-BB23 -> 3500 | AZ23: =Calculator!$R$34 -> 3500 | BA23: =Calculator!$V$36 -> 0.28571429 | BB23: =Calculator!$R$36 -> 1000 | BC23: =MIN(Calculator!$R$32,R23) -> 2500 | BD23: =AY23+BB23 -> 4500 | BE23: =MIN(BD23-BB23,R23-BC23) -> 3500 | BG23: =BC23 -> 2500 | BH23: =R23 -> 9176.1849 | BI23: =MIN(BG23:BH23) -> 2500 | BJ23: =IF(B23<=Jaargegevens!$M$7,Calculator!$S$49,AH23+Jaargegevens!S25+Jaargegevens!J25) -> 0.19873706 | BL23: =IF(Calculator!$R$118<=B23,Keuzemenu!$I$18,Keuzemenu!$I$17) -> Ja | BM23: =Jaargegevens!AB25 -> 14 | BN23: =IF(Calculator!R$102/4<Q23,Calculator!R$102*(BM23/60),Q23) -> 2.3333333 | BO23: =IF(BL23="Ja",365*24*4*BN23,0) -> 81760 | BP23: =MAX(0,BH23-BE23-BI23) -> 3176.1849 | BQ23: =MAX(0,MIN(BO23:BP23)) -> 3176.1849 | BR23: =AF23 -> 0.14370914 | BS23: =Jaargegevens!R25+Jaargegevens!AD25+Jaargegevens!J25 -> 0.39873706 | BT23: =BS23-BR23 -> 0.25502792 | BU23: =Jaargegevens!AF25 -> 0.85 | BV23: =BT23*BU23 -> 0.21677373 | BX23: =-(((1-I23)*R23)*(BR23+BV23)) -> -132.3143 | BY23: =(BE23*(AJ23-AF23)) -> 579.20773 | BZ23: =BC23*BJ23 -> 496.84265 | CA23: =BQ23*BV23 -> 688.51345 | CB23: =CN23 -> 0 | CC23: =U23-V23 -> 47.696894 | CD23: =ROUND(SUM(BX23:CC23),0) -> 1680 | CE23: =IF(CD23<>"",SUM(CD$12:CD23),"") -> 19530 | CH23: =R23 -> 9176.1849 | CI23: =BC23 -> 2500 | CJ23: =CH23-CI23 -> 6676.1849 | CK23: =Jaargegevens!G25 -> 10000 | CL23: =MAX(CJ23-CK23,0) -> 0 | CM23: =Jaargegevens!F25-Jaargegevens!H25 -> 0.02652 | CN23: =CL23*CM23 -> 0 | CP23: =R23 -> 9176.1849 | CQ23: =BC23 -> 2500 | CR23: =CP23-CQ23 -> 6676.1849 | CS23: =AF23 -> 0.14370914 | CT23: =CR23*CS23 -> 959.42877 | CV23: =CP23 -> 9176.1849 | CW23: =(1-I23)*CV23 -> 367.04739 | CX23: =CV23-CW23 -> 8809.1375 | CY23: =AY23 -> 3500 | CZ23: =AJ23 -> 0.30919706 | DA23: =CY23*CZ23 -> 1082.1897 | DB23: =CQ23 -> 2500 | DC23: =BJ23 -> 0.19873706 | DD23: =DB23*DC23 -> 496.84265 | DE23: =IF(CX23-CY23-DB23>0,CX23-CY23-DB23,0) -> 2809.1375 | DF23: =BR23+BV23 -> 0.36048287 | DG23: =DE23*DF23 -> 1012.6459 | DH23: =DA23+DD23+DG23 -> 2591.6783 | DJ23: =DH23-CT23 -> 1632.2495 | DK23: =CB23 -> 0 | DL23: =CC23 -> 47.696894 | DN23: =ROUND(SUM(DI23:DM23),0) -> 1680
A24: 13 | B24: =Jaargegevens!A26 -> 2037 | C24: =IF(A24>Calculator!$R$96,"Nee",IF(H23<K24,"Ja","Nee")) -> Nee | D24: =Jaargegevens!D26 -> 0.025 | F24: =Cycli!Q22 -> 1.5 | G24: =F24*365 -> 547.5 | H24: =SUM(G$12:G24) -> 6616.5 | I24: =Calculator!$R$94 -> 0.96 | K24: =K23 -> 10000 | L24: =Calculator!$R$100 -> 0.7 | M24: =Degradatie!F28 -> 0.015966569 | N24: =SUM(M$10:M24) -> 0.25750222 | P24: =((1-N23)+(1-N24))/2 -> 0.75048106 | Q24: =P24*Calculator!$R$92 -> 16.398011 | R24: =Q24*G24 -> 8977.9111 | S24: =SUM(R$12:R24) -> 124472.4 | U24: =U23*(1+D23) -> 244.12065 | V24: =IF(Calculator!$R$73>0,(Jaargegevens!L26+Jaargegevens!M26)*12,Jaargegevens!L26*12) -> 195.23134 | X24: =X23*(1+$D23) -> 0.07759821 | Y24: =Jaargegevens!F26 -> 0.11046 | Z24: =SUM(X24:Y24) -> 0.18805821 | AA24: =IF(Calculator!$R$25="Dynamisch",Opbrengsten!Z24,AA23*(1+D23)) -> 0.20370549 | AB24: =IF(Calculator!$R$25="Dynamisch",0,AB23*(1+D23)) -> 0.19012512 | AD24: =Jaargegevens!O26+Jaargegevens!P26 -> 0.033580366 | AE24: =Y24 -> 0.11046 | AF24: =SUM(AD24:AE24) -> 0.14404037 | AH24: =Jaargegevens!R26 -> 0.20370549 | AI24: =Y24 -> 0.11046 | AJ24: =SUM(AH24:AI24) -> 0.31416549 | AL24: =(AD24+AH24)/2 -> 0.11864293 | AM24: =AE24 -> 0.11046 | AN24: =SUM(AL24:AM24) -> 0.22910293 | AP24: =Calculator!$R$38 -> 4500 | AQ24: =AW24 -> 0 | AR24: =SUM(AP24:AQ24) -> 4500 | AT24: =MIN(MAX(0,-Jaargegevens!U26),365) -> 0 | AU24: =MAX(0,(Opbrengsten!AT24/365)*Calculator!$R$71) -> 0 | AV24: =Jaargegevens!X26 -> 3.5 | AW24: =AV24*AU24 -> 0 | AY24: =AR24-BB24 -> 3500 | AZ24: =Calculator!$R$34 -> 3500 | BA24: =Calculator!$V$36 -> 0.28571429 | BB24: =Calculator!$R$36 -> 1000 | BC24: =MIN(Calculator!$R$32,R24) -> 2500 | BD24: =AY24+BB24 -> 4500 | BE24: =MIN(BD24-BB24,R24-BC24) -> 3500 | BG24: =BC24 -> 2500 | BH24: =R24 -> 8977.9111 | BI24: =MIN(BG24:BH24) -> 2500 | BJ24: =IF(B24<=Jaargegevens!$M$7,Calculator!$S$49,AH24+Jaargegevens!S26+Jaargegevens!J26) -> 0.20370549 | BL24: =IF(Calculator!$R$118<=B24,Keuzemenu!$I$18,Keuzemenu!$I$17) -> Ja | BM24: =Jaargegevens!AB26 -> 14 | BN24: =IF(Calculator!R$102/4<Q24,Calculator!R$102*(BM24/60),Q24) -> 2.3333333 | BO24: =IF(BL24="Ja",365*24*4*BN24,0) -> 81760 | BP24: =MAX(0,BH24-BE24-BI24) -> 2977.9111 | BQ24: =MAX(0,MIN(BO24:BP24)) -> 2977.9111 | BR24: =AF24 -> 0.14404037 | BS24: =Jaargegevens!R26+Jaargegevens!AD26+Jaargegevens!J26 -> 0.40370549 | BT24: =BS24-BR24 -> 0.25966512 | BU24: =Jaargegevens!AF26 -> 0.85 | BV24: =BT24*BU24 -> 0.22071535 | BX24: =-(((1-I24)*R24)*(BR24+BV24)) -> -130.98978 | BY24: =(BE24*(AJ24-AF24)) -> 595.43792 | BZ24: =BC24*BJ24 -> 509.26371 | CA24: =BQ24*BV24 -> 657.27071 | CB24: =CN24 -> 0 | CC24: =U24-V24 -> 48.889317 | CD24: =ROUND(SUM(BX24:CC24),0) -> 1680 | CE24: =IF(CD24<>"",SUM(CD$12:CD24),"") -> 21210 | CH24: =R24 -> 8977.9111 | CI24: =BC24 -> 2500 | CJ24: =CH24-CI24 -> 6477.9111 | CK24: =Jaargegevens!G26 -> 10000 | CL24: =MAX(CJ24-CK24,0) -> 0 | CM24: =Jaargegevens!F26-Jaargegevens!H26 -> 0.02652 | CN24: =CL24*CM24 -> 0 | CP24: =R24 -> 8977.9111 | CQ24: =BC24 -> 2500 | CR24: =CP24-CQ24 -> 6477.9111 | CS24: =AF24 -> 0.14404037 | CT24: =CR24*CS24 -> 933.08069 | CV24: =CP24 -> 8977.9111 | CW24: =(1-I24)*CV24 -> 359.11645 | CX24: =CV24-CW24 -> 8618.7947 | CY24: =AY24 -> 3500 | CZ24: =AJ24 -> 0.31416549 | DA24: =CY24*CZ24 -> 1099.5792 | DB24: =CQ24 -> 2500 | DC24: =BJ24 -> 0.20370549 | DD24: =DB24*DC24 -> 509.26371 | DE24: =IF(CX24-CY24-DB24>0,CX24-CY24-DB24,0) -> 2618.7947 | DF24: =BR24+BV24 -> 0.36475572 | DG24: =DE24*DF24 -> 955.22034 | DH24: =DA24+DD24+DG24 -> 2564.0633 | DJ24: =DH24-CT24 -> 1630.9826 | DK24: =CB24 -> 0 | DL24: =CC24 -> 48.889317 | DN24: =ROUND(SUM(DI24:DM24),0) -> 1680
A25: 14 | B25: =Jaargegevens!A27 -> 2038 | C25: =IF(A25>Calculator!$R$96,"Nee",IF(H24<K25,"Ja","Nee")) -> Nee | D25: =Jaargegevens!D27 -> 0.025 | F25: =Cycli!Q23 -> 1.5 | G25: =F25*365 -> 547.5 | H25: =SUM(G$12:G25) -> 7164 | I25: =Calculator!$R$94 -> 0.96 | K25: =K24 -> 10000 | L25: =Calculator!$R$100 -> 0.7 | M25: =Degradatie!F29 -> 0.014657311 | N25: =SUM(M$10:M25) -> 0.27215953 | P25: =((1-N24)+(1-N25))/2 -> 0.73516912 | Q25: =P25*Calculator!$R$92 -> 16.063445 | R25: =Q25*G25 -> 8794.7363 | S25: =SUM(R$12:R25) -> 133267.14 | U25: =U24*(1+D24) -> 250.22367 | V25: =IF(Calculator!$R$73>0,(Jaargegevens!L27+Jaargegevens!M27)*12,Jaargegevens!L27*12) -> 200.11212 | X25: =X24*(1+$D24) -> 0.079538165 | Y25: =Jaargegevens!F27 -> 0.11046 | Z25: =SUM(X25:Y25) -> 0.18999817 | AA25: =IF(Calculator!$R$25="Dynamisch",Opbrengsten!Z25,AA24*(1+D24)) -> 0.20879812 | AB25: =IF(Calculator!$R$25="Dynamisch",0,AB24*(1+D24)) -> 0.19487825 | AD25: =Jaargegevens!O27+Jaargegevens!P27 -> 0.033919875 | AE25: =Y25 -> 0.11046 | AF25: =SUM(AD25:AE25) -> 0.14437987 | AH25: =Jaargegevens!R27 -> 0.20879812 | AI25: =Y25 -> 0.11046 | AJ25: =SUM(AH25:AI25) -> 0.31925812 | AL25: =(AD25+AH25)/2 -> 0.121359 | AM25: =AE25 -> 0.11046 | AN25: =SUM(AL25:AM25) -> 0.231819 | AP25: =Calculator!$R$38 -> 4500 | AQ25: =AW25 -> 0 | AR25: =SUM(AP25:AQ25) -> 4500 | AT25: =MIN(MAX(0,-Jaargegevens!U27),365) -> 0 | AU25: =MAX(0,(Opbrengsten!AT25/365)*Calculator!$R$71) -> 0 | AV25: =Jaargegevens!X27 -> 3.5 | AW25: =AV25*AU25 -> 0 | AY25: =AR25-BB25 -> 3500 | AZ25: =Calculator!$R$34 -> 3500 | BA25: =Calculator!$V$36 -> 0.28571429 | BB25: =Calculator!$R$36 -> 1000 | BC25: =MIN(Calculator!$R$32,R25) -> 2500 | BD25: =AY25+BB25 -> 4500 | BE25: =MIN(BD25-BB25,R25-BC25) -> 3500 | BG25: =BC25 -> 2500 | BH25: =R25 -> 8794.7363 | BI25: =MIN(BG25:BH25) -> 2500 | BJ25: =IF(B25<=Jaargegevens!$M$7,Calculator!$S$49,AH25+Jaargegevens!S27+Jaargegevens!J27) -> 0.20879812 | BL25: =IF(Calculator!$R$118<=B25,Keuzemenu!$I$18,Keuzemenu!$I$17) -> Ja | BM25: =Jaargegevens!AB27 -> 14 | BN25: =IF(Calculator!R$102/4<Q25,Calculator!R$102*(BM25/60),Q25) -> 2.3333333 | BO25: =IF(BL25="Ja",365*24*4*BN25,0) -> 81760 | BP25: =MAX(0,BH25-BE25-BI25) -> 2794.7363 | BQ25: =MAX(0,MIN(BO25:BP25)) -> 2794.7363 | BR25: =AF25 -> 0.14437987 | BS25: =Jaargegevens!R27+Jaargegevens!AD27+Jaargegevens!J27 -> 0.40879812 | BT25: =BS25-BR25 -> 0.26441825 | BU25: =Jaargegevens!AF27 -> 0.85 | BV25: =BT25*BU25 -> 0.22475551 | BX25: =-(((1-I25)*R25)*(BR25+BV25)) -> -129.85794 | BY25: =(BE25*(AJ25-AF25)) -> 612.07387 | BZ25: =BC25*BJ25 -> 521.99531 | CA25: =BQ25*BV25 -> 628.13239 | CB25: =CN25 -> 0 | CC25: =U25-V25 -> 50.11155 | CD25: =ROUND(SUM(BX25:CC25),0) -> 1682 | CE25: =IF(CD25<>"",SUM(CD$12:CD25),"") -> 22892 | CH25: =R25 -> 8794.7363 | CI25: =BC25 -> 2500 | CJ25: =CH25-CI25 -> 6294.7363 | CK25: =Jaargegevens!G27 -> 10000 | CL25: =MAX(CJ25-CK25,0) -> 0 | CM25: =Jaargegevens!F27-Jaargegevens!H27 -> 0.02652 | CN25: =CL25*CM25 -> 0 | CP25: =R25 -> 8794.7363 | CQ25: =BC25 -> 2500 | CR25: =CP25-CQ25 -> 6294.7363 | CS25: =AF25 -> 0.14437987 | CT25: =CR25*CS25 -> 908.83324 | CV25: =CP25 -> 8794.7363 | CW25: =(1-I25)*CV25 -> 351.78945 | CX25: =CV25-CW25 -> 8442.9469 | CY25: =AY25 -> 3500 | CZ25: =AJ25 -> 0.31925812 | DA25: =CY25*CZ25 -> 1117.4034 | DB25: =CQ25 -> 2500 | DC25: =BJ25 -> 0.20879812 | DD25: =DB25*DC25 -> 521.99531 | DE25: =IF(CX25-CY25-DB25>0,CX25-CY25-DB25,0) -> 2442.9469 | DF25: =BR25+BV25 -> 0.36913539 | DG25: =DE25*DF25 -> 901.77813 | DH25: =DA25+DD25+DG25 -> 2541.1769 | DJ25: =DH25-CT25 -> 1632.3436 | DK25: =CB25 -> 0 | DL25: =CC25 -> 50.11155 | DN25: =ROUND(SUM(DI25:DM25),0) -> 1682
... A31: 20 | B31: =Jaargegevens!A33 -> 2044 | C31: =IF(A31>Calculator!$R$96,"Nee",IF(H30<K31,"Ja","Nee")) -> Nee | D31: =Jaargegevens!D33 -> 0.025 | F31: =Cycli!Q29 -> 1.5 | G31: =F31*365 -> 547.5 | H31: =SUM(G$12:G31) -> 10449 | I31: =Calculator!$R$94 -> 0.96 | K31: =K30 -> 10000 | L31: =Calculator!$R$100 -> 0.7 | M31: =Degradatie!F35 -> 0.0043717056 | N31: =SUM(M$10:M31) -> 0.3263367 | P31: =((1-N30)+(1-N31))/2 -> 0.67584916 | Q31: =P31*Calculator!$R$92 -> 14.767304 | R31: =Q31*G31 -> 8085.099 | S31: =SUM(R$12:R31) -> 183194.01 | U31: =U30*(1+D30) -> 290.18274 | V31: =IF(Calculator!$R$73>0,(Jaargegevens!L33+Jaargegevens!M33)*12,Jaargegevens!L33*12) -> 232.06871 | X31: =X30*(1+$D30) -> 0.092239886 | Y31: =Jaargegevens!F33 -> 0.11046 | Z31: =SUM(X31:Y31) -> 0.20269989 | AA31: =IF(Calculator!$R$25="Dynamisch",Opbrengsten!Z31,AA30*(1+D30)) -> 0.24214181 | AB31: =IF(Calculator!$R$25="Dynamisch",0,AB30*(1+D30)) -> 0.22599902 | AD31: =Jaargegevens!O33+Jaargegevens!P33 -> 0.036142787 | AE31: =Y31 -> 0.11046 | AF31: =SUM(AD31:AE31) -> 0.14660279 | AH31: =Jaargegevens!R33 -> 0.24214181 | AI31: =Y31 -> 0.11046 | AJ31: =SUM(AH31:AI31) -> 0.35260181 | AL31: =(AD31+AH31)/2 -> 0.1391423 | AM31: =AE31 -> 0.11046 | AN31: =SUM(AL31:AM31) -> 0.2496023 | AP31: =Calculator!$R$38 -> 4500 | AQ31: =AW31 -> 0 | AR31: =SUM(AP31:AQ31) -> 4500 | AT31: =MIN(MAX(0,-Jaargegevens!U33),365) -> 0 | AU31: =MAX(0,(Opbrengsten!AT31/365)*Calculator!$R$71) -> 0 | AV31: =Jaargegevens!X33 -> 3.5 | AW31: =AV31*AU31 -> 0 | AY31: =AR31-BB31 -> 3500 | AZ31: =Calculator!$R$34 -> 3500 | BA31: =Calculator!$V$36 -> 0.28571429 | BB31: =Calculator!$R$36 -> 1000 | BC31: =MIN(Calculator!$R$32,R31) -> 2500 | BD31: =AY31+BB31 -> 4500 | BE31: =MIN(BD31-BB31,R31-BC31) -> 3500 | BG31: =BC31 -> 2500 | BH31: =R31 -> 8085.099 | BI31: =MIN(BG31:BH31) -> 2500 | BJ31: =IF(B31<=Jaargegevens!$M$7,Calculator!$S$49,AH31+Jaargegevens!S33+Jaargegevens!J33) -> 0.24214181 | BL31: =IF(Calculator!$R$118<=B31,Keuzemenu!$I$18,Keuzemenu!$I$17) -> Ja | BM31: =Jaargegevens!AB33 -> 14 | BN31: =IF(Calculator!R$102/4<Q31,Calculator!R$102*(BM31/60),Q31) -> 2.3333333 | BO31: =IF(BL31="Ja",365*24*4*BN31,0) -> 81760 | BP31: =MAX(0,BH31-BE31-BI31) -> 2085.099 | BQ31: =MAX(0,MIN(BO31:BP31)) -> 2085.099 | BR31: =AF31 -> 0.14660279 | BS31: =Jaargegevens!R33+Jaargegevens!AD33+Jaargegevens!J33 -> 0.44214181 | BT31: =BS31-BR31 -> 0.29553902 | BU31: =Jaargegevens!AF33 -> 0.85 | BV31: =BT31*BU31 -> 0.25120817 | BX31: =-(((1-I31)*R31)*(BR31+BV31)) -> -128.65364 | BY31: =(BE31*(AJ31-AF31)) -> 720.99658 | BZ31: =BC31*BJ31 -> 605.35452 | CA31: =BQ31*BV31 -> 523.79389 | CB31: =CN31 -> 0 | CC31: =U31-V31 -> 58.114034 | CD31: =ROUND(SUM(BX31:CC31),0) -> 1780 | CE31: =IF(CD31<>"",SUM(CD$12:CD31),"") -> 33246 | CH31: =R31 -> 8085.099 | CI31: =BC31 -> 2500 | CJ31: =CH31-CI31 -> 5585.099 | CK31: =Jaargegevens!G33 -> 10000 | CL31: =MAX(CJ31-CK31,0) -> 0 | CM31: =Jaargegevens!F33-Jaargegevens!H33 -> 0.02652 | CN31: =CL31*CM31 -> 0 | CP31: =R31 -> 8085.099 | CQ31: =BC31 -> 2500 | CR31: =CP31-CQ31 -> 5585.099 | CS31: =AF31 -> 0.14660279 | CT31: =CR31*CS31 -> 818.79107 | CV31: =CP31 -> 8085.099 | CW31: =(1-I31)*CV31 -> 323.40396 | CX31: =CV31-CW31 -> 7761.695 | CY31: =AY31 -> 3500 | CZ31: =AJ31 -> 0.35260181 | DA31: =CY31*CZ31 -> 1234.1063 | DB31: =CQ31 -> 2500 | DC31: =BJ31 -> 0.24214181 | DD31: =DB31*DC31 -> 605.35452 | DE31: =IF(CX31-CY31-DB31>0,CX31-CY31-DB31,0) -> 1761.695 | DF31: =BR31+BV31 -> 0.39781096 | DG31: =DE31*DF31 -> 700.82157 | DH31: =DA31+DD31+DG31 -> 2540.2824 | DJ31: =DH31-CT31 -> 1721.4914 | DK31: =CB31 -> 0 | DL31: =CC31 -> 58.114034 | DN31: =ROUND(SUM(DI31:DM31),0) -> 1780
A32: 21 | B32: =Jaargegevens!A34 -> 2045 | C32: =IF(A32>Calculator!$R$96,"Nee",IF(H31<K32,"Ja","Nee")) -> Nee | D32: =Jaargegevens!D34 -> 0.025 | F32: =Cycli!Q30 -> 1.5 | G32: =F32*365*D5 -> 501 | H32: =SUM(G$12:G32) -> 10950 | I32: =Calculator!$R$94 -> 0.96 | K32: =K31 -> 10000 | L32: =Calculator!$R$100 -> 0.7 | M32: =Degradatie!F36 -> 0.0021633023 | N32: =SUM(M$10:M32) -> 0.3285 | P32: =((1-N31)+(1-N32))/2 -> 0.67258165 | Q32: =P32*Calculator!$R$92 -> 14.695909 | R32: =Q32*G32 -> 7362.6504 | S32: =SUM(R$12:R32) -> 190556.66 | U32: =U31*(1+D31)*D5 -> 272.17551 | V32: =IF(Calculator!$R$73>0,(Jaargegevens!L34+Jaargegevens!M34)*12*D5,Jaargegevens!L34*12*D5) -> 217.66773 | X32: =X31*(1+$D31) -> 0.094545884 | Y32: =Jaargegevens!F34 -> 0.11046 | Z32: =SUM(X32:Y32) -> 0.20500588 | AA32: =IF(Calculator!$R$25="Dynamisch",Opbrengsten!Z32,AA31*(1+D31)) -> 0.24819535 | AB32: =IF(Calculator!$R$25="Dynamisch",0,AB31*(1+D31)) -> 0.231649 | AD32: =Jaargegevens!O34+Jaargegevens!P34 -> 0.036546357 | AE32: =Y32 -> 0.11046 | AF32: =SUM(AD32:AE32) -> 0.14700636 | AH32: =Jaargegevens!R34 -> 0.24819535 | AI32: =Y32 -> 0.11046 | AJ32: =SUM(AH32:AI32) -> 0.35865535 | AL32: =(AD32+AH32)/2 -> 0.14237086 | AM32: =AE32 -> 0.11046 | AN32: =SUM(AL32:AM32) -> 0.25283086 | AP32: =Calculator!$R$38*D5 -> 4117.8082 | AQ32: =AW32 -> 0 | AR32: =SUM(AP32:AQ32) -> 4117.8082 | AT32: =MIN(MAX(0,-Jaargegevens!U34),365)*D5 -> 0 | AU32: =MAX(0,(Opbrengsten!AT32/365)*Calculator!$R$71) -> 0 | AV32: =Jaargegevens!X34 -> 3.5 | AW32: =AV32*AU32 -> 0 | AY32: =AR32-BB32 -> 3202.7397 | AZ32: =Calculator!$R$34*D5 -> 3202.7397 | BA32: =Calculator!$V$36 -> 0.28571429 | BB32: =Calculator!$R$36*D5 -> 915.06849 | BC32: =MIN(Calculator!$R$32*D5,R32) -> 2287.6712 | BD32: =AY32+BB32 -> 4117.8082 | BE32: =MIN(BD32-BB32,R32-BC32) -> 3202.7397 | BG32: =BC32 -> 2287.6712 | BH32: =R32 -> 7362.6504 | BI32: =MIN(BG32:BH32) -> 2287.6712 | BJ32: =IF(B32<=Jaargegevens!$M$7,Calculator!$S$49,AH32+Jaargegevens!S34+Jaargegevens!J34) -> 0.24819535 | BL32: =IF(Calculator!$R$118<=B32,Keuzemenu!$I$18,Keuzemenu!$I$17) -> Ja | BM32: =Jaargegevens!AB34 -> 14 | BN32: =IF(Calculator!R$102/4<Q32,Calculator!R$102*(BM32/60),Q32) -> 2.3333333 | BO32: =IF(BL32="Ja",365*24*4*BN32,0)*D5 -> 74816 | BP32: =MAX(0,BH32-BE32-BI32) -> 1872.2395 | BQ32: =MAX(0,MIN(BO32:BP32)) -> 1872.2395 | BR32: =AF32 -> 0.14700636 | BS32: =Jaargegevens!R34+Jaargegevens!AD34+Jaargegevens!J34 -> 0.44819535 | BT32: =BS32-BR32 -> 0.301189 | BU32: =Jaargegevens!AF34 -> 0.85 | BV32: =BT32*BU32 -> 0.25601065 | BX32: =-(((1-I32)*R32)*(BR32+BV32)) -> -118.69093 | BY32: =(BE32*(AJ32-AF32)) -> 677.85665 | BZ32: =BC32*BJ32 -> 567.78937 | CA32: =BQ32*BV32 -> 479.31324 | CB32: =CN32 -> 0 | CC32: =U32-V32 -> 54.50778 | CD32: =ROUND(SUM(BX32:CC32),0) -> 1661 | CE32: =IF(CD32<>"",SUM(CD$12:CD32),"") -> 34907 | CH32: =R32 -> 7362.6504 | CI32: =BC32 -> 2287.6712 | CJ32: =CH32-CI32 -> 5074.9792 | CK32: =Jaargegevens!G34 -> 10000 | CL32: =MAX(CJ32-CK32,0) -> 0 | CM32: =Jaargegevens!F34-Jaargegevens!H34 -> 0.02652 | CN32: =CL32*CM32 -> 0 | CP32: =R32 -> 7362.6504 | CQ32: =BC32 -> 2287.6712 | CR32: =CP32-CQ32 -> 5074.9792 | CS32: =AF32 -> 0.14700636 | CT32: =CR32*CS32 -> 746.05421 | CV32: =CP32 -> 7362.6504 | CW32: =(1-I32)*CV32 -> 294.50602 | CX32: =CV32-CW32 -> 7068.1444 | CY32: =AY32 -> 3202.7397 | CZ32: =AJ32 -> 0.35865535 | DA32: =CY32*CZ32 -> 1148.6798 | DB32: =CQ32 -> 2287.6712 | DC32: =BJ32 -> 0.24819535 | DD32: =DB32*DC32 -> 567.78937 | DE32: =IF(CX32-CY32-DB32>0,CX32-CY32-DB32,0) -> 1577.7335 | DF32: =BR32+BV32 -> 0.403017 | DG32: =DE32*DF32 -> 635.85342 | DH32: =DA32+DD32+DG32 -> 2352.3225 | DJ32: =DH32-CT32 -> 1606.2683 | DK32: =CB32 -> 0 | DL32: =CC32 -> 54.50778 | DN32: =ROUND(SUM(DI32:DM32),0) -> 1661
BX34: =SUM(BX12:BX33) -> -2768.0357 | BY34: =SUM(BY12:BY33) -> 11526.506 | BZ34: =SUM(BZ12:BZ33) -> 9880.7341 | CA34: =SUM(CA12:CA33) -> 15318.258 | CB34: =SUM(CB12:CB33) -> 0 | CC34: =SUM(CC12:CC33) -> 949.70247 | CD34: =SUM(CD12:CD33) -> 34907 | CN34: =SUM(CN12:CN33) -> 0 | CT34: =SUM(CT12:CT33) -> 20157.449 | DH34: =SUM(DH12:DH33) -> 54114.911 | DJ34: =SUM(DJ12:DJ33) -> 33957.462 | DK34: =SUM(DK12:DK33) -> 0 | DL34: =SUM(DL12:DL33) -> 949.70247 | DN34: =SUM(DN12:DN33) -> 34906.782
AV35: =IF(AT32="Nee",0,IF(AT28="Ja",1,0)) -> 0 | BO35: Voor zelfconsumptie en Teruglevering vanuit PV mag de batterij maar 1 cycle per dag gebruiken.
BO36: De restcapaciteit boven 1 cycle per dag wordt in eerste instantie gebruikt voor opslag PV en teruglevering.
BO37: De restacapaciteit daarboven mag gebruikt worden voor handelen

Sheet Kosten
B1: Kosten | J1: looptijd financiering | K1: looptijd financiering | M1: =Calculator!R167*12 -> 120 | N1: Rente-% | O1: =Calculator!R169+0.0000000001 -> 0.066
B3: Periode | E3: Inflatie | H3: Aankoop | M3: Financiering | T3: Overige kosten | X3: Kosten
B4: Jaar | C4: beginmaand | E4: Inflatie (jaar) | F4: Inflatie (maand) | H4: Aankoop | I4: Bijkomende kosten | J4: BTW teruggave | K4: Aankoop netto | M4: Leensom | N4: Bruto | O4: Rente per jaar | P4: Aflossing per jaar | Q4: Teruggave | R4: Netto | T4: Onderhoud | U4: Overstapboete | V4: Zwaardere aansluiting | X4: Kosten periode | Y4: Kosten Cumulatief
B6: =Jaargegevens!A14 -> 2025 | C6: =IF(Jaargegevens!F3>12,0,1) -> 0 | E6: =Jaargegevens!D14 -> 0.032 | H6: =Calculator!R125+Calculator!R127 -> 14999 | I6: =SUM(Calculator!R129,Calculator!R131,Calculator!R133) -> 0 | J6: =BTW!V10 -> 2102 | K6: =H6+I6-J6 -> 12897 | M6: =Calculator!$R$165+0.000001 -> 1e-06 | N6: =IF(C6=0,0,(C7-C6)*Calculator!$S$176) -> 0 | O6: =IF(C6=0,0,IF(C6-1<$M$1,-CUMIPMT((1+EFFECT($O$1,12))^(1/12)-1,$M$1,$M$6,C6,C7-1,0),0)) -> 0 | P6: =IF(C6-1<$M$1,N6-O6,0) -> 0 | Q6: =Calculator!$R$171*Kosten!O6 -> 0 | R6: =N6-Q6 -> 0 | U6: =Calculator!R133 -> 0 | V6: =Calculator!$R$158 -> 0 | X6: =IF(K6-M6+R6+T6+U6+V6>0,K6-M6+R6+T6+U6+V6,0) -> 12897 | Y6: =SUM(K$6:K6)-SUM(M$6:M6)+SUM(R$6:R6)+SUM(T$6:T6)+SUM(V$6:V6) -> 12897
B7: =Jaargegevens!A15 -> 2026 | C7: =12-Jaargegevens!F3+2 -> 1 | E7: =Jaargegevens!D15 -> 0.028 | H7: 0 | J7: =(IF(BTW!$X$11>=B7,-BTW!$V$11,0)) -> 0 | K7: =H7-J7 -> 0 | N7: =(C8-C7)*Calculator!$S$176 -> 0 | O7: =IF(C7-1<$M$1,-CUMIPMT((1+EFFECT($O$1,12))^(1/12)-1,$M$1,$M$6,C7,C8-1,0),0) -> 6.3816422e-08 | P7: =IF(C7-1<$M$1,N7-O7,0) -> -6.3816422e-08 | Q7: =Calculator!$R$171*Kosten!O7 -> 2.3592931e-08 | R7: =N7-Q7 -> -2.3592931e-08 | T7: =Calculator!R160 -> 0 | U7: 0 | V7: =V6*(1+E6) -> 0 | X7: =IF(K7-M7+R7+T7+U7+V7>0,K7-M7+R7+T7+U7+V7,0) -> 0 | Y7: =SUM(K$6:K7)-SUM(M$6:M7)+SUM(R$6:R7)+SUM(T$6:T7)+SUM(V$6:V7) -> 12897
B8: =Jaargegevens!A16 -> 2027 | C8: =MIN($M$1+1,C7+12) -> 13 | E8: =Jaargegevens!D16 -> 0.025 | H8: 0 | J8: =(IF(BTW!$X$11>=B8,-BTW!$V$11,0)) -> 0 | K8: =H8-J8 -> 0 | N8: =(C9-C8)*Calculator!$S$176 -> 0 | O8: =IF(C8-1<$M$1,-CUMIPMT((1+EFFECT($O$1,12))^(1/12)-1,$M$1,$M$6,C8,C9-1,0),0) -> 5.8846399e-08 | P8: =IF(C8-1<$M$1,N8-O8,0) -> -5.8846399e-08 | Q8: =Calculator!$R$171*Kosten!O8 -> 2.1755514e-08 | R8: =N8-Q8 -> -2.1755514e-08 | T8: =T7*(1+E7) -> 0 | U8: 0 | V8: =V7*(1+E7) -> 0 | X8: =IF(K8-M8+R8+T8+U8+V8>0,K8-M8+R8+T8+U8+V8,0) -> 0 | Y8: =SUM(K$6:K8)-SUM(M$6:M8)+SUM(R$6:R8)+SUM(T$6:T8)+SUM(V$6:V8) -> 12897
B9: =Jaargegevens!A17 -> 2028 | C9: =MIN($M$1+1,C8+12) -> 25 | E9: =Jaargegevens!D17 -> 0.025 | H9: 0 | J9: =(IF(BTW!$X$11>=B9,-BTW!$V$11,0)) -> 0 | K9: =H9-J9 -> 0 | N9: =(C10-C9)*Calculator!$S$176 -> 0 | O9: =IF(C9-1<$M$1,-CUMIPMT((1+EFFECT($O$1,12))^(1/12)-1,$M$1,$M$6,C9,C10-1,0),0) -> 5.3538249e-08 | P9: =IF(C9-1<$M$1,N9-O9,0) -> -5.3538249e-08 | Q9: =Calculator!$R$171*Kosten!O9 -> 1.9793091e-08 | R9: =N9-Q9 -> -1.9793091e-08 | T9: =T8*(1+E8) -> 0 | U9: 0 | V9: =V8*(1+E8) -> 0 | X9: =IF(K9-M9+R9+T9+U9+V9>0,K9-M9+R9+T9+U9+V9,0) -> 0 | Y9: =SUM(K$6:K9)-SUM(M$6:M9)+SUM(R$6:R9)+SUM(T$6:T9)+SUM(V$6:V9) -> 12897
B10: =Jaargegevens!A18 -> 2029 | C10: =MIN($M$1+1,C9+12) -> 37 | E10: =Jaargegevens!D18 -> 0.025 | H10: 0 | J10: =(IF(BTW!$X$11>=B10,-BTW!$V$11,0)) -> 0 | K10: =H10-J10 -> 0 | N10: =(C11-C10)*Calculator!$S$176 -> 0 | O10: =IF(C10-1<$M$1,-CUMIPMT((1+EFFECT($O$1,12))^(1/12)-1,$M$1,$M$6,C10,C11-1,0),0) -> 4.7868966e-08 | P10: =IF(C10-1<$M$1,N10-O10,0) -> -4.7868966e-08 | Q10: =Calculator!$R$171*Kosten!O10 -> 1.7697157e-08 | R10: =N10-Q10 -> -1.7697157e-08 | T10: =T9*(1+E9) -> 0 | U10: 0 | V10: =V9*(1+E9) -> 0 | X10: =IF(K10-M10+R10+T10+U10+V10>0,K10-M10+R10+T10+U10+V10,0) -> 0 | Y10: =SUM(K$6:K10)-SUM(M$6:M10)+SUM(R$6:R10)+SUM(T$6:T10)+SUM(V$6:V10) -> 12897
B11: =Jaargegevens!A19 -> 2030 | C11: =MIN($M$1+1,C10+12) -> 49 | E11: =Jaargegevens!D19 -> 0.025 | H11: 0 | J11: =(IF(BTW!$X$11>=B11,-BTW!$V$11,0)) -> 0 | K11: =H11-J11 -> 0 | N11: =(C12-C11)*Calculator!$S$176 -> 0 | O11: =IF(C11-1<$M$1,-CUMIPMT((1+EFFECT($O$1,12))^(1/12)-1,$M$1,$M$6,C11,C12-1,0),0) -> 4.1813981e-08 | P11: =IF(C11-1<$M$1,N11-O11,0) -> -4.1813981e-08 | Q11: =Calculator!$R$171*Kosten!O11 -> 1.5458629e-08 | R11: =N11-Q11 -> -1.5458629e-08 | T11: =T10*(1+E10) -> 0 | U11: 0 | V11: =V10*(1+E10) -> 0 | X11: =IF(K11-M11+R11+T11+U11+V11>0,K11-M11+R11+T11+U11+V11,0) -> 0 | Y11: =SUM(K$6:K11)-SUM(M$6:M11)+SUM(R$6:R11)+SUM(T$6:T11)+SUM(V$6:V11) -> 12897
B12: =Jaargegevens!A20 -> 2031 | C12: =MIN($M$1+1,C11+12) -> 61 | E12: =Jaargegevens!D20 -> 0.025 | H12: 0 | J12: =(IF(BTW!$X$11>=B12,-BTW!$V$11,0)) -> 0 | K12: =H12-J12 -> 0 | N12: =(C13-C12)*Calculator!$S$176 -> 0 | O12: =IF(C12-1<$M$1,-CUMIPMT((1+EFFECT($O$1,12))^(1/12)-1,$M$1,$M$6,C12,C13-1,0),0) -> 3.5347055e-08 | P12: =IF(C12-1<$M$1,N12-O12,0) -> -3.5347055e-08 | Q12: =Calculator!$R$171*Kosten!O12 -> 1.3067806e-08 | R12: =N12-Q12 -> -1.3067806e-08 | T12: =T11*(1+E11) -> 0 | U12: 0 | V12: =V11*(1+E11) -> 0 | X12: =IF(K12-M12+R12+T12+U12+V12>0,K12-M12+R12+T12+U12+V12,0) -> 0 | Y12: =SUM(K$6:K12)-SUM(M$6:M12)+SUM(R$6:R12)+SUM(T$6:T12)+SUM(V$6:V12) -> 12897
B13: =Jaargegevens!A21 -> 2032 | C13: =MIN($M$1+1,C12+12) -> 73 | E13: =Jaargegevens!D21 -> 0.025 | H13: 0 | J13: =(IF(BTW!$X$11>=B13,-BTW!$V$11,0)) -> 0 | K13: =H13-J13 -> 0 | N13: =(C14-C13)*Calculator!$S$176 -> 0 | O13: =IF(C13-1<$M$1,-CUMIPMT((1+EFFECT($O$1,12))^(1/12)-1,$M$1,$M$6,C13,C14-1,0),0) -> 2.844016e-08 | P13: =IF(C13-1<$M$1,N13-O13,0) -> -2.844016e-08 | Q13: =Calculator!$R$171*Kosten!O13 -> 1.0514327e-08 | R13: =N13-Q13 -> -1.0514327e-08 | T13: =T12*(1+E12) -> 0 | U13: 0 | V13: =V12*(1+E12) -> 0 | X13: =IF(K13-M13+R13+T13+U13+V13>0,K13-M13+R13+T13+U13+V13,0) -> 0 | Y13: =SUM(K$6:K13)-SUM(M$6:M13)+SUM(R$6:R13)+SUM(T$6:T13)+SUM(V$6:V13) -> 12897
B14: =Jaargegevens!A22 -> 2033 | C14: =MIN($M$1+1,C13+12) -> 85 | E14: =Jaargegevens!D22 -> 0.025 | H14: 0 | J14: =(IF(BTW!$X$11>=B14,-BTW!$V$11,0)) -> 0 | K14: =H14-J14 -> 0 | N14: =(C15-C14)*Calculator!$S$176 -> 0 | O14: =IF(C14-1<$M$1,-CUMIPMT((1+EFFECT($O$1,12))^(1/12)-1,$M$1,$M$6,C14,C15-1,0),0) -> 2.1063365e-08 | P14: =IF(C14-1<$M$1,N14-O14,0) -> -2.1063365e-08 | Q14: =Calculator!$R$171*Kosten!O14 -> 7.7871259e-09 | R14: =N14-Q14 -> -7.7871259e-09 | T14: =T13*(1+E13) -> 0 | U14: 0 | V14: =V13*(1+E13) -> 0 | X14: =IF(K14-M14+R14+T14+U14+V14>0,K14-M14+R14+T14+U14+V14,0) -> 0 | Y14: =SUM(K$6:K14)-SUM(M$6:M14)+SUM(R$6:R14)+SUM(T$6:T14)+SUM(V$6:V14) -> 12897
B15: =Jaargegevens!A23 -> 2034 | C15: =MIN($M$1+1,C14+12) -> 97 | E15: =Jaargegevens!D23 -> 0.025 | H15: 0 | J15: =(IF(BTW!$X$11>=B15,-BTW!$V$11,0)) -> 0 | K15: =H15-J15 -> 0 | N15: =(C16-C15)*Calculator!$S$176 -> 0 | O15: =IF(C15-1<$M$1,-CUMIPMT((1+EFFECT($O$1,12))^(1/12)-1,$M$1,$M$6,C15,C16-1,0),0) -> 1.31847e-08 | P15: =IF(C15-1<$M$1,N15-O15,0) -> -1.31847e-08 | Q15: =Calculator!$R$171*Kosten!O15 -> 4.8743834e-09 | R15: =N15-Q15 -> -4.8743834e-09 | T15: =T14*(1+E14) -> 0 | U15: 0 | V15: =V14*(1+E14) -> 0 | X15: =IF(K15-M15+R15+T15+U15+V15>0,K15-M15+R15+T15+U15+V15,0) -> 0 | Y15: =SUM(K$6:K15)-SUM(M$6:M15)+SUM(R$6:R15)+SUM(T$6:T15)+SUM(V$6:V15) -> 12897
B16: =Jaargegevens!A24 -> 2035 | C16: =MIN($M$1+1,C15+12) -> 109 | E16: =Jaargegevens!D24 -> 0.025 | H16: 0 | J16: =(IF(BTW!$X$11>=B16,-BTW!$V$11,0)) -> 0 | K16: =H16-J16 -> 0 | N16: =(C17-C16)*Calculator!$S$176 -> 0 | O16: =IF(C16-1<$M$1,-CUMIPMT((1+EFFECT($O$1,12))^(1/12)-1,$M$1,$M$6,C16,C17-1,0),0) -> 4.770021e-09 | P16: =IF(C16-1<$M$1,N16-O16,0) -> -4.770021e-09 | Q16: =Calculator!$R$171*Kosten!O16 -> 1.7634768e-09 | R16: =N16-Q16 -> -1.7634768e-09 | T16: =T15*(1+E15) -> 0 | U16: 0 | V16: =V15*(1+E15) -> 0 | X16: =IF(K16-M16+R16+T16+U16+V16>0,K16-M16+R16+T16+U16+V16,0) -> 0 | Y16: =SUM(K$6:K16)-SUM(M$6:M16)+SUM(R$6:R16)+SUM(T$6:T16)+SUM(V$6:V16) -> 12897
B17: =Jaargegevens!A25 -> 2036 | C17: =MIN($M$1+1,C16+12) -> 121 | E17: =Jaargegevens!D25 -> 0.025 | H17: 0 | J17: =(IF(BTW!$X$11>=B17,-BTW!$V$11,0)) -> 0 | K17: =H17-J17 -> 0 | N17: =(C18-C17)*Calculator!$S$176 -> 0 | O17: =IF(C17-1<$M$1,-CUMIPMT((1+EFFECT($O$1,12))^(1/12)-1,$M$1,$M$6,C17,C18-1,0),0) -> 0 | P17: =IF(C17-1<$M$1,N17-O17,0) -> 0 | Q17: =Calculator!$R$171*Kosten!O17 -> 0 | R17: =N17-Q17 -> 0 | T17: =T16*(1+E16) -> 0 | U17: 0 | V17: =V16*(1+E16) -> 0 | X17: =IF(K17-M17+R17+T17+U17+V17>0,K17-M17+R17+T17+U17+V17,0) -> 0 | Y17: =SUM(K$6:K17)-SUM(M$6:M17)+SUM(R$6:R17)+SUM(T$6:T17)+SUM(V$6:V17) -> 12897
B18: =Jaargegevens!A26 -> 2037 | C18: =MIN($M$1+1,C17+12) -> 121 | E18: =Jaargegevens!D26 -> 0.025 | H18: 0 | J18: =(IF(BTW!$X$11>=B18,-BTW!$V$11,0)) -> 0 | K18: =H18-J18 -> 0 | N18: =(C19-C18)*Calculator!$S$176 -> 0 | O18: =IF(C18-1<$M$1,-CUMIPMT((1+EFFECT($O$1,12))^(1/12)-1,$M$1,$M$6,C18,C19-1,0),0) -> 0 | P18: =IF(C18-1<$M$1,N18-O18,0) -> 0 | Q18: =Calculator!$R$171*Kosten!O18 -> 0 | R18: =N18-Q18 -> 0 | T18: =T17*(1+E17) -> 0 | U18: 0 | V18: =V17*(1+E17) -> 0 | X18: =IF(K18-M18+R18+T18+U18+V18>0,K18-M18+R18+T18+U18+V18,0) -> 0 | Y18: =SUM(K$6:K18)-SUM(M$6:M18)+SUM(R$6:R18)+SUM(T$6:T18)+SUM(V$6:V18) -> 12897
B19: =Jaargegevens!A27 -> 2038 | C19: =MIN($M$1+1,C18+12) -> 121 | E19: =Jaargegevens!D27 -> 0.025 | H19: 0 | J19: =(IF(BTW!$X$11>=B19,-BTW!$V$11,0)) -> 0 | K19: =H19-J19 -> 0 | N19: =(C20-C19)*Calculator!$S$176 -> 0 | O19: =IF(C19-1<$M$1,-CUMIPMT((1+EFFECT($O$1,12))^(1/12)-1,$M$1,$M$6,C19,C20-1,0),0) -> 0 | P19: =IF(C19-1<$M$1,N19-O19,0) -> 0 | Q19: =Calculator!$R$171*Kosten!O19 -> 0 | R19: =N19-Q19 -> 0 | T19: =T18*(1+E18) -> 0 | U19: 0 | V19: =V18*(1+E18) -> 0 | X19: =IF(K19-M19+R19+T19+U19+V19>0,K19-M19+R19+T19+U19+V19,0) -> 0 | Y19: =SUM(K$6:K19)-SUM(M$6:M19)+SUM(R$6:R19)+SUM(T$6:T19)+SUM(V$6:V19) -> 12897
... B21: =Jaargegevens!A29 -> 2040 | C21: =MIN($M$1+1,C20+12) -> 121 | E21: =Jaargegevens!D29 -> 0.025 | H21: 0 | J21: =(IF(BTW!$X$11>=B21,-BTW!$V$11,0)) -> 0 | K21: =H21-J21 -> 0 | N21: =(C22-C21)*Calculator!$S$176 -> 0 | O21: =IF(C21-1<$M$1,-CUMIPMT((1+EFFECT($O$1,12))^(1/12)-1,$M$1,$M$6,C21,C22-1,0),0) -> 0 | P21: =IF(C21-1<$M$1,N21-O21,0) -> 0 | Q21: =Calculator!$R$171*Kosten!O21 -> 0 | R21: =N21-Q21 -> 0 | T21: =T20*(1+E20) -> 0 | U21: 0 | V21: =V20*(1+E20) -> 0 | X21: =IF(K21-M21+R21+T21+U21+V21>0,K21-M21+R21+T21+U21+V21,0) -> 0 | Y21: =SUM(K$6:K21)-SUM(M$6:M21)+SUM(R$6:R21)+SUM(T$6:T21)+SUM(V$6:V21) -> 12897
B22: =Jaargegevens!A30 -> 2041 | C22: =MIN($M$1+1,C21+12) -> 121 | E22: =Jaargegevens!D30 -> 0.025 | H22: 0 | J22: =(IF(BTW!$X$11>=B22,-BTW!$V$11,0)) -> 0 | K22: =H22-J22 -> 0 | N22: =(C23-C22)*Calculator!$S$176 -> 0 | O22: =IF(C22-1<$M$1,-CUMIPMT((1+EFFECT($O$1,12))^(1/12)-1,$M$1,$M$6,C22,C23-1,0),0) -> 0 | P22: =IF(C22-1<$M$1,$N$6-O22,0) -> 0 | Q22: =Calculator!$R$171*Kosten!O22 -> 0 | R22: =N22-Q22 -> 0 | T22: =T21*(1+E21) -> 0 | U22: 0 | V22: =V21*(1+E21) -> 0 | X22: =IF(K22-M22+R22+T22+U22+V22>0,K22-M22+R22+T22+U22+V22,0) -> 0 | Y22: =SUM(K$6:K22)-SUM(M$6:M22)+SUM(R$6:R22)+SUM(T$6:T22)+SUM(V$6:V22) -> 12897
B23: =Jaargegevens!A31 -> 2042 | C23: =MIN($M$1+1,C22+12) -> 121 | E23: =Jaargegevens!D31 -> 0.025 | H23: 0 | J23: =(IF(BTW!$X$11>=B23,-BTW!$V$11,0)) -> 0 | K23: =H23-J23 -> 0 | N23: =(C24-C23)*Calculator!$S$176 -> 0 | O23: =IF(C23-1<$M$1,-CUMIPMT((1+EFFECT($O$1,12))^(1/12)-1,$M$1,$M$6,C23,C24-1,0),0) -> 0 | P23: =IF(C23-1<$M$1,$N$6-O23,0) -> 0 | Q23: =Calculator!$R$171*Kosten!O23 -> 0 | R23: =N23-Q23 -> 0 | T23: =T22*(1+E22) -> 0 | U23: 0 | V23: =V22*(1+E22) -> 0 | X23: =IF(K23-M23+R23+T23+U23+V23>0,K23-M23+R23+T23+U23+V23,0) -> 0 | Y23: =SUM(K$6:K23)-SUM(M$6:M23)+SUM(R$6:R23)+SUM(T$6:T23)+SUM(V$6:V23) -> 12897
B24: =Jaargegevens!A32 -> 2043 | C24: =MIN($M$1+1,C23+12) -> 121 | E24: =Jaargegevens!D32 -> 0.025 | H24: 0 | J24: =(IF(BTW!$X$11>=B24,-BTW!$V$11,0)) -> 0 | K24: =H24-J24 -> 0 | N24: =(C25-C24)*Calculator!$S$176 -> 0 | O24: =IF(C24-1<$M$1,-CUMIPMT((1+EFFECT($O$1,12))^(1/12)-1,$M$1,$M$6,C24,C25-1,0),0) -> 0 | P24: =IF(C24-1<$M$1,$N$6-O24,0) -> 0 | Q24: =Calculator!$R$171*Kosten!O24 -> 0 | R24: =N24-Q24 -> 0 | T24: =T23*(1+E23) -> 0 | U24: 0 | V24: =V23*(1+E23) -> 0 | X24: =IF(K24-M24+R24+T24+U24+V24>0,K24-M24+R24+T24+U24+V24,0) -> 0 | Y24: =SUM(K$6:K24)-SUM(M$6:M24)+SUM(R$6:R24)+SUM(T$6:T24)+SUM(V$6:V24) -> 12897
B25: =Jaargegevens!A33 -> 2044 | C25: =MIN($M$1+1,C24+12) -> 121 | E25: =Jaargegevens!D33 -> 0.025 | H25: 0 | J25: =(IF(BTW!$X$11>=B25,-BTW!$V$11,0)) -> 0 | K25: =H25-J25 -> 0 | N25: =(C26-C25)*Calculator!$S$176 -> 0 | O25: =IF(C25-1<$M$1,-CUMIPMT((1+EFFECT($O$1,12))^(1/12)-1,$M$1,$M$6,C25,C26-1,0),0) -> 0 | P25: =IF(C25-1<$M$1,$N$6-O25,0) -> 0 | Q25: =Calculator!$R$171*Kosten!O25 -> 0 | R25: =N25-Q25 -> 0 | T25: =T24*(1+E24) -> 0 | U25: 0 | V25: =V24*(1+E24) -> 0 | X25: =IF(K25-M25+R25+T25+U25+V25>0,K25-M25+R25+T25+U25+V25,0) -> 0 | Y25: =SUM(K$6:K25)-SUM(M$6:M25)+SUM(R$6:R25)+SUM(T$6:T25)+SUM(V$6:V25) -> 12897
B26: =Jaargegevens!A34 -> 2045 | C26: =MIN($M$1+1,C25+12) -> 121 | E26: =Jaargegevens!D34 -> 0.025 | H26: 0 | J26: =(IF(BTW!$X$11>=B26,-BTW!$V$11,0)) -> 0 | K26: =H26-J26 -> 0 | N26: =(C27-C26)*Calculator!$S$176 -> 0 | O26: 0 | P26: =IF(C26-1<$M$1,$N$6-O26,0) -> 0 | Q26: =Calculator!$R$171*Kosten!O26 -> 0 | R26: =N26-Q26 -> 0 | U26: 0 | V26: =V25*(1+E25) -> 0 | X26: =K26+R26+T26+U26+V26 -> 0 | Y26: =SUM(K$6:K26)-SUM(M$6:M26)+SUM(R$6:R26)+SUM(T$6:T26)+SUM(V$6:V26) -> 12897
C27: =MIN($M$1+1,C25+12) -> 121
H29: =SUM(H6:H28) -> 14999 | I29: =SUM(I6:I28) -> 0 | J29: =SUM(J6:J28) -> 2102 | K29: =SUM(K6:K28) -> 12897 | M29: =SUM(M6:M28) -> 1e-06 | N29: =SUM(N6:N28) -> 0 | O29: =SUM(O6:O28) -> 3.6868932e-07 | P29: =SUM(P6:P28) -> -3.6868932e-07 | Q29: =SUM(Q6:Q28) -> 1.3630444e-07 | R29: =SUM(R6:R28) -> -1.3630444e-07 | T29: =SUM(T6:T28) -> 0 | V29: =SUM(V6:V28) -> 0 | X29: =SUM(X6:X28) -> 12897
